Workbook

Sheet Leyenda
A1: Revisión de los errores de 1920 contra el Libro de Mormón de 1946
A3: Hoja "Errores": una fila por cada error registrado en "errors in 1920.txt", en el orden del libro (preliminares, 1 Nefi ... Moroni). Las entradas FAMILIA se desglosan en sus instancias (columna Familia).
A4: Columnas que usted llena (fondo amarillo):
A5: P 1946: ¿qué dice? -- lista: igual que 1920 / corregido / otro cambio / no encontrado / no se puede leer
A6: Q 1946: lectura / nota -- lo que imprime 1946, si difiere, o cualquier observación
A7: R Decisión Gutenberg 1920 (_cleaned) -- lista: corregir / mantener / pendiente / ver comentario
A8: S Decisión versión moderna -- lista: modernizar / mantener / pendiente / ver comentario
A9: T Comentarios -- texto libre
A10: Las listas son una ayuda: puede escribir otra cosa en cualquier celda amarilla.
A12: Ejemplo de una fila llenada (formato esperado):
A13: Alma 36:20 | Lectura 1920: "Biblía" | 1946: corregido | Lectura/nota: "Biblia" | Gutenberg: corregir | Moderna: modernizar | Comentarios: 1946 lo corrige
A15: Columna N "Aviso": "instancia extraída ... verificar" = fila generada a partir del texto de una FAMILIA; puede ser una cita de comparación y no un error -- basta con marcarla "no encontrado" o anotarlo. "ubicación aproximada" = la entrada no tiene referencia exacta.
... A19: Avance
A20: Filas en total | B20: =COUNTA(Errores!A2:A2187)
A21: Filas con lectura de 1946 | B21: =COUNTA(Errores!P2:P2187)
A22: de ellas "corregido" | B22: =COUNTIF(Errores!P2:P2187,"corregido")
A23: de ellas "igual que 1920" | B23: =COUNTIF(Errores!P2:P2187,"igual que 1920")
A24: Filas con decisión Gutenberg | B24: =COUNTA(Errores!R2:R2187)
A25: Filas con decisión moderna | B25: =COUNTA(Errores!S2:S2187)
A27: Hoja "Familias", columnas D-F (añadidas 2026-10-18):
A28: D versículos sugeridos (unos 5 repartidos por el libro) para mirar en 1946
A29: E resultado: corrige todos / mantiene todos / mixto / no encontrado
A30: F nota libre. Si las 5 coinciden, no hace falta mirar las demás filas de esa familia en "Errores".

Sheet Errores
A1: # | B1: Libro | C1: Cap. | D1: Vers. | E1: Pág. 1920 | F1: Lugar | G1: Nota (n.º / clave) | H1: Lectura 1920 | I1: Forma correcta | J1: Tipo | K1: 1886 (según el registro) | L1: Familia | M1: Propuesta _cleaned ya registrada | N1: Aviso | O1: Línea en el registro | P1: 1946: ¿qué dice? | Q1: 1946: lectura / nota | R1: Decisión Gutenberg 1920 (_cleaned) | S1: Decisión versión moderna | T1: Comentarios | U1: Entrada completa del registro
A2: 1 | B2: Preliminares | E2: iii | F2: portada | H2: revalación | I2: revelación | J2: letra(s) | K2: es correcto en la de 1886 | O2: 2 | P2: corregido | R2: corregir | U2: Página del título iii revalación (revelación) (es correcto en la de 1886)
A3: 2 | B3: Preliminares | E3: iii | F3: portada | H3: Ultimos | I3: Últimos | J3: tilde | K3: transcripción ya coincide con la impresión; 1886 no cotejado | O3: 3 | P3: corregido | R3: corregir | U3: Página del título iii Ultimos (Últimos) (1920 imprime "Santos de los Ultimos Días" sin tilde en la "U" mayúscula, aunque la misma línea acentúa "Días" y la fuente tiene mayúsculas acentuadas; pages_1920/page_0011.png; confirmado en la imagen 2026-10-17 (revisión de variantes de tilde, item 4a); la transcripción ya coincide con la impresión; 1886 no cotejado)
A4: 3 | B4: Preliminares | E4: v | F4: testimonios | H4: Nuestros Señor, Jesucristo | I4: Nuestro Señor, Jesu Cristo | J4: palabra(s)/gramática | K4: de Jesucristo 1886 | O4: 4 | P4: corregido | Q4: de nuestro Señor, Jesucristo | R4: corregir | U4: Testimonios página v Nuestros Señor, Jesucristo (Nuestro Señor, Jesu Cristo)(de Jesucristo 1886)
A5: 4 | B5: Preliminares | E5: v | F5: testimonios | H5: los grabado que | I5: los grabados que | J5: letra(s) | K5: 1886 dice los grabados | O5: 5 | P5: corregido | R5: corregir | U5: Testimonios página v los grabado que (los grabados que) (1886 dice los grabados)
A6: 5 | B6: Preliminares | E6: vii | F6: índice | H6: Sueño de Lahi | I6: Sueño de Lehi | J6: letra(s) | K6: Lehi en 1886 | O6: 6 | P6: no encontrado | Q6: No hay ese tipo de indice | R6: corregir | U6: Indice página vii Sueño de Lahi (Sueño de Lehi) (Lehi en 1886)
A7: 6 | B7: Preliminares | E7: vii | F7: índice | H7: bronze | I7: bronce | J7: letra(s) | K7: bronze en 1886 | O7: 7 | P7: no encontrado | R7: ver comentario | T7: Research usage of bronze | U7: Indice página vii bronze (bronce) 2x (bronze en 1886)
A8: 7 | B8: Preliminares | E8: vii | F8: índice | H8: atras | I8: atrás | J8: tilde | K8: coincide con la impresión; atras también en 1886 | O8: 16 | P8: no encontrado | R8: corregir | U8: Indice página vii atras (atrás) ("el barco es arrojado hacia atras.. 45"; pages_1920/page_0015.png; confirmado en la imagen 2026-10-17 (revisión de variantes de tilde, item 4a); la transcripción ya coincide con la impresión; atras también en 1886)
A9: 8 | B9: Preliminares | E9: viii | F9: índice | H9: Baustismo | I9: Bautismo | J9: letra(s) | K9: Bautismo en 1886 | O9: 8 | P9: no encontrado | R9: corregir | U9: Indice página viii Baustismo (Bautismo) (Bautismo en 1886)
A10: 9 | B10: Preliminares | E10: viii | F10: índice | H10: sobrepajado | I10: sobrepujado | J10: letra(s) | K10: Sobrepujado en 1886 | O10: 9 | P10: no encontrado | R10: corregir | U10: Indice página viii sobrepajado (sobrepujado) (Sobrepujado en 1886)
A11: 10 | B11: Preliminares | E11: viii | F11: índice | H11: Isaias | I11: Isaías | J11: tilde | K11: ción ya coincide con la impresión; Isaías en 1886 | O11: 17 | P11: no encontrado | R11: corregir | U11: Indice página viii Isaias (Isaías) ("Palabras de Isaias (por Jacob).. 75"; pages_1920/page_0016.png; confirmado en la imagen 2026-10-17 (revisión de variantes de tilde, item 4a); la transcripción ya coincide con la impresión; Isaías en 1886)
A12: 11 | B12: Preliminares | E12: viii | F12: índice | H12: Moises | I12: Moisés | J12: tilde | K12: ción ya coincide con la impresión; Moisés en 1886 | O12: 18 | P12: no encontrado | R12: corregir | U12: Indice página viii Moises (Moisés) ("Guardan la ley de Moises.. 111"; pages_1920/page_0016.png; confirmado en la imagen 2026-10-17 (revisión de variantes de tilde, item 4a); la transcripción ya coincide con la impresión; Moisés en 1886)
A13: 12 | B13: Preliminares | E13: ix | F13: índice | H13: prisón | I13: prisión | J13: letra(s) | K13: prision -- no accento en 1886 - intention was to add accent? | O13: 10 | P13: no encontrado | R13: corregir | U13: Indice página ix prisón (prisión) (prision -- no accento en 1886 - intention was to add accent?)
A14: 13 | B14: Preliminares | E14: ix | F14: índice | H14: Lamaitas | I14: Lamanitas | J14: letra(s) | K14: 1886 aún no cotejado para este lugar exacto | O14: 13 | P14: no encontrado | R14: corregir | U14: Indice página ix Lamaitas (Lamanitas) ("Sueño profundo de los Lama-itas.. 218-219" -- falta la "n" justo después del guión de partición de línea "Lama-"; confirmado independientemente en la imagen de 1920 (pages_1920/page_0017.png, zoom) y en la capa de OCR incrustada del propio PDF (que también lee "Lama-" / "itas" sin "n"); segunda aparición del mismo tipo de error que la ya registrada en "Indice página xii Lamaitas" (entrada distinta, página distinta); 1886 aún no cotejado para este lugar exacto; hallado 2026-09-11 durante la revisión del índice -- véase `workspace/diff1920ocr-trans.md`; preservado como se imprime en librodm_transcribed)
A15: 14 | B15: Preliminares | E15: ix | F15: índice | H15: Elderes | I15: Élderes | J15: tilde | K15: oincide con la impresión; Elderes también en 1886 | O15: 19 | P15: no encontrado | R15: corregir | U15: Indice página ix Elderes (Élderes) ("Alma ordena Sacerdotes y Elderes 253"; pages_1920/page_0017.png; confirmado en la imagen 2026-10-17 (revisión de variantes de tilde, item 4a); la transcripción ya coincide con la impresión; Elderes también en 1886; el cuerpo escribe "Élderes" 5 veces)
A16: 15 | B16: Preliminares | E16: x | F16: índice | H16: Restrauración | I16: Restauración | J16: letra(s) | K16: Restauración en 1886 | O16: 11 | P16: no encontrado | R16: corregir | U16: Indice página x Restrauración (Restauración) (Restauración en 1886) (corregida la cita de página 2026-09-11: estaba etiquetada "página ix" por error -- la entrada "Restrauración .. 358" cae en el bloque de librodm.txt bajo el marcador "Página x", no "ix"; confirmado contra la imagen de 1920, pages_1920/page_0018.png)
A17: 16 | B17: Preliminares | E17: x | F17: índice | H17: Zarahemnah | I17: Zerahémnah | J17: letra(s) | K17: frente al cuerpo, no un error de paginación; 1886 aún no cotejado para este lugar exacto | O17: 12 | P17: no encontrado | R17: corregir | U17: Indice página x Zarahemnah (Zerahémnah) ("Discurso de Moroni á Zarahemnah.. 369", entrada del índice de Alma capítulo 44; confirmado contra la imagen de 1920, pages_1920/page_0018.png; el CUERPO del texto (Alma 43-44, en torno a la pág. 369-370) escribe el nombre de este capitán lamanita SIEMPRE "Zerahémnah" -- 17 apariciones, todas idénticas, `grep -c` -- nunca "Zarahemnah"; el índice es la única discrepancia; la referencia de página en sí es correcta -- el discurso de Moroni sí ocurre en la pág. 369 -- se trata de una variante de grafía del índice frente al cuerpo, no un error de paginación; 1886 aún no cotejado para este lugar exacto; hallado 2026-09-11 durante la extensión del cotejo del índice a las 474 entradas -- véase `workspace/diff1920ocr-trans.md`; preservado como se imprime en librodm_transcribed)
A18: 17 | B18: Preliminares | E18: x | F18: índice | H18: jovenes | I18: jóvenes | J18: tilde | K18: ión ya coincide con la impresión; jóvenes en 1886 | O18: 20 | P18: no encontrado | R18: corregir | U18: Indice página x jovenes (jóvenes) ("Los 2000 jovenes hijos de los Ammonitas 400-401"; pages_1920/page_0018.png; confirmado en la imagen 2026-10-17 (revisión de variantes de tilde, item 4a); la transcripción ya coincide con la impresión; jóvenes en 1886)
A19: 18 | B19: Preliminares | E19: xi | F19: índice | H19: Espiritu | I19: Espíritu | J19: tilde | K19: ón ya coincide con la impresión; Espíritu en 1886 | O19: 21 | P19: no encontrado | R19: corregir | U19: Indice página xi Espiritu (Espíritu) ("Nefi llevado por el Espiritu.. 463"; pages_1920/page_0019.png; confirmado en la imagen 2026-10-17 (revisión de variantes de tilde, item 4a); la transcripción ya coincide con la impresión; Espíritu en 1886)
... A21: 20 | B21: Preliminares | E21: xiii | F21: índice | H21: granancia | I21: ganancia | J21: letra(s) | K21: ganancia en 1886 | O21: 15 | P21: no encontrado | R21: corregir | U21: Indice página xiii granancia (ganancia) (ganancia en 1886)
A22: 21 | B22: 1 Nefi | C22: 1 | D22: 2 | E22: 1 | F22: texto | H22: lenguage | I22: lenguaje | J22: familia | K22: pág. 466/467, LIBRO DE HELAMÁN CAPÍTULO 11; 1886 comparte "pillage" en este lugar exacto, pages_18 | L22: -age | M22: -> _cleaned (DECISIÓN DEL EDITOR | O22: 22 | U22: FAMILIA -age (por -aje) -- grafía "-age" arcaica donde el español moderno escribe "-aje". ENTRADA MAESTRA (2026-09-09; consolida las entradas antes dispersas de 1 Nefi 1:2 y 1 Nefi 5:3, ambas "el/este lenguage"). Alcance: "lenguage" 11 apariciones en el cuerpo (`grep -nE "lenguage" librodm_transcribed.txt`) + "lenguage del libro" en el índice (pág. xiii) + "344 días de pasage" en el índice (pág. xiii, entrada de Éther 6:11) + "pillage" 1x en el cuerpo (Helamán 11:25, "Y entregándose al pillage y al asesinato", pág. 466/467, LIBRO DE HELAMÁN CAPÍTULO 11; 1886 comparte "pillage" en este lugar exacto, pages_1886/page_0481.png, book page 463/file 481). Frente a "lenguaje" 3x, "pasaje" 12x y "pillaje/pillajes" 13x en el cuerpo (Helamán 11:25 es la ÚNICA aparición de "pillage" -- 1920 usa "pillaje" en las otras 13). La grafía "-age" (mensage/linage/viage/salvage/lenguage/pasage) fue la NORMA del español hasta que la RAE estandarizó "-aje" (~1815); para 1886/1920 era arcaica pero aún frecuente en imprenta. 1920 ya ha completado el cambio a "-aje" en TODAS las demás palabras (mensaje 22x, viaje 29x, salvaje 5x, linaje 4x, ultraje 2x -- 0 con "-age"), quedando SOLO "lenguage" (su forma de casa dominante, 11:3) y un "pasage" suelto en el índice. 1886: comparte "lenguage" ("lenguage en 1886" en las entradas originales de 1 Nefi 1:2 y 5:3). Atestiguación externa: "-age" en estas palabras = 0 en Quijote / Reina-Valera 1909 NT / Reina-Valera Biblia completa; "lenguaje" Quijote 10, "pasaje" Quijote 10, "pillaje" 1 en Reina-Valera Biblia completa (0 "pillage"). CLASIFICACIÓN: grafía ortográfica arcaica de época (norma pre-1815), compartida con 1886, NO un error tipográfico; edición inconsistente (casi todo "-aje", pero "lenguage" mayoritario). -> _cleaned (DECISIÓN DEL EDITOR): normalizar las apariciones restantes de "-age" a "-aje" (lenguage -> lenguaje; pasage -> pasaje; pillage -> pillaje, forma ya mayoritaria 13:1 en la propia 1920), como regularización de una grafía de época, no como corrección de errores. Preservado como se imprime en librodm_transcribed.
A23: 22 | B23: 1 Nefi | C23: 1 | D23: 9 | E23: 2 | F23: texto | H23: su resplendor era | I23: su resplandor era | J23: letra(s) | K23: resplendor en 1886 | O23: 29 | U23: 1 Nefi 1:9 su resplendor era (su resplandor era) (resplendor en 1886)
A24: 23 | B24: 1 Nefi | C24: 1 | D24: 9 | E24: 2 | F24: texto | H24: ("él" por "el") | I24: (ver la entrada de la familia) | J24: familia | K24: . 1886: el texto OCR del PDF de 1886 | L24: "él" por "el" | M24: _cleaned`, normalizar a "el" sin tilde | N24: forma no hallada en este versículo: quizá cita de comparación, no error -- verificar | O24: 85 | U24: FAMILIA "él" por "el" (artículo acentuado como pronombre ante "de"/"que") -- ENTRADA MAESTRA (2026-09-23, abierta durante el `manual-proofread` de Alma 43; consolida las entradas antes sueltas de Alma 40:6, Mormón 6:21 y Éther 12:38). 1920 imprime sistemáticamente con tilde el ARTÍCULO "el" cuando va ante "de"/"del" (sustantivo elidido: "mayor que él de los Nefitas" = "mayor que el [número] de los Nefitas"; "y él de su familia" = "y el [corazón] de su familia") o ante el relativo "que" ("en él que" = "en el que", "él que busque, halla" = "el que busque, halla", aposición "José, él que fué llevado"). Según la RAE (tilde diacrítica: "él" pronombre personal tónico / "el" artículo átono), en todas estas posiciones corresponde "el" SIN tilde; la forma con tilde leída literalmente significa "él" (he/him), lo que rompe la gramática. Clasificación del editor (2026-09-23): "gringismo" -- error de un hablante de español como segunda lengua (probable calco de "he that..." / "that of..." del inglés), no una variante de época: no se halló ninguna fuente normativa ni histórica que lo avale, y la ortografía académica del siglo XIX ya distinguía "él"/"el". Alcance: 156 apariciones en el cuerpo de librodm.txt (ninguna en los bloques de notas), frente a 0 apariciones del artículo sin tilde en estas mismas construcciones ("el de " 0x; "en el que" 0x; los únicos "el que" sin tilde son del tipo nominalizador "el que + subjuntivo", p.ej. "me aflige el que se levanten", construcción distinta). Excluidas deliberadamente ~29 apariciones de "él" que SÍ son pronombre personal correcto ("hizo él que", "sabía él que", "mandóles él que", "deseando de él que", "contra él de la manera", "trataba él de destruir", etc.). Verificación: las 156 confirmadas independientemente contra el texto OCR de Google del PDF de 1920 (google_text_1920/), que lee "él" en todas; imágenes cotejadas a zoom en Alma 43:21 (pages_1920/page_0387.png) y Alma 62:6 (page_0449.png). 1886: el texto OCR del PDF de 1886 (localizado por página vía chapter_map.csv) lee "el" sin tilde en ~141 de las 156 posiciones; ~5 las lee con tilde (1 Nefi 7:5, Mosíah 18:27, III Nefi 4:17, III Nefi 29:7, Mormón 9:17 -- sin verificar contra imagen) y el resto quedan indeterminadas (redacción distinta u OCR ilegible). Conteo global en 1886: "en el que" 22x vs "en él que" 1x; "mayor que el de" 4x vs 0x. Imagen de 1886 cotejada en Alma 40:6 y 40:9 (pages_1886/page_0371.png: "y el de la resurreccion" en ambos -- corrige la entrada suelta anterior de Alma 40:6, que decía "él de en 1886"), Alma 43:21 (page_0380.png, "el de los Nefitas") y Alma 62:6 (page_0442.png, "el de los partidarios"). Conclusión: la forma con tilde es, en esencia, EXCLUSIVA DE 1920; 1886 usa el artículo correcto. Edición moderna en español (churchofjesuschrist.org, cotejada 2026-09-23): Alma 43:21 "mucho mayor que el de los nefitas"; Alma 40:6 "y el de la resurrección"; Éter 12:38 y Alma 62:6 reformulados sin la construcción. Subgrupo dudoso (anotado, no exclui
A25: 24 | B25: 1 Nefi | C25: 1 | D25: 12 | E25: 2 | F25: texto | H25: el Espíritu de Señor | I25: el Espíritu del Señor | J25: letra(s) | K25: 1886 en este lugar exacto | M25: -> _cleaned: corregir a "del Señor" | O25: 30 | U25: 1 Nefi 1:12 el Espíritu de Señor (el Espíritu del Señor) (1920 imprime "él se llenó del Espíritu de Señor," -- falta la "l" de "del" antes de "Señor" --, página 2; confirmado a zoom en alta resolución (pages_1920/page_0024.png); 1886 en este lugar exacto (pages_1886/page_0020.png, book page 2/file 20) imprime IGUALMENTE "él se llenó del Espíritu\nde Señor," -- ERROR COMPARTIDO CON 1886, heredado; la edición moderna del Libro de Mormón en español (churchofjesuschrist.org, 1 Nefi 1:12) trae "lleno del Espíritu del Señor" completo; -> _cleaned: corregir a "del Señor"; preservado como se imprime en librodm_transcribed; hallado 2026-09-12 durante el cotejo manual de imagen del `manual-proofread`, primera unidad tras el frontispicio -- véase `workspace/proofread-1920.md`)
A26: 25 | B26: 1 Nefi | C26: 1 | D26: 15 | E26: 2 | F26: texto | H26: por las cosas el Señor le había mostrado | I26: por las cosas que el Señor le había mostrado | J26: palabra(s)/gramática | K26: o simplemente salta de "cosas" a "el Señor"; 1886 en este lugar exacto | O26: 31 | U26: 1 Nefi 1:15 por las cosas el Señor le había mostrado (por las cosas que el Señor le había mostrado) (1920 omite la palabra "que" en "por las cosas que él había visto, sí, por las cosas el Señor le había mostrado", pág. 2; confirmado a zoom en alta resolución (pages_1920/page_0024.png) -- no hay hueco ni mota de tinta, el texto simplemente salta de "cosas" a "el Señor"; 1886 en este lugar exacto (pages_1886/page_0020.png, book page 2/file 20) SÍ trae el "que" completo, "por las cosas que el Señor le había mostrado" -- construcción paralela con la cláusula anterior ("las cosas que él había visto"); la edición moderna del Libro de Mormón en español (churchofjesuschrist.org, 1 Nefi 1:15) también usa "que"; ERROR EXCLUSIVO DE 1920 -- 1886 no comparte la omisión; hallado mediante cotejo con la capa de OCR incrustada del propio PDF de 1920 [`google_text_1920`/`check_google_crosscheck.py`], 2026-09-10, primer resultado del muestreo piloto de páginas 1-436 -- véase `workspace/diff1920ocr-trans.md`; preservado como se imprime en librodm_transcribed [la transcripción anterior incluía por error el "que" tomado de 1886; corregida silenciosamente para igualar el 1920 real])
A27: 26 | B27: 1 Nefi | C27: 1 | D27: 16 | E27: 2 | F27: texto | H27: hablo á sus hijos | I27: habló á sus hijos | J27: tilde | K27: 1886 en este lugar exacto | O27: 32 | U27: 1 Nefi 1:16 hablo á sus hijos (habló á sus hijos) (1920 imprime "que profetizó y hablo á sus hijos" sin tilde en "hablo" -- rompe el paralelismo con "profetizó", tiempo pasado --, página 2; confirmado a zoom en alta resolución (pages_1920/page_0024.png) y de forma independiente por la capa de OCR incrustada del propio PDF (`google_text_1920/page_0024.txt` line 43, lee igualmente "hablo" sin tilde); 1886 en este lugar exacto (pages_1886/page_0021.png, book page 3/file 21) SÍ trae la tilde, "que profetizó y habló á sus hijos" -- ERROR EXCLUSIVO DE 1920, 1886 no lo comparte; la edición moderna del Libro de Mormón en español también usa "habló"; preservado como se imprime en librodm_transcribed [la transcripción anterior traía por error "habló" con tilde, tomada aparentemente de 1886/corrección tácita; corregida silenciosamente para igualar el 1920 real]; hallado 2026-09-12 durante el cotejo manual de imagen del `manual-proofread` -- este caso concreto había sido descartado antes como ruido de OCR bajo la categoría "Google drops or garbles a single... accent" del `ocr-diff-pilot` sin comprobar la imagen; aquí Google tenía razón -- véase `workspace/proofread-1920.md`)
A28: 27 | B28: 1 Nefi | C28: 1 | D28: 20 | E28: 3 | F28: texto | H28: quiénes | I28: quienes | J28: familia | K28: . USO DE ÉPOCA COMPROBADO: 1886 | L28: relativos "quién/quiénes" y "dónde" con tilde | M28: en librodm_cleaned, suprimir la tilde en las 289 (y conservarla en las 14 excluidas | O28: 87 | U28: FAMILIA relativos "quién/quiénes" y "dónde" con tilde (tilde diacrítica de interrogativo puesta sobre el RELATIVO) -- ENTRADA MAESTRA (2026-09-24, abierta durante el `manual-proofread` de Alma 52, a partir de Alma 52:12 "con quiénes marchó" y 52:27 "ciudad de Abundancia, dónde se encontraton"). NORMA DE ÉPOCA: el Prontuario de ortografía de la lengua castellana de la RAE (1844, oficial para las escuelas por Real Orden) prescribe la tilde en "que, como, cuando, quien, cual, donde y cuanto" solo "siempre que den principio a una cláusula de interrogación o de admiración", y además, sin signos de interrogación, "en los casos en que, para dar la debida entonación a la frase, sea preciso detenerse algo más que de ordinario" en la sílaba (1844: 26-27, citado en M. Peñalver Castillo, Anuario de Letras III-2, 2015) -- es decir, en las interrogativas indirectas tónicas ("no sé quién vino"), NUNCA en el relativo átono ("el hombre á quien vi"); la Gramática de 1870 mantiene la distinción; la norma actual (RAE, Ortografía 2010; DPD s.v. "quién") es la misma. Con "haber/tener": con infinitivo es interrogativo y lleva tilde ("no tenía á quién dejar el reino"); con verbo conjugado es relativo y no la lleva ("no hay quien pueda interpretar"). USO DE ÉPOCA COMPROBADO: 1886 (OCR del PDF completo) escribe el relativo SIEMPRE sin tilde -- fuera de preguntas: 355 "quien/quienes" sin tilde, 146 "donde" sin tilde, 0 "dónde" con tilde, y solo 2 "Quién" con tilde que resultan ser preguntas a las que les falta el "¿" inicial; dentro de preguntas lee 45 "quién" y 9 "dónde" con tilde, prueba de que el OCR sí capta las tildes. La Reina-Valera 1909 (NT, ortografía de época: "á", "fué") sigue la norma de 1844 al pie de la letra: relativos sin tilde ("á quien vosotros no conocéis", "Sobre quien vieres descender") y tilde solo en interrogativas indirectas ("dudando de quién decía", "no sabemos dónde le han puesto"). (El corpus del Quijote de workspace/reference_corpora/ NO sirve como prueba de época: es edición con ortografía moderna -- "fue", "vio", sin "á".) COTEJO POSICIÓN POR POSICIÓN CON 1886 (2026-09-24): (a) automático -- de las 281 posiciones, 276 localizadas en el OCR de 1886 por su contexto, TODAS sin tilde (0 con tilde; 5 no localizadas por ruido del OCR); (b) comprobación visual en las imágenes de 1886 (muestra pedida por el editor), 11 lugares fuera de pregunta, TODOS sin tilde: 1 Nefi 4:26 "á quien yo había matado" (file 28), 1 Nefi 10:8 "á quien no conocéis, quien es más poderoso... de quien no soy digno" (37), 1 Nefi 19:10 "á quienes sacó" (67), Mosíah 7:9 "quien era hijo de Zeniff, quien fué hecho rey" (193), Mosíah 26:21 "Y quien oyere mi voz" (239), Alma 13:15 "á quien Abraham pagaba" (291), Alma 29:5 "quien no conoce... quien distingue" (337), Alma 52:12 "con quienes marchó" (410), Helamán 6:30 "él es quien dirige... él es quien trasmite" (467), Éther 9:14 "á quien llamó Émer" (610), Alma 56:15 "donde encontré" (422), III Nefi 27:11 "de donde no se vuelve" (55
A29: 28 | B29: 1 Nefi | C29: 2 | D29: 2 | E29: 3 | F29: texto | H29: aún | I29: aun | J29: familia | K29: por el mismo camino en que vinieron", donde 1886 lee "aun atrás" | L29: "aún" con tilde por "aun" | M29: en librodm_cleaned, "aun" en (a | O29: 90 | P29: corregido | U29: FAMILIA "aún" con tilde por "aun" (= "hasta, incluso, también, siquiera") -- ENTRADA MAESTRA (2026-09-26, abierta durante el `manual-proofread` de Alma 58, a partir de Alma 58:24 "sí, aún atrás por el mismo camino en que vinieron", donde 1886 lee "aun atrás"). NORMA DE ÉPOCA: desde la Gramática de la RAE de 1880 y hasta 1952 la tilde de "aun" se regía por la POSICIÓN: antepuesto a lo que modifica era monosílabo átono y se escribía "aun"; pospuesto era bisílabo tónico y se escribía "aún" (Á. Calderón Rivera, Thesaurus XLVIII, 1993). Las Nuevas normas de prosodia y ortografía de 1952 (regla 17; texto en BRAE XXXVIII, cuad. CLV, pp. 331-347) adoptaron el criterio de SIGNIFICADO que mantiene la RAE actual (Ortografía 2010): "aún" cuando puede sustituirse por "todavía" ("aún está enfermo; está enfermo aún"); "aun" con el sentido de "hasta, también, inclusive (o siquiera, con negación)" ("aun los sordos han de oírme; ni hizo nada por él ni aun lo intentó"). CRITERIO DE ESTA ENTRADA: sólo se registran los casos que AMBAS normas condenan: (a) "aún" con tilde con el sentido de "hasta/incluso/siquiera" y ANTEPUESTO a lo que modifica ("aún hasta la muerte", "aún como", "sí, aún la ley de Moisés", "ni aún entre los Nefitas", "aún cuando" concesivo, "aún así"); (b) "aun" sin tilde con el sentido de "todavía" y POSPUESTO a lo que modifica. EXCLUIDOS, no registrados: los correctos por ambas normas ("aun" = "incluso" antepuesto; "aún" = "todavía" pospuesto: "viven aún", "no ha llegado aún", "os llama aún", "permanecían aún duros"); los que una norma aprueba y la otra condena ("aun/aún" = "todavía" antepuesto: "aun no se ha concluido mi obra", "aun están vivas", "mas aun quedará"); y las construcciones con "más/mayor" ("aun más", "aún más ruin", "aun mayor"), que admiten las dos lecturas. Clasificación hecha a mano sobre las 389 apariciones de "aun/aún" en el cuerpo de librodm.txt (217 "aún", 172 "aun"), con apoyo en el inglés en las dudosas ("even" frente a "yet/still"). USO DE 1886: el OCR del PDF completo tiene 194 "aun/Aun" y un solo "aún" (Alma 20:30 "aún más dura", caso excluido); de las 194 posiciones de esta entrada en el cuerpo, 179 se localizaron automáticamente en 1886 por su contexto, TODAS "aun" sin tilde, y las 15 restantes (no localizadas por ruido del OCR o redacción distinta) tampoco pueden llevarla, pues el único "aún" de 1886 está en Alma 20:30 -> el grupo (a) es EXCLUSIVO DE 1920; el grupo (b) es COMPARTIDO CON 1886. APARICIONES: (a) "aún" por "aun" -- 192 en el cuerpo: 1 Nefi 2:2; 1 Nefi 5:13; 1 Nefi 12:11; 1 Nefi 12:18; 1 Nefi 13:29; 1 Nefi 17:4; 1 Nefi 17:48; 1 Nefi 17:52; 1 Nefi 20:5; 1 Nefi 22:17 x2; 2 Nefi 1:13; 2 Nefi 1:29; 2 Nefi 2:15; 2 Nefi 2:18; 2 Nefi 3:20 x2; 2 Nefi 4:10; 2 Nefi 4:25; 2 Nefi 5:25; 2 Nefi 9:2; 2 Nefi 9:14; 2 Nefi 9:46; 2 Nefi 13:9; 2 Nefi 18:7; 2 Nefi 19:7; 2 Nefi 19:9; 2 Nefi 23:12; 2 Nefi 24:9; 2 Nefi 25:16; 2 Nefi 26:15; 2 Nefi 26:16; 2 Nefi 27:1; 2 Nefi 27:11; 2 Nefi 28:23; 2 Nefi 28:30; 2 Nefi 29:7; 2 Nefi 31:
A30: 29 | B30: 1 Nefi | C30: 2 | D30: 19 | E30: 5 | F30: texto | H30: con humilidad | I30: con humildad | J30: letra(s) | K30: humildad en versión de 1886 | O30: 33 | U30: 1 Nefi 2:19 con humilidad (con humildad)(humildad en versión de 1886)
A31: 30 | B31: 1 Nefi | C31: 3 | D31: 5 | E31: 5 | F31: texto | H31: quién | I31: quien | J31: familia | K31: . USO DE ÉPOCA COMPROBADO: 1886 | L31: relativos "quién/quiénes" y "dónde" con tilde | M31: en librodm_cleaned, suprimir la tilde en las 289 (y conservarla en las 14 excluidas | O31: 87 | U31: FAMILIA relativos "quién/quiénes" y "dónde" con tilde (tilde diacrítica de interrogativo puesta sobre el RELATIVO) -- ENTRADA MAESTRA (2026-09-24, abierta durante el `manual-proofread` de Alma 52, a partir de Alma 52:12 "con quiénes marchó" y 52:27 "ciudad de Abundancia, dónde se encontraton"). NORMA DE ÉPOCA: el Prontuario de ortografía de la lengua castellana de la RAE (1844, oficial para las escuelas por Real Orden) prescribe la tilde en "que, como, cuando, quien, cual, donde y cuanto" solo "siempre que den principio a una cláusula de interrogación o de admiración", y además, sin signos de interrogación, "en los casos en que, para dar la debida entonación a la frase, sea preciso detenerse algo más que de ordinario" en la sílaba (1844: 26-27, citado en M. Peñalver Castillo, Anuario de Letras III-2, 2015) -- es decir, en las interrogativas indirectas tónicas ("no sé quién vino"), NUNCA en el relativo átono ("el hombre á quien vi"); la Gramática de 1870 mantiene la distinción; la norma actual (RAE, Ortografía 2010; DPD s.v. "quién") es la misma. Con "haber/tener": con infinitivo es interrogativo y lleva tilde ("no tenía á quién dejar el reino"); con verbo conjugado es relativo y no la lleva ("no hay quien pueda interpretar"). USO DE ÉPOCA COMPROBADO: 1886 (OCR del PDF completo) escribe el relativo SIEMPRE sin tilde -- fuera de preguntas: 355 "quien/quienes" sin tilde, 146 "donde" sin tilde, 0 "dónde" con tilde, y solo 2 "Quién" con tilde que resultan ser preguntas a las que les falta el "¿" inicial; dentro de preguntas lee 45 "quién" y 9 "dónde" con tilde, prueba de que el OCR sí capta las tildes. La Reina-Valera 1909 (NT, ortografía de época: "á", "fué") sigue la norma de 1844 al pie de la letra: relativos sin tilde ("á quien vosotros no conocéis", "Sobre quien vieres descender") y tilde solo en interrogativas indirectas ("dudando de quién decía", "no sabemos dónde le han puesto"). (El corpus del Quijote de workspace/reference_corpora/ NO sirve como prueba de época: es edición con ortografía moderna -- "fue", "vio", sin "á".) COTEJO POSICIÓN POR POSICIÓN CON 1886 (2026-09-24): (a) automático -- de las 281 posiciones, 276 localizadas en el OCR de 1886 por su contexto, TODAS sin tilde (0 con tilde; 5 no localizadas por ruido del OCR); (b) comprobación visual en las imágenes de 1886 (muestra pedida por el editor), 11 lugares fuera de pregunta, TODOS sin tilde: 1 Nefi 4:26 "á quien yo había matado" (file 28), 1 Nefi 10:8 "á quien no conocéis, quien es más poderoso... de quien no soy digno" (37), 1 Nefi 19:10 "á quienes sacó" (67), Mosíah 7:9 "quien era hijo de Zeniff, quien fué hecho rey" (193), Mosíah 26:21 "Y quien oyere mi voz" (239), Alma 13:15 "á quien Abraham pagaba" (291), Alma 29:5 "quien no conoce... quien distingue" (337), Alma 52:12 "con quienes marchó" (410), Helamán 6:30 "él es quien dirige... él es quien trasmite" (467), Éther 9:14 "á quien llamó Émer" (610), Alma 56:15 "donde encontré" (422), III Nefi 27:11 "de donde no se vuelve" (55
A32: 31 | B32: 1 Nefi | C32: 3 | D32: 11 | E32: 6 | F32: texto | H32: quién | I32: quien | J32: familia | K32: . USO DE ÉPOCA COMPROBADO: 1886 | L32: relativos "quién/quiénes" y "dónde" con tilde | M32: en librodm_cleaned, suprimir la tilde en las 289 (y conservarla en las 14 excluidas | O32: 87 | U32: FAMILIA relativos "quién/quiénes" y "dónde" con tilde (tilde diacrítica de interrogativo puesta sobre el RELATIVO) -- ENTRADA MAESTRA (2026-09-24, abierta durante el `manual-proofread` de Alma 52, a partir de Alma 52:12 "con quiénes marchó" y 52:27 "ciudad de Abundancia, dónde se encontraton"). NORMA DE ÉPOCA: el Prontuario de ortografía de la lengua castellana de la RAE (1844, oficial para las escuelas por Real Orden) prescribe la tilde en "que, como, cuando, quien, cual, donde y cuanto" solo "siempre que den principio a una cláusula de interrogación o de admiración", y además, sin signos de interrogación, "en los casos en que, para dar la debida entonación a la frase, sea preciso detenerse algo más que de ordinario" en la sílaba (1844: 26-27, citado en M. Peñalver Castillo, Anuario de Letras III-2, 2015) -- es decir, en las interrogativas indirectas tónicas ("no sé quién vino"), NUNCA en el relativo átono ("el hombre á quien vi"); la Gramática de 1870 mantiene la distinción; la norma actual (RAE, Ortografía 2010; DPD s.v. "quién") es la misma. Con "haber/tener": con infinitivo es interrogativo y lleva tilde ("no tenía á quién dejar el reino"); con verbo conjugado es relativo y no la lleva ("no hay quien pueda interpretar"). USO DE ÉPOCA COMPROBADO: 1886 (OCR del PDF completo) escribe el relativo SIEMPRE sin tilde -- fuera de preguntas: 355 "quien/quienes" sin tilde, 146 "donde" sin tilde, 0 "dónde" con tilde, y solo 2 "Quién" con tilde que resultan ser preguntas a las que les falta el "¿" inicial; dentro de preguntas lee 45 "quién" y 9 "dónde" con tilde, prueba de que el OCR sí capta las tildes. La Reina-Valera 1909 (NT, ortografía de época: "á", "fué") sigue la norma de 1844 al pie de la letra: relativos sin tilde ("á quien vosotros no conocéis", "Sobre quien vieres descender") y tilde solo en interrogativas indirectas ("dudando de quién decía", "no sabemos dónde le han puesto"). (El corpus del Quijote de workspace/reference_corpora/ NO sirve como prueba de época: es edición con ortografía moderna -- "fue", "vio", sin "á".) COTEJO POSICIÓN POR POSICIÓN CON 1886 (2026-09-24): (a) automático -- de las 281 posiciones, 276 localizadas en el OCR de 1886 por su contexto, TODAS sin tilde (0 con tilde; 5 no localizadas por ruido del OCR); (b) comprobación visual en las imágenes de 1886 (muestra pedida por el editor), 11 lugares fuera de pregunta, TODOS sin tilde: 1 Nefi 4:26 "á quien yo había matado" (file 28), 1 Nefi 10:8 "á quien no conocéis, quien es más poderoso... de quien no soy digno" (37), 1 Nefi 19:10 "á quienes sacó" (67), Mosíah 7:9 "quien era hijo de Zeniff, quien fué hecho rey" (193), Mosíah 26:21 "Y quien oyere mi voz" (239), Alma 13:15 "á quien Abraham pagaba" (291), Alma 29:5 "quien no conoce... quien distingue" (337), Alma 52:12 "con quienes marchó" (410), Helamán 6:30 "él es quien dirige... él es quien trasmite" (467), Éther 9:14 "á quien llamó Émer" (610), Alma 56:15 "donde encontré" (422), III Nefi 27:11 "de donde no se vuelve" (55
A33: 32 | B33: 1 Nefi | C33: 4 | D33: 9 | E33: 8 | F33: nota | G33: 20 (4a) | H33: Covenios | I33: Convenios | J33: letra(s) | K33: 1886 no tiene aparato de notas con el cual comparar | O33: 34 | U33: Footnote 1 Nefi 4a, 20 Covenios (Convenios) (1920 imprime "Doctrinas y Covenios 17:1" -- falta la "n" de "Convenios" -- en la nota a del capítulo 4, página 8; confirmado a zoom en alta resolución (pages_1920/page_0030.png); 1886 no tiene aparato de notas con el cual comparar; "Doctrinas y Convenios" (con "n") aparece correctamente unas 40 veces más a lo largo de `librodm_foot.txt`/`librodm.txt`, por lo que esta es una errata aislada, no una grafía de casa; error exclusivo de 1920; preservado como se imprime en librodm_transcribed [tanto Block 1 como Block 2 traían por error "Convenios" ya corregido; corregidos silenciosamente ambos para igualar el 1920 real, "Covenios"]; hallado 2026-09-12 durante el cotejo manual de imagen del `manual-proofread` -- véase `workspace/proofread-1920.md`)
A34: 33 | B34: 1 Nefi | C34: 4 | D34: 17 | E34: 9 | F34: texto | H34: Quién | I34: Quien | J34: familia | K34: . USO DE ÉPOCA COMPROBADO: 1886 | L34: relativos "quién/quiénes" y "dónde" con tilde | M34: en librodm_cleaned, suprimir la tilde en las 289 (y conservarla en las 14 excluidas | O34: 87 | U34: FAMILIA relativos "quién/quiénes" y "dónde" con tilde (tilde diacrítica de interrogativo puesta sobre el RELATIVO) -- ENTRADA MAESTRA (2026-09-24, abierta durante el `manual-proofread` de Alma 52, a partir de Alma 52:12 "con quiénes marchó" y 52:27 "ciudad de Abundancia, dónde se encontraton"). NORMA DE ÉPOCA: el Prontuario de ortografía de la lengua castellana de la RAE (1844, oficial para las escuelas por Real Orden) prescribe la tilde en "que, como, cuando, quien, cual, donde y cuanto" solo "siempre que den principio a una cláusula de interrogación o de admiración", y además, sin signos de interrogación, "en los casos en que, para dar la debida entonación a la frase, sea preciso detenerse algo más que de ordinario" en la sílaba (1844: 26-27, citado en M. Peñalver Castillo, Anuario de Letras III-2, 2015) -- es decir, en las interrogativas indirectas tónicas ("no sé quién vino"), NUNCA en el relativo átono ("el hombre á quien vi"); la Gramática de 1870 mantiene la distinción; la norma actual (RAE, Ortografía 2010; DPD s.v. "quién") es la misma. Con "haber/tener": con infinitivo es interrogativo y lleva tilde ("no tenía á quién dejar el reino"); con verbo conjugado es relativo y no la lleva ("no hay quien pueda interpretar"). USO DE ÉPOCA COMPROBADO: 1886 (OCR del PDF completo) escribe el relativo SIEMPRE sin tilde -- fuera de preguntas: 355 "quien/quienes" sin tilde, 146 "donde" sin tilde, 0 "dónde" con tilde, y solo 2 "Quién" con tilde que resultan ser preguntas a las que les falta el "¿" inicial; dentro de preguntas lee 45 "quién" y 9 "dónde" con tilde, prueba de que el OCR sí capta las tildes. La Reina-Valera 1909 (NT, ortografía de época: "á", "fué") sigue la norma de 1844 al pie de la letra: relativos sin tilde ("á quien vosotros no conocéis", "Sobre quien vieres descender") y tilde solo en interrogativas indirectas ("dudando de quién decía", "no sabemos dónde le han puesto"). (El corpus del Quijote de workspace/reference_corpora/ NO sirve como prueba de época: es edición con ortografía moderna -- "fue", "vio", sin "á".) COTEJO POSICIÓN POR POSICIÓN CON 1886 (2026-09-24): (a) automático -- de las 281 posiciones, 276 localizadas en el OCR de 1886 por su contexto, TODAS sin tilde (0 con tilde; 5 no localizadas por ruido del OCR); (b) comprobación visual en las imágenes de 1886 (muestra pedida por el editor), 11 lugares fuera de pregunta, TODOS sin tilde: 1 Nefi 4:26 "á quien yo había matado" (file 28), 1 Nefi 10:8 "á quien no conocéis, quien es más poderoso... de quien no soy digno" (37), 1 Nefi 19:10 "á quienes sacó" (67), Mosíah 7:9 "quien era hijo de Zeniff, quien fué hecho rey" (193), Mosíah 26:21 "Y quien oyere mi voz" (239), Alma 13:15 "á quien Abraham pagaba" (291), Alma 29:5 "quien no conoce... quien distingue" (337), Alma 52:12 "con quienes marchó" (410), Helamán 6:30 "él es quien dirige... él es quien trasmite" (467), Éther 9:14 "á quien llamó Émer" (610), Alma 56:15 "donde encontré" (422), III Nefi 27:11 "de donde no se vuelve" (55
A35: 34 | B35: 1 Nefi | C35: 4 | D35: 26 | E35: 9 | F35: texto | H35: quién | I35: quien | J35: familia | K35: . USO DE ÉPOCA COMPROBADO: 1886 | L35: relativos "quién/quiénes" y "dónde" con tilde | M35: en librodm_cleaned, suprimir la tilde en las 289 (y conservarla en las 14 excluidas | O35: 87 | U35: FAMILIA relativos "quién/quiénes" y "dónde" con tilde (tilde diacrítica de interrogativo puesta sobre el RELATIVO) -- ENTRADA MAESTRA (2026-09-24, abierta durante el `manual-proofread` de Alma 52, a partir de Alma 52:12 "con quiénes marchó" y 52:27 "ciudad de Abundancia, dónde se encontraton"). NORMA DE ÉPOCA: el Prontuario de ortografía de la lengua castellana de la RAE (1844, oficial para las escuelas por Real Orden) prescribe la tilde en "que, como, cuando, quien, cual, donde y cuanto" solo "siempre que den principio a una cláusula de interrogación o de admiración", y además, sin signos de interrogación, "en los casos en que, para dar la debida entonación a la frase, sea preciso detenerse algo más que de ordinario" en la sílaba (1844: 26-27, citado en M. Peñalver Castillo, Anuario de Letras III-2, 2015) -- es decir, en las interrogativas indirectas tónicas ("no sé quién vino"), NUNCA en el relativo átono ("el hombre á quien vi"); la Gramática de 1870 mantiene la distinción; la norma actual (RAE, Ortografía 2010; DPD s.v. "quién") es la misma. Con "haber/tener": con infinitivo es interrogativo y lleva tilde ("no tenía á quién dejar el reino"); con verbo conjugado es relativo y no la lleva ("no hay quien pueda interpretar"). USO DE ÉPOCA COMPROBADO: 1886 (OCR del PDF completo) escribe el relativo SIEMPRE sin tilde -- fuera de preguntas: 355 "quien/quienes" sin tilde, 146 "donde" sin tilde, 0 "dónde" con tilde, y solo 2 "Quién" con tilde que resultan ser preguntas a las que les falta el "¿" inicial; dentro de preguntas lee 45 "quién" y 9 "dónde" con tilde, prueba de que el OCR sí capta las tildes. La Reina-Valera 1909 (NT, ortografía de época: "á", "fué") sigue la norma de 1844 al pie de la letra: relativos sin tilde ("á quien vosotros no conocéis", "Sobre quien vieres descender") y tilde solo en interrogativas indirectas ("dudando de quién decía", "no sabemos dónde le han puesto"). (El corpus del Quijote de workspace/reference_corpora/ NO sirve como prueba de época: es edición con ortografía moderna -- "fue", "vio", sin "á".) COTEJO POSICIÓN POR POSICIÓN CON 1886 (2026-09-24): (a) automático -- de las 281 posiciones, 276 localizadas en el OCR de 1886 por su contexto, TODAS sin tilde (0 con tilde; 5 no localizadas por ruido del OCR); (b) comprobación visual en las imágenes de 1886 (muestra pedida por el editor), 11 lugares fuera de pregunta, TODOS sin tilde: 1 Nefi 4:26 "á quien yo había matado" (file 28), 1 Nefi 10:8 "á quien no conocéis, quien es más poderoso... de quien no soy digno" (37), 1 Nefi 19:10 "á quienes sacó" (67), Mosíah 7:9 "quien era hijo de Zeniff, quien fué hecho rey" (193), Mosíah 26:21 "Y quien oyere mi voz" (239), Alma 13:15 "á quien Abraham pagaba" (291), Alma 29:5 "quien no conoce... quien distingue" (337), Alma 52:12 "con quienes marchó" (410), Helamán 6:30 "él es quien dirige... él es quien trasmite" (467), Éther 9:14 "á quien llamó Émer" (610), Alma 56:15 "donde encontré" (422), III Nefi 27:11 "de donde no se vuelve" (55
A36: 35 | B36: 1 Nefi | C36: 4 | D36: 36 | E36: 10 | F36: texto | H36: que nos perseguieran | I36: que nos persiguieran | J36: letra(s) | K36: perseguieran en 1886 | O36: 35 | U36: 1 Nefi 4:36 que nos perseguieran (que nos persiguieran) (perseguieran en 1886)
A37: 36 | B37: 1 Nefi | C37: 5 | D37: 1 | E37: 10 | F37: texto | H37: acausa | I37: a causa | J37: puntuación/espacio | K37: á cáusa en 1886 | O37: 36 | U37: 1 Nefi 5:1 acausa (a causa) (á cáusa en 1886)
A38: 37 | B38: 1 Nefi | C38: 5 | D38: 2 | E38: 10 | F38: texto | H38: quién | I38: quien | J38: familia | K38: . USO DE ÉPOCA COMPROBADO: 1886 | L38: relativos "quién/quiénes" y "dónde" con tilde | M38: en librodm_cleaned, suprimir la tilde en las 289 (y conservarla en las 14 excluidas | O38: 87 | U38: FAMILIA relativos "quién/quiénes" y "dónde" con tilde (tilde diacrítica de interrogativo puesta sobre el RELATIVO) -- ENTRADA MAESTRA (2026-09-24, abierta durante el `manual-proofread` de Alma 52, a partir de Alma 52:12 "con quiénes marchó" y 52:27 "ciudad de Abundancia, dónde se encontraton"). NORMA DE ÉPOCA: el Prontuario de ortografía de la lengua castellana de la RAE (1844, oficial para las escuelas por Real Orden) prescribe la tilde en "que, como, cuando, quien, cual, donde y cuanto" solo "siempre que den principio a una cláusula de interrogación o de admiración", y además, sin signos de interrogación, "en los casos en que, para dar la debida entonación a la frase, sea preciso detenerse algo más que de ordinario" en la sílaba (1844: 26-27, citado en M. Peñalver Castillo, Anuario de Letras III-2, 2015) -- es decir, en las interrogativas indirectas tónicas ("no sé quién vino"), NUNCA en el relativo átono ("el hombre á quien vi"); la Gramática de 1870 mantiene la distinción; la norma actual (RAE, Ortografía 2010; DPD s.v. "quién") es la misma. Con "haber/tener": con infinitivo es interrogativo y lleva tilde ("no tenía á quién dejar el reino"); con verbo conjugado es relativo y no la lleva ("no hay quien pueda interpretar"). USO DE ÉPOCA COMPROBADO: 1886 (OCR del PDF completo) escribe el relativo SIEMPRE sin tilde -- fuera de preguntas: 355 "quien/quienes" sin tilde, 146 "donde" sin tilde, 0 "dónde" con tilde, y solo 2 "Quién" con tilde que resultan ser preguntas a las que les falta el "¿" inicial; dentro de preguntas lee 45 "quién" y 9 "dónde" con tilde, prueba de que el OCR sí capta las tildes. La Reina-Valera 1909 (NT, ortografía de época: "á", "fué") sigue la norma de 1844 al pie de la letra: relativos sin tilde ("á quien vosotros no conocéis", "Sobre quien vieres descender") y tilde solo en interrogativas indirectas ("dudando de quién decía", "no sabemos dónde le han puesto"). (El corpus del Quijote de workspace/reference_corpora/ NO sirve como prueba de época: es edición con ortografía moderna -- "fue", "vio", sin "á".) COTEJO POSICIÓN POR POSICIÓN CON 1886 (2026-09-24): (a) automático -- de las 281 posiciones, 276 localizadas en el OCR de 1886 por su contexto, TODAS sin tilde (0 con tilde; 5 no localizadas por ruido del OCR); (b) comprobación visual en las imágenes de 1886 (muestra pedida por el editor), 11 lugares fuera de pregunta, TODOS sin tilde: 1 Nefi 4:26 "á quien yo había matado" (file 28), 1 Nefi 10:8 "á quien no conocéis, quien es más poderoso... de quien no soy digno" (37), 1 Nefi 19:10 "á quienes sacó" (67), Mosíah 7:9 "quien era hijo de Zeniff, quien fué hecho rey" (193), Mosíah 26:21 "Y quien oyere mi voz" (239), Alma 13:15 "á quien Abraham pagaba" (291), Alma 29:5 "quien no conoce... quien distingue" (337), Alma 52:12 "con quienes marchó" (410), Helamán 6:30 "él es quien dirige... él es quien trasmite" (467), Éther 9:14 "á quien llamó Émer" (610), Alma 56:15 "donde encontré" (422), III Nefi 27:11 "de donde no se vuelve" (55
A39: 38 | B39: 1 Nefi | C39: 5 | D39: 3 | E39: 10 | F39: texto | H39: lenguage | I39: lenguaje | J39: familia | K39: pág. 466/467, LIBRO DE HELAMÁN CAPÍTULO 11; 1886 comparte "pillage" en este lugar exacto, pages_18 | L39: -age | M39: -> _cleaned (DECISIÓN DEL EDITOR | O39: 22 | U39: FAMILIA -age (por -aje) -- grafía "-age" arcaica donde el español moderno escribe "-aje". ENTRADA MAESTRA (2026-09-09; consolida las entradas antes dispersas de 1 Nefi 1:2 y 1 Nefi 5:3, ambas "el/este lenguage"). Alcance: "lenguage" 11 apariciones en el cuerpo (`grep -nE "lenguage" librodm_transcribed.txt`) + "lenguage del libro" en el índice (pág. xiii) + "344 días de pasage" en el índice (pág. xiii, entrada de Éther 6:11) + "pillage" 1x en el cuerpo (Helamán 11:25, "Y entregándose al pillage y al asesinato", pág. 466/467, LIBRO DE HELAMÁN CAPÍTULO 11; 1886 comparte "pillage" en este lugar exacto, pages_1886/page_0481.png, book page 463/file 481). Frente a "lenguaje" 3x, "pasaje" 12x y "pillaje/pillajes" 13x en el cuerpo (Helamán 11:25 es la ÚNICA aparición de "pillage" -- 1920 usa "pillaje" en las otras 13). La grafía "-age" (mensage/linage/viage/salvage/lenguage/pasage) fue la NORMA del español hasta que la RAE estandarizó "-aje" (~1815); para 1886/1920 era arcaica pero aún frecuente en imprenta. 1920 ya ha completado el cambio a "-aje" en TODAS las demás palabras (mensaje 22x, viaje 29x, salvaje 5x, linaje 4x, ultraje 2x -- 0 con "-age"), quedando SOLO "lenguage" (su forma de casa dominante, 11:3) y un "pasage" suelto en el índice. 1886: comparte "lenguage" ("lenguage en 1886" en las entradas originales de 1 Nefi 1:2 y 5:3). Atestiguación externa: "-age" en estas palabras = 0 en Quijote / Reina-Valera 1909 NT / Reina-Valera Biblia completa; "lenguaje" Quijote 10, "pasaje" Quijote 10, "pillaje" 1 en Reina-Valera Biblia completa (0 "pillage"). CLASIFICACIÓN: grafía ortográfica arcaica de época (norma pre-1815), compartida con 1886, NO un error tipográfico; edición inconsistente (casi todo "-aje", pero "lenguage" mayoritario). -> _cleaned (DECISIÓN DEL EDITOR): normalizar las apariciones restantes de "-age" a "-aje" (lenguage -> lenguaje; pasage -> pasaje; pillage -> pillaje, forma ya mayoritaria 13:1 en la propia 1920), como regularización de una grafía de época, no como corrección de errores. Preservado como se imprime en librodm_transcribed.
A40: 39 | B40: 1 Nefi | C40: 5 | D40: 4 | E40: 10 | F40: texto | H40: y hubieria permanecido | I40: y hubiera permanecido | J40: letra(s) | K40: 1886 en este lugar exacto | O40: 37 | U40: 1 Nefi 5:4 y hubieria permanecido (y hubiera permanecido) (1920 imprime "no habría conocido su bondad y hubieria permanecido en Jerusalem", página 10/11 [línea de vuelta de página]; confirmado a zoom en alta resolución (pages_1920/page_0032.png fin + pages_1920/page_0033.png inicio); único "hubieria" en todo el documento (`grep -c hubieria librodm_transcribed.txt` = 1); 1886 en este lugar exacto (pages_1886/page_0029.png, book page 11/file 29) trae "hubiera permanecido" sin la "i" espuria; error exclusivo de 1920; preservado como se imprime en librodm_transcribed; entrada corregida 2026-09-12 durante el `manual-proofread` -- el fragmento citado originalmente, "no hubieria visto", no corresponde a ningún texto real de este versículo [ese tramo dice correctamente "si no hubiere visto" / "no habría conocido"]; la palabra "hubieria" realmente aparece más adelante en el mismo v.4, "y hubieria permanecido"; véase `workspace/proofread-1920.md`)
A41: 40 | B41: 1 Nefi | C41: 5 | D41: 13 | E41: 11 | F41: texto | H41: aún | I41: aun | J41: familia | K41: por el mismo camino en que vinieron", donde 1886 lee "aun atrás" | L41: "aún" con tilde por "aun" | M41: en librodm_cleaned, "aun" en (a | O41: 90 | U41: FAMILIA "aún" con tilde por "aun" (= "hasta, incluso, también, siquiera") -- ENTRADA MAESTRA (2026-09-26, abierta durante el `manual-proofread` de Alma 58, a partir de Alma 58:24 "sí, aún atrás por el mismo camino en que vinieron", donde 1886 lee "aun atrás"). NORMA DE ÉPOCA: desde la Gramática de la RAE de 1880 y hasta 1952 la tilde de "aun" se regía por la POSICIÓN: antepuesto a lo que modifica era monosílabo átono y se escribía "aun"; pospuesto era bisílabo tónico y se escribía "aún" (Á. Calderón Rivera, Thesaurus XLVIII, 1993). Las Nuevas normas de prosodia y ortografía de 1952 (regla 17; texto en BRAE XXXVIII, cuad. CLV, pp. 331-347) adoptaron el criterio de SIGNIFICADO que mantiene la RAE actual (Ortografía 2010): "aún" cuando puede sustituirse por "todavía" ("aún está enfermo; está enfermo aún"); "aun" con el sentido de "hasta, también, inclusive (o siquiera, con negación)" ("aun los sordos han de oírme; ni hizo nada por él ni aun lo intentó"). CRITERIO DE ESTA ENTRADA: sólo se registran los casos que AMBAS normas condenan: (a) "aún" con tilde con el sentido de "hasta/incluso/siquiera" y ANTEPUESTO a lo que modifica ("aún hasta la muerte", "aún como", "sí, aún la ley de Moisés", "ni aún entre los Nefitas", "aún cuando" concesivo, "aún así"); (b) "aun" sin tilde con el sentido de "todavía" y POSPUESTO a lo que modifica. EXCLUIDOS, no registrados: los correctos por ambas normas ("aun" = "incluso" antepuesto; "aún" = "todavía" pospuesto: "viven aún", "no ha llegado aún", "os llama aún", "permanecían aún duros"); los que una norma aprueba y la otra condena ("aun/aún" = "todavía" antepuesto: "aun no se ha concluido mi obra", "aun están vivas", "mas aun quedará"); y las construcciones con "más/mayor" ("aun más", "aún más ruin", "aun mayor"), que admiten las dos lecturas. Clasificación hecha a mano sobre las 389 apariciones de "aun/aún" en el cuerpo de librodm.txt (217 "aún", 172 "aun"), con apoyo en el inglés en las dudosas ("even" frente a "yet/still"). USO DE 1886: el OCR del PDF completo tiene 194 "aun/Aun" y un solo "aún" (Alma 20:30 "aún más dura", caso excluido); de las 194 posiciones de esta entrada en el cuerpo, 179 se localizaron automáticamente en 1886 por su contexto, TODAS "aun" sin tilde, y las 15 restantes (no localizadas por ruido del OCR o redacción distinta) tampoco pueden llevarla, pues el único "aún" de 1886 está en Alma 20:30 -> el grupo (a) es EXCLUSIVO DE 1920; el grupo (b) es COMPARTIDO CON 1886. APARICIONES: (a) "aún" por "aun" -- 192 en el cuerpo: 1 Nefi 2:2; 1 Nefi 5:13; 1 Nefi 12:11; 1 Nefi 12:18; 1 Nefi 13:29; 1 Nefi 17:4; 1 Nefi 17:48; 1 Nefi 17:52; 1 Nefi 20:5; 1 Nefi 22:17 x2; 2 Nefi 1:13; 2 Nefi 1:29; 2 Nefi 2:15; 2 Nefi 2:18; 2 Nefi 3:20 x2; 2 Nefi 4:10; 2 Nefi 4:25; 2 Nefi 5:25; 2 Nefi 9:2; 2 Nefi 9:14; 2 Nefi 9:46; 2 Nefi 13:9; 2 Nefi 18:7; 2 Nefi 19:7; 2 Nefi 19:9; 2 Nefi 23:12; 2 Nefi 24:9; 2 Nefi 25:16; 2 Nefi 26:15; 2 Nefi 26:16; 2 Nefi 27:1; 2 Nefi 27:11; 2 Nefi 28:23; 2 Nefi 28:30; 2 Nefi 29:7; 2 Nefi 31:
A42: 41 | B42: 1 Nefi | C42: 5 | D42: 22 | E42: 12 | F42: texto | H42: fué despuesto | I42: fué dispuesto | J42: letra(s) | K42: dispuesto en 1886 | O42: 38 | U42: 1 Nefi 5:22 fué despuesto (fué dispuesto) (dispuesto en 1886)
A43: 42 | B43: 1 Nefi | C43: 7 | D43: 1 | E43: 12 | F43: texto | H43: sóla | I43: sola | J43: tilde | K43: transcripción ya coincide con la impresión; 1886 no localizado en el texto del PDF | O43: 39 | U43: 1 Nefi 7:1 sóla (sola) (1920 imprime "no era conveniente que tuviera sóla su familia en el desierto", página 13 (pages_1920/page_0035.png), con tilde espuria en el adjetivo "sola"; confirmado en la imagen 2026-10-17 (revisión de variantes de tilde, item 4a); la transcripción ya coincide con la impresión; 1886 no localizado en el texto del PDF)
A44: 43 | B44: 1 Nefi | C44: 7 | D44: 5 | E44: 13 | F44: texto | H44: él | I44: el | J44: familia | K44: . 1886: el texto OCR del PDF de 1886 | L44: "él" por "el" | M44: _cleaned`, normalizar a "el" sin tilde | O44: 85 | U44: FAMILIA "él" por "el" (artículo acentuado como pronombre ante "de"/"que") -- ENTRADA MAESTRA (2026-09-23, abierta durante el `manual-proofread` de Alma 43; consolida las entradas antes sueltas de Alma 40:6, Mormón 6:21 y Éther 12:38). 1920 imprime sistemáticamente con tilde el ARTÍCULO "el" cuando va ante "de"/"del" (sustantivo elidido: "mayor que él de los Nefitas" = "mayor que el [número] de los Nefitas"; "y él de su familia" = "y el [corazón] de su familia") o ante el relativo "que" ("en él que" = "en el que", "él que busque, halla" = "el que busque, halla", aposición "José, él que fué llevado"). Según la RAE (tilde diacrítica: "él" pronombre personal tónico / "el" artículo átono), en todas estas posiciones corresponde "el" SIN tilde; la forma con tilde leída literalmente significa "él" (he/him), lo que rompe la gramática. Clasificación del editor (2026-09-23): "gringismo" -- error de un hablante de español como segunda lengua (probable calco de "he that..." / "that of..." del inglés), no una variante de época: no se halló ninguna fuente normativa ni histórica que lo avale, y la ortografía académica del siglo XIX ya distinguía "él"/"el". Alcance: 156 apariciones en el cuerpo de librodm.txt (ninguna en los bloques de notas), frente a 0 apariciones del artículo sin tilde en estas mismas construcciones ("el de " 0x; "en el que" 0x; los únicos "el que" sin tilde son del tipo nominalizador "el que + subjuntivo", p.ej. "me aflige el que se levanten", construcción distinta). Excluidas deliberadamente ~29 apariciones de "él" que SÍ son pronombre personal correcto ("hizo él que", "sabía él que", "mandóles él que", "deseando de él que", "contra él de la manera", "trataba él de destruir", etc.). Verificación: las 156 confirmadas independientemente contra el texto OCR de Google del PDF de 1920 (google_text_1920/), que lee "él" en todas; imágenes cotejadas a zoom en Alma 43:21 (pages_1920/page_0387.png) y Alma 62:6 (page_0449.png). 1886: el texto OCR del PDF de 1886 (localizado por página vía chapter_map.csv) lee "el" sin tilde en ~141 de las 156 posiciones; ~5 las lee con tilde (1 Nefi 7:5, Mosíah 18:27, III Nefi 4:17, III Nefi 29:7, Mormón 9:17 -- sin verificar contra imagen) y el resto quedan indeterminadas (redacción distinta u OCR ilegible). Conteo global en 1886: "en el que" 22x vs "en él que" 1x; "mayor que el de" 4x vs 0x. Imagen de 1886 cotejada en Alma 40:6 y 40:9 (pages_1886/page_0371.png: "y el de la resurreccion" en ambos -- corrige la entrada suelta anterior de Alma 40:6, que decía "él de en 1886"), Alma 43:21 (page_0380.png, "el de los Nefitas") y Alma 62:6 (page_0442.png, "el de los partidarios"). Conclusión: la forma con tilde es, en esencia, EXCLUSIVA DE 1920; 1886 usa el artículo correcto. Edición moderna en español (churchofjesuschrist.org, cotejada 2026-09-23): Alma 43:21 "mucho mayor que el de los nefitas"; Alma 40:6 "y el de la resurrección"; Éter 12:38 y Alma 62:6 reformulados sin la construcción. Subgrupo dudoso (anotado, no exclui
A45: 44 | B45: 1 Nefi | C45: 7 | D45: 15 | E45: 14 | F45: texto | H45: a | I45: á | J45: familia | K45: con su cotejo de 1886 | L45: preposición "a" sin tilde | M45: -> _cleaned: "á" (o "a", según la norma que fije el editor para toda la edición | O45: 99 | U45: FAMILIA preposición "a" sin tilde (por "á") -- ENTRADA MAESTRA (2026-10-05, abierta durante el `manual-proofread` de Mormón 9, a partir de Mormón 9:22 "sí, y también a todos sus discípulos"; aprobada por el editor). 1920 escribe la preposición con tilde ("á") como norma de toda la edición (miles de casos), pero en estos lugares la imprime sin ella. Cada uno confirmado en el OCR de Google del PDF de 1920 (google_text_1920/) y, para los añadidos ahora, a la vista en un recorte de la imagen de 1920 (salvo 2 Nefi 27:14, 28:16, Mosíah 2:25, 29:39, Alma 4:12, 16:13 y III Nefi 14:9, confirmados solo por el OCR de Google). Distinta de la FAMILIA "vino á suceder"/"vino a suceder" (que no se repite aquí) y de dos casos que NO son esta preposición sino una "l" perdida: Alma 24:6 "a Señor" (= "al Señor", entrada propia) y Éther 14:13 "le dió a batalla" (= "la batalla", pendiente para el `manual-proofread` de Éther 14). YA REGISTRADAS POR SEPARADO (con su cotejo de 1886; se conservan, esta entrada solo las agrupa): Alma 44:3, 52:2, 57:18, 61:1, 62:43; Helamán 10:9, 11:4 (compartido con 1886), 13:17, 15:12; III Nefi 16:4; Éther 2:14; notas III Nefi 10f (3594) y Éther 5d (4369). NUEVAS (2026-10-05; libro capítulo:versículo, pág.; texto): 1 Nefi 7:15 (14) "volver a Jerusalem"; 2 Nefi 1:7 (58) "conduzca a ella"; 2 Nefi 27:14 (116) "procederá a traer"; 2 Nefi 28:16 (120) "súbitamente a los habitantes"; Jacob 5:18 (141) "y a causa de la mucha fuerza"; Jacob 7:9 (150) "¿Niegas tú a Cristo"; Jarom 1:7 (155) "venían a guerrear"; Mosíah 1:7 (163) "las promesas que el Señor hizo a vuestros padres" ("a" a final de renglón); Mosíah 2:25 (166) "él pertenece a Él"; Mosíah 29:39 (234) "vinieron a reunirse"; Alma 4:12 (246) "a los necesitados"; Alma 15:17 (284) "ya a humillarse"; Alma 16:13 (285) "fabricados a la moda judaica"; Alma 22:21 (305) "fueran a llamar al pueblo"; Alma 31:32 (333) "tanto a mí, como á mis colaboradores"; Alma 32:34 (336) "ha dilatado a vuestras almas"; Helamán 13, encabezamiento (469) "Profecia de Samuel, el Lamanita, a los Nefitas"; III Nefi 3:7 (487) "uníos a nosotros"; III Nefi 14:9 (516) "de vosotros, a quién"; Mormón 9:22 (575) "y también a todos sus discípulos" (1886, file 589: "y tambien á todos" -> exclusiva de 1920); Éther 9:28 (597) "llamando a sus habitantes"; Éther 14:11 (610) "dió la batalla a Lib". 1886: cotejado solo en Mormón 9:22 (con tilde) y en las entradas ya registradas; el resto sin cotejar. TOTAL DE LA FAMILIA: 13 ya registradas + 22 nuevas = 35. -> _cleaned: "á" (o "a", según la norma que fije el editor para toda la edición); preservadas como se imprimen en librodm_transcribed.
A46: 45 | B46: 1 Nefi | C46: 7 | D46: 15 | E46: 14 | F46: texto | H46: ("cuando" + futuro de indicativo en oración temporal de futuro) | I46: (ver la entrada de la familia) | J46: familia | K46: 11, todas COMPARTIDAS CON 1886 -- cotejo en la capa de texto del PDF de 1886 | L46: "cuando" + futuro de indicativo en oración temporal de futuro | M46: -> _cleaned (opcional, a decidir por el editor | N46: forma no hallada en este versículo: quizá cita de comparación, no error -- verificar | O46: 102 | U46: FAMILIA "cuando" + futuro de indicativo en oración temporal de futuro (por presente o futuro de subjuntivo) -- ARCAÍSMO / USO RARO DE REGISTRO BÍBLICO, NO ERROR (reclasificado 2026-10-09) -- ENTRADA MAESTRA (2026-10-09, abierta durante el `manual-proofread` de Éther 4, a partir de Éther 4:15 "cuando desgarraréis ese velo"). NORMA: la oración temporal con "cuando" referida al futuro lleva subjuntivo ("cuando recibáis", o en la lengua antigua "cuando recibiereis"), nunca futuro de indicativo. CORDE (consultas del editor, 2026-10-09): "cuando recibiréis" 0, "cuando vendréis" 0 y "cuando clamaréis" 0, frente a "cuando recibáis" 2 y "cuando vengáis" 5 (1582 carta de Felipe II, Castillo Solórzano 1628-1629, Fernández Navarrete 1830, Castelar 1862, Galdós 1902) -> la forma con subjuntivo es la normal. PERO "cuando vendrá" (consulta del editor, 2026-10-09) da 7 resultados, entre ellos oraciones temporales de futuro auténticas con futuro de indicativo: Reina-Valera 1909, Marcos 8:38 "se avergonzará también de él, cuando vendrá en la gloria de su Padre", y Ribadeneira 1595 "cuando vendrá el mismo pueblo á suplicarle"; y la construcción enfática "será... cuando" + futuro: Reina-Valera 1909, Ezequiel 38:18 "Y será en aquel tiempo, cuando vendrá Gog", y Rodó 1900 "Es hoy cuando vendrá" (este tipo cubre Helamán 13:32). CONCLUSIÓN: construcción minoritaria pero documentada en el registro bíblico (la propia Reina-Valera 1909), no agramatical en ese registro; se registra como arcaísmo/rareza, igual que Mormón 8:35 "me os". Además, el propio libro usa la forma correcta con el mismo verbo y en la misma construcción: Moroni 10:3-4 "cuando leáis estas cosas... Y cuando recibáis estas cosas" (pág. 628), frente a Éther 4:17 "cuando recibiréis estos anales". Barrido de todo "cuando" + forma de futuro en librodm.txt (25 casos) revisado a mano; se EXCLUYEN: subjuntivos ("veamos", "encontréis", "administréis", "llegue", "hayas", "veáis"); futuro de la oración principal (1 Nefi 7:15); interrogativas indirectas, donde el futuro es correcto (Alma 5:29 "no sabe él cuando vendrá el tiempo", Alma 40:4 "cuando vendrá ese tiempo... nadie lo sabe", III Nefi 21:1 "para que conozcáis cuando... cuando yo recogeré"); y "cuando" explicativo con antecedente temporal expreso, donde el indicativo es admisible (2 Nefi 9:2 "la época de su restauración..., cuando serán juntados", 2 Nefi 9:44 "en el postrer día, cuando todos los hombres serán juzgados", 2 Nefi 26:14 "los días cuando el Señor traerá", Moroni 8:26 "el fin, cuando todos los santos habitarán"). APARICIONES (11, todas COMPARTIDAS CON 1886 -- cotejo en la capa de texto del PDF de 1886): 2 Nefi 13:6 "Cuando el hombre agarrará á su hermano" (Isaías 3:6; pág. 90; 1886 file 107); 2 Nefi 14:4 "Cuando el Señor habrá lavado la inmundicia" (Isaías 4:4; pág. 91; file 108; la Reina-Valera en el mismo versículo trae futuro de subjuntivo: "Cuando el Señor lavare las inmundicias de las hijas de Sión, y limpiare las sangres de Jerusalem", verific
A47: 46 | B47: 1 Nefi | C47: 7 | D47: 17 | E47: 14 | F47: texto | H47: Quién | I47: Quien | J47: familia | K47: . USO DE ÉPOCA COMPROBADO: 1886 | L47: relativos "quién/quiénes" y "dónde" con tilde | M47: en librodm_cleaned, suprimir la tilde en las 289 (y conservarla en las 14 excluidas | O47: 87 | U47: FAMILIA relativos "quién/quiénes" y "dónde" con tilde (tilde diacrítica de interrogativo puesta sobre el RELATIVO) -- ENTRADA MAESTRA (2026-09-24, abierta durante el `manual-proofread` de Alma 52, a partir de Alma 52:12 "con quiénes marchó" y 52:27 "ciudad de Abundancia, dónde se encontraton"). NORMA DE ÉPOCA: el Prontuario de ortografía de la lengua castellana de la RAE (1844, oficial para las escuelas por Real Orden) prescribe la tilde en "que, como, cuando, quien, cual, donde y cuanto" solo "siempre que den principio a una cláusula de interrogación o de admiración", y además, sin signos de interrogación, "en los casos en que, para dar la debida entonación a la frase, sea preciso detenerse algo más que de ordinario" en la sílaba (1844: 26-27, citado en M. Peñalver Castillo, Anuario de Letras III-2, 2015) -- es decir, en las interrogativas indirectas tónicas ("no sé quién vino"), NUNCA en el relativo átono ("el hombre á quien vi"); la Gramática de 1870 mantiene la distinción; la norma actual (RAE, Ortografía 2010; DPD s.v. "quién") es la misma. Con "haber/tener": con infinitivo es interrogativo y lleva tilde ("no tenía á quién dejar el reino"); con verbo conjugado es relativo y no la lleva ("no hay quien pueda interpretar"). USO DE ÉPOCA COMPROBADO: 1886 (OCR del PDF completo) escribe el relativo SIEMPRE sin tilde -- fuera de preguntas: 355 "quien/quienes" sin tilde, 146 "donde" sin tilde, 0 "dónde" con tilde, y solo 2 "Quién" con tilde que resultan ser preguntas a las que les falta el "¿" inicial; dentro de preguntas lee 45 "quién" y 9 "dónde" con tilde, prueba de que el OCR sí capta las tildes. La Reina-Valera 1909 (NT, ortografía de época: "á", "fué") sigue la norma de 1844 al pie de la letra: relativos sin tilde ("á quien vosotros no conocéis", "Sobre quien vieres descender") y tilde solo en interrogativas indirectas ("dudando de quién decía", "no sabemos dónde le han puesto"). (El corpus del Quijote de workspace/reference_corpora/ NO sirve como prueba de época: es edición con ortografía moderna -- "fue", "vio", sin "á".) COTEJO POSICIÓN POR POSICIÓN CON 1886 (2026-09-24): (a) automático -- de las 281 posiciones, 276 localizadas en el OCR de 1886 por su contexto, TODAS sin tilde (0 con tilde; 5 no localizadas por ruido del OCR); (b) comprobación visual en las imágenes de 1886 (muestra pedida por el editor), 11 lugares fuera de pregunta, TODOS sin tilde: 1 Nefi 4:26 "á quien yo había matado" (file 28), 1 Nefi 10:8 "á quien no conocéis, quien es más poderoso... de quien no soy digno" (37), 1 Nefi 19:10 "á quienes sacó" (67), Mosíah 7:9 "quien era hijo de Zeniff, quien fué hecho rey" (193), Mosíah 26:21 "Y quien oyere mi voz" (239), Alma 13:15 "á quien Abraham pagaba" (291), Alma 29:5 "quien no conoce... quien distingue" (337), Alma 52:12 "con quienes marchó" (410), Helamán 6:30 "él es quien dirige... él es quien trasmite" (467), Éther 9:14 "á quien llamó Émer" (610), Alma 56:15 "donde encontré" (422), III Nefi 27:11 "de donde no se vuelve" (55
A48: 47 | B48: 1 Nefi | C48: 8 | D48: 9 | E48: 15 | F48: texto | H48: inmediatemente | I48: inmediatamente | J48: letra(s) | K48: inmediatemente en 1886 | O48: 40 | U48: 1 Nefi 8:9 inmediatemente (inmediatamente) (inmediatemente en 1886)
A49: 48 | B49: 1 Nefi | C49: 8 | D49: 15 | E49: 15 | F49: texto | H49: equel fruto | I49: aquel fruto | J49: letra(s) | K49: aquel fruto en 1886 | O49: 41 | U49: 1 Nefi 8:15 equel fruto (aquel fruto) (aquel fruto en 1886)
A50: 49 | B50: 1 Nefi | C50: 8 | D50: 20 | E50: 16 | F50: texto | H50: extención | I50: extensión | J50: letra(s) | K50: 1886 en este lugar exacto | M50: -> _cleaned: corregir a "extensión" | O50: 42 | U50: 1 Nefi 8:20 extención (extensión) (1920 imprime "por toda la extención de la barra" con "c" por "s", página 16; confirmado a zoom (pages_1920/page_0038.png); 1886 en este lugar exacto (pages_1886/page_0034.png, book page 16/file 34) imprime IGUALMENTE "extencion" -- ERROR COMPARTIDO CON 1886, heredado; la propia 1920 escribe "extensión" con "s" 8x en otros lugares (incl. Mormón 9:33); "extención" = 0 en Quijote/RV1909/RV-full; -> _cleaned: corregir a "extensión"; preservado como se imprime en librodm_transcribed; hallado en la auditoría de permitted words.txt 2026-09-09)
A51: 50 | B51: 1 Nefi | C51: 8 | D51: 23 | E51: 16 | F51: texto | H51: aconetció | I51: aconteció | J51: letra(s) | K51: aconteció en 1886 | O51: 43 | U51: 1 Nefi 8:23 aconetció (aconteció) (aconteció en 1886)
A52: 51 | B52: 1 Nefi | C52: 8 | D52: 26 | E52: 16 | F52: nota | G52: 45 (8f) | H52: I Nefi 9:31,33 | I52: cita imposible: I Nefi 9 tiene 6 versículos | J52: palabra(s)/gramática | O52: 44 | U52: Footnote 1 Nefi 8f, 45 I Nefi 9:31,33 (cita imposible: I Nefi 9 tiene 6 versículos) (1920 imprime "I Nefi 9:31,33; 11:35-36"; 1879 imprime lo mismo, "f, I. Nep. 9: 31, 33. 11: 35, 36" (pages_1879/page_0024.png) -- error heredado de 1879, no exclusivo de 1920, como en Footnote Mosiah 2q "II Nefi 2:37"; destino correcto no determinado; hallado 2026-10-17 en el cotejo de notas con 1879 (item 5b); la transcripción coincide con la impresión de 1920)
A53: 52 | B53: 1 Nefi | C53: 8 | D53: 27 | E53: 16 | F53: texto | H53: Él | I53: El | J53: familia | K53: . 1886: el texto OCR del PDF de 1886 | L53: "él" por "el" | M53: _cleaned`, normalizar a "el" sin tilde | O53: 85 | U53: FAMILIA "él" por "el" (artículo acentuado como pronombre ante "de"/"que") -- ENTRADA MAESTRA (2026-09-23, abierta durante el `manual-proofread` de Alma 43; consolida las entradas antes sueltas de Alma 40:6, Mormón 6:21 y Éther 12:38). 1920 imprime sistemáticamente con tilde el ARTÍCULO "el" cuando va ante "de"/"del" (sustantivo elidido: "mayor que él de los Nefitas" = "mayor que el [número] de los Nefitas"; "y él de su familia" = "y el [corazón] de su familia") o ante el relativo "que" ("en él que" = "en el que", "él que busque, halla" = "el que busque, halla", aposición "José, él que fué llevado"). Según la RAE (tilde diacrítica: "él" pronombre personal tónico / "el" artículo átono), en todas estas posiciones corresponde "el" SIN tilde; la forma con tilde leída literalmente significa "él" (he/him), lo que rompe la gramática. Clasificación del editor (2026-09-23): "gringismo" -- error de un hablante de español como segunda lengua (probable calco de "he that..." / "that of..." del inglés), no una variante de época: no se halló ninguna fuente normativa ni histórica que lo avale, y la ortografía académica del siglo XIX ya distinguía "él"/"el". Alcance: 156 apariciones en el cuerpo de librodm.txt (ninguna en los bloques de notas), frente a 0 apariciones del artículo sin tilde en estas mismas construcciones ("el de " 0x; "en el que" 0x; los únicos "el que" sin tilde son del tipo nominalizador "el que + subjuntivo", p.ej. "me aflige el que se levanten", construcción distinta). Excluidas deliberadamente ~29 apariciones de "él" que SÍ son pronombre personal correcto ("hizo él que", "sabía él que", "mandóles él que", "deseando de él que", "contra él de la manera", "trataba él de destruir", etc.). Verificación: las 156 confirmadas independientemente contra el texto OCR de Google del PDF de 1920 (google_text_1920/), que lee "él" en todas; imágenes cotejadas a zoom en Alma 43:21 (pages_1920/page_0387.png) y Alma 62:6 (page_0449.png). 1886: el texto OCR del PDF de 1886 (localizado por página vía chapter_map.csv) lee "el" sin tilde en ~141 de las 156 posiciones; ~5 las lee con tilde (1 Nefi 7:5, Mosíah 18:27, III Nefi 4:17, III Nefi 29:7, Mormón 9:17 -- sin verificar contra imagen) y el resto quedan indeterminadas (redacción distinta u OCR ilegible). Conteo global en 1886: "en el que" 22x vs "en él que" 1x; "mayor que el de" 4x vs 0x. Imagen de 1886 cotejada en Alma 40:6 y 40:9 (pages_1886/page_0371.png: "y el de la resurreccion" en ambos -- corrige la entrada suelta anterior de Alma 40:6, que decía "él de en 1886"), Alma 43:21 (page_0380.png, "el de los Nefitas") y Alma 62:6 (page_0442.png, "el de los partidarios"). Conclusión: la forma con tilde es, en esencia, EXCLUSIVA DE 1920; 1886 usa el artículo correcto. Edición moderna en español (churchofjesuschrist.org, cotejada 2026-09-23): Alma 43:21 "mucho mayor que el de los nefitas"; Alma 40:6 "y el de la resurrección"; Éter 12:38 y Alma 62:6 reformulados sin la construcción. Subgrupo dudoso (anotado, no exclui
A54: 53 | B54: 1 Nefi | C54: 10 | D54: 4 | E54: 18 | F54: texto | H54: seis cientos | I54: seiscientos | J54: puntuación/espacio | K54: ición de 1920 escribe "seiscientos" 4 veces; 1886 en este lugar | O54: 45 | U54: 1 Nefi 10:4 seis cientos (seiscientos) (1920 imprime "Sí, aun seis cientos años desde la época en que mi padre salió de Jerusalem", página 18, con la centena partida en dos palabras; confirmado en el OCR de Google del PDF de 1920 ("seis cientos años", pages_1920/page_0040.png); la RAE escribe las centenas en una sola palabra (Autoridades "seiscientos"/"quatrocientos"; DRAE) y la propia edición de 1920 escribe "seiscientos" 4 veces; 1886 en este lugar (OCR, file 37) imprime también "séis cientos" separado -> ERROR COMPARTIDO CON 1886; pareja con Alma 63:4 "cuatro cientos"; registrado por decisión del editor (2026-09-26), hallado en el `manual-proofread` de Alma 63; preservado como se imprime)
A55: 54 | B55: 1 Nefi | C55: 10 | D55: 8 | E55: 18 | F55: texto | H55: él | I55: el | J55: familia | K55: . 1886: el texto OCR del PDF de 1886 | L55: "él" por "el" | M55: _cleaned`, normalizar a "el" sin tilde | O55: 85 | U55: FAMILIA "él" por "el" (artículo acentuado como pronombre ante "de"/"que") -- ENTRADA MAESTRA (2026-09-23, abierta durante el `manual-proofread` de Alma 43; consolida las entradas antes sueltas de Alma 40:6, Mormón 6:21 y Éther 12:38). 1920 imprime sistemáticamente con tilde el ARTÍCULO "el" cuando va ante "de"/"del" (sustantivo elidido: "mayor que él de los Nefitas" = "mayor que el [número] de los Nefitas"; "y él de su familia" = "y el [corazón] de su familia") o ante el relativo "que" ("en él que" = "en el que", "él que busque, halla" = "el que busque, halla", aposición "José, él que fué llevado"). Según la RAE (tilde diacrítica: "él" pronombre personal tónico / "el" artículo átono), en todas estas posiciones corresponde "el" SIN tilde; la forma con tilde leída literalmente significa "él" (he/him), lo que rompe la gramática. Clasificación del editor (2026-09-23): "gringismo" -- error de un hablante de español como segunda lengua (probable calco de "he that..." / "that of..." del inglés), no una variante de época: no se halló ninguna fuente normativa ni histórica que lo avale, y la ortografía académica del siglo XIX ya distinguía "él"/"el". Alcance: 156 apariciones en el cuerpo de librodm.txt (ninguna en los bloques de notas), frente a 0 apariciones del artículo sin tilde en estas mismas construcciones ("el de " 0x; "en el que" 0x; los únicos "el que" sin tilde son del tipo nominalizador "el que + subjuntivo", p.ej. "me aflige el que se levanten", construcción distinta). Excluidas deliberadamente ~29 apariciones de "él" que SÍ son pronombre personal correcto ("hizo él que", "sabía él que", "mandóles él que", "deseando de él que", "contra él de la manera", "trataba él de destruir", etc.). Verificación: las 156 confirmadas independientemente contra el texto OCR de Google del PDF de 1920 (google_text_1920/), que lee "él" en todas; imágenes cotejadas a zoom en Alma 43:21 (pages_1920/page_0387.png) y Alma 62:6 (page_0449.png). 1886: el texto OCR del PDF de 1886 (localizado por página vía chapter_map.csv) lee "el" sin tilde en ~141 de las 156 posiciones; ~5 las lee con tilde (1 Nefi 7:5, Mosíah 18:27, III Nefi 4:17, III Nefi 29:7, Mormón 9:17 -- sin verificar contra imagen) y el resto quedan indeterminadas (redacción distinta u OCR ilegible). Conteo global en 1886: "en el que" 22x vs "en él que" 1x; "mayor que el de" 4x vs 0x. Imagen de 1886 cotejada en Alma 40:6 y 40:9 (pages_1886/page_0371.png: "y el de la resurreccion" en ambos -- corrige la entrada suelta anterior de Alma 40:6, que decía "él de en 1886"), Alma 43:21 (page_0380.png, "el de los Nefitas") y Alma 62:6 (page_0442.png, "el de los partidarios"). Conclusión: la forma con tilde es, en esencia, EXCLUSIVA DE 1920; 1886 usa el artículo correcto. Edición moderna en español (churchofjesuschrist.org, cotejada 2026-09-23): Alma 43:21 "mucho mayor que el de los nefitas"; Alma 40:6 "y el de la resurrección"; Éter 12:38 y Alma 62:6 reformulados sin la construcción. Subgrupo dudoso (anotado, no exclui
A56: 55 | B56: 1 Nefi | C56: 10 | D56: 8 | E56: 18 | F56: texto | H56: Quién | I56: Quien | J56: familia | K56: . USO DE ÉPOCA COMPROBADO: 1886 | L56: relativos "quién/quiénes" y "dónde" con tilde | M56: en librodm_cleaned, suprimir la tilde en las 289 (y conservarla en las 14 excluidas | O56: 87 | U56: FAMILIA relativos "quién/quiénes" y "dónde" con tilde (tilde diacrítica de interrogativo puesta sobre el RELATIVO) -- ENTRADA MAESTRA (2026-09-24, abierta durante el `manual-proofread` de Alma 52, a partir de Alma 52:12 "con quiénes marchó" y 52:27 "ciudad de Abundancia, dónde se encontraton"). NORMA DE ÉPOCA: el Prontuario de ortografía de la lengua castellana de la RAE (1844, oficial para las escuelas por Real Orden) prescribe la tilde en "que, como, cuando, quien, cual, donde y cuanto" solo "siempre que den principio a una cláusula de interrogación o de admiración", y además, sin signos de interrogación, "en los casos en que, para dar la debida entonación a la frase, sea preciso detenerse algo más que de ordinario" en la sílaba (1844: 26-27, citado en M. Peñalver Castillo, Anuario de Letras III-2, 2015) -- es decir, en las interrogativas indirectas tónicas ("no sé quién vino"), NUNCA en el relativo átono ("el hombre á quien vi"); la Gramática de 1870 mantiene la distinción; la norma actual (RAE, Ortografía 2010; DPD s.v. "quién") es la misma. Con "haber/tener": con infinitivo es interrogativo y lleva tilde ("no tenía á quién dejar el reino"); con verbo conjugado es relativo y no la lleva ("no hay quien pueda interpretar"). USO DE ÉPOCA COMPROBADO: 1886 (OCR del PDF completo) escribe el relativo SIEMPRE sin tilde -- fuera de preguntas: 355 "quien/quienes" sin tilde, 146 "donde" sin tilde, 0 "dónde" con tilde, y solo 2 "Quién" con tilde que resultan ser preguntas a las que les falta el "¿" inicial; dentro de preguntas lee 45 "quién" y 9 "dónde" con tilde, prueba de que el OCR sí capta las tildes. La Reina-Valera 1909 (NT, ortografía de época: "á", "fué") sigue la norma de 1844 al pie de la letra: relativos sin tilde ("á quien vosotros no conocéis", "Sobre quien vieres descender") y tilde solo en interrogativas indirectas ("dudando de quién decía", "no sabemos dónde le han puesto"). (El corpus del Quijote de workspace/reference_corpora/ NO sirve como prueba de época: es edición con ortografía moderna -- "fue", "vio", sin "á".) COTEJO POSICIÓN POR POSICIÓN CON 1886 (2026-09-24): (a) automático -- de las 281 posiciones, 276 localizadas en el OCR de 1886 por su contexto, TODAS sin tilde (0 con tilde; 5 no localizadas por ruido del OCR); (b) comprobación visual en las imágenes de 1886 (muestra pedida por el editor), 11 lugares fuera de pregunta, TODOS sin tilde: 1 Nefi 4:26 "á quien yo había matado" (file 28), 1 Nefi 10:8 "á quien no conocéis, quien es más poderoso... de quien no soy digno" (37), 1 Nefi 19:10 "á quienes sacó" (67), Mosíah 7:9 "quien era hijo de Zeniff, quien fué hecho rey" (193), Mosíah 26:21 "Y quien oyere mi voz" (239), Alma 13:15 "á quien Abraham pagaba" (291), Alma 29:5 "quien no conoce... quien distingue" (337), Alma 52:12 "con quienes marchó" (410), Helamán 6:30 "él es quien dirige... él es quien trasmite" (467), Éther 9:14 "á quien llamó Émer" (610), Alma 56:15 "donde encontré" (422), III Nefi 27:11 "de donde no se vuelve" (55
A57: 56 | B57: 1 Nefi | C57: 10 | D57: 9 | E57: 19 | F57: texto | H57: Betabara | I57: Betábara | J57: tilde | K57: Bethabary en 1886 | O57: 46 | U57: 1 Nefi 10:9 Betabara (Betábara) (Bethabary en 1886)
A58: 57 | B58: 1 Nefi | C58: 10 | D58: 10 | E58: 19 | F58: texto | H58: Quién | I58: Quien | J58: familia | K58: . USO DE ÉPOCA COMPROBADO: 1886 | L58: relativos "quién/quiénes" y "dónde" con tilde | M58: en librodm_cleaned, suprimir la tilde en las 289 (y conservarla en las 14 excluidas | O58: 87 | U58: FAMILIA relativos "quién/quiénes" y "dónde" con tilde (tilde diacrítica de interrogativo puesta sobre el RELATIVO) -- ENTRADA MAESTRA (2026-09-24, abierta durante el `manual-proofread` de Alma 52, a partir de Alma 52:12 "con quiénes marchó" y 52:27 "ciudad de Abundancia, dónde se encontraton"). NORMA DE ÉPOCA: el Prontuario de ortografía de la lengua castellana de la RAE (1844, oficial para las escuelas por Real Orden) prescribe la tilde en "que, como, cuando, quien, cual, donde y cuanto" solo "siempre que den principio a una cláusula de interrogación o de admiración", y además, sin signos de interrogación, "en los casos en que, para dar la debida entonación a la frase, sea preciso detenerse algo más que de ordinario" en la sílaba (1844: 26-27, citado en M. Peñalver Castillo, Anuario de Letras III-2, 2015) -- es decir, en las interrogativas indirectas tónicas ("no sé quién vino"), NUNCA en el relativo átono ("el hombre á quien vi"); la Gramática de 1870 mantiene la distinción; la norma actual (RAE, Ortografía 2010; DPD s.v. "quién") es la misma. Con "haber/tener": con infinitivo es interrogativo y lleva tilde ("no tenía á quién dejar el reino"); con verbo conjugado es relativo y no la lleva ("no hay quien pueda interpretar"). USO DE ÉPOCA COMPROBADO: 1886 (OCR del PDF completo) escribe el relativo SIEMPRE sin tilde -- fuera de preguntas: 355 "quien/quienes" sin tilde, 146 "donde" sin tilde, 0 "dónde" con tilde, y solo 2 "Quién" con tilde que resultan ser preguntas a las que les falta el "¿" inicial; dentro de preguntas lee 45 "quién" y 9 "dónde" con tilde, prueba de que el OCR sí capta las tildes. La Reina-Valera 1909 (NT, ortografía de época: "á", "fué") sigue la norma de 1844 al pie de la letra: relativos sin tilde ("á quien vosotros no conocéis", "Sobre quien vieres descender") y tilde solo en interrogativas indirectas ("dudando de quién decía", "no sabemos dónde le han puesto"). (El corpus del Quijote de workspace/reference_corpora/ NO sirve como prueba de época: es edición con ortografía moderna -- "fue", "vio", sin "á".) COTEJO POSICIÓN POR POSICIÓN CON 1886 (2026-09-24): (a) automático -- de las 281 posiciones, 276 localizadas en el OCR de 1886 por su contexto, TODAS sin tilde (0 con tilde; 5 no localizadas por ruido del OCR); (b) comprobación visual en las imágenes de 1886 (muestra pedida por el editor), 11 lugares fuera de pregunta, TODOS sin tilde: 1 Nefi 4:26 "á quien yo había matado" (file 28), 1 Nefi 10:8 "á quien no conocéis, quien es más poderoso... de quien no soy digno" (37), 1 Nefi 19:10 "á quienes sacó" (67), Mosíah 7:9 "quien era hijo de Zeniff, quien fué hecho rey" (193), Mosíah 26:21 "Y quien oyere mi voz" (239), Alma 13:15 "á quien Abraham pagaba" (291), Alma 29:5 "quien no conoce... quien distingue" (337), Alma 52:12 "con quienes marchó" (410), Helamán 6:30 "él es quien dirige... él es quien trasmite" (467), Éther 9:14 "á quien llamó Émer" (610), Alma 56:15 "donde encontré" (422), III Nefi 27:11 "de donde no se vuelve" (55
A59: 58 | B59: 1 Nefi | C59: 10 | D59: 13 | E59: 19 | F59: texto | H59: unánimemente | I59: (ver la entrada de la familia) | J59: familia | K59: la práctica DOMINANTE de la edición de 1920. 1886: comparte la omisión en la mayoría de los lugares | L59: adverbios en -mente sin tilde | M59: -> _cleaned: añadir a TODAS las apariciones la tilde del adjetivo base | O59: 198 | U59: FAMILIA adverbios en -mente sin tilde (por -mente CON la tilde del adjetivo base) -- ENTRADA MAESTRA (2026-09-09; consolida las entradas antes dispersas de Jacob 5:71, Alma 7:15, Alma 46:8, Alma 59:3, Alma 59:9, Alma 62:21, Éther 9:30 y Moroni 7:45). Regla (RAE, estable): el adverbio en -mente conserva la tilde que el adjetivo base lleva por sí solo ("fácil">"fácilmente"; "rápido">"rápidamente"; "único">"únicamente"; "áspero">"ásperamente"; "intrépido">"intrépidamente"; "plácido">"plácidamente"; "enérgico">"enérgicamente"). Alcance: `grep -nE "\b(facil|rapida|unica|aspera|intrepida|placida|energica)mente\b" librodm_transcribed.txt` -> 22 apariciones sin tilde (facilmente x9, rapidamente x6, intrepidamente x4, unicamente x2, asperamente x1, placidamente x1, energicamente x1), frente a solo 3 con tilde (rápidamente 1, fácilmente 1, intrépidamente 1) -> dejar el adverbio en -mente sin tilde es la práctica DOMINANTE de la edición de 1920. 1886: comparte la omisión en la mayoría de los lugares cotejados (facilmente Alma 7:15/46:8/59:3/59:9/Moroni 7:45; rapidamente Alma 62:21/Éther 9:30); heredado, no introducido en 1920. Atestiguación externa: la forma SIN tilde = CERO en los corpus limpios (Quijote 0, Reina-Valera 1909 NT 0 para facilmente/rapidamente/etc.); la forma CON tilde sí está atestiguada (Quijote: fácilmente 9, ásperamente 1, intrépidamente 1, difícilmente 1; RV 1909 NT: fácilmente 1). La Reina-Valera de 1909 -- de fecha intermedia entre 1886 y 1920 -- ya acentúa "fácilmente", de modo que la práctica correcta estaba vigente en la época. Edición moderna (churchofjesuschrist.org): acentúa (p.ej. "no se irrita fácilmente", Moroni 7:45). -> _cleaned: añadir a TODAS las apariciones la tilde del adjetivo base. Omisión sistemática de tilde de época (compartida con 1886), no una variante legítima ni un error puntual. Preservado como se imprime en librodm_transcribed. AMPLIACIÓN (2026-09-26/27, `manual-proofread` de Helamán 1): dos apariciones que la transcripción había "corregido" en silencio añadiendo la tilde, restituidas ahora a la forma impresa tras comprobar cada adverbio acentuado de librodm.txt contra el OCR de Google: Helamán 1:33 "hizo enviar pacificamente fuera del país" (página 436, pages_1920/page_0458.png, confirmado a zoom; "pacífico" > "pacíficamente"; 1886 file 451 también "pacifi-camente" sin tilde -> compartido) y Helamán 8:19 "que intrepidamente dió testimonio de Él" (página 457, pages_1920/page_0479.png, confirmado en la imagen -- era el único "intrépidamente" acentuado del recuento). Los otros 5 adverbios acentuados (unánimemente 1 Nefi 10:13, rápidamente 1 Nefi 22:24, fácilmente 2 Nefi 4:18, súbitamente 2 Nefi 28:16, rígidamente Mosíah 13:30) coinciden con el OCR de Google (tilde impresa). NUEVO RECUENTO (grep sobre librodm.txt, 2026-09-27; el recuento original de 2026-09-09 decía "facilmente x9", pero hoy aparecen 7): 24 sin tilde (facilmente x7, rapidamente x6, intrepidamente x5, unicamente x2, asperamente x1, placidamente x1
A60: 59 | B60: 1 Nefi | C60: 10 | D60: 14 | E60: 19 | F60: texto | H60: ingertos | I60: injertos | J60: letra(s) | K60: ingertos en 1886 | O60: 47 | U60: 1 Nefi 10:14 ingertos (injertos) (ingertos en 1886)
A61: 60 | B61: 1 Nefi | C61: 11 | D61: 1 | E61: 20 | F61: texto | H61: fuí llevando | I61: fuí llevado | J61: letra(s) | K61: llevado en 1886 | O61: 48 | U61: 1 Nefi 11:1 fuí llevando (fuí llevado) (llevado en 1886)
A62: 61 | B62: 1 Nefi | C62: 11 | D62: 6 | E62: 20 | F62: texto | H62: Hosana | I62: Hosanna | J62: letra(s) | K62: Hosana en 1886 | O62: 49 | U62: 1 Nefi 11:6 Hosana (Hosanna) (Hosana en 1886)
A63: 62 | B63: 1 Nefi | C63: 11 | D63: 27 | E63: 22 | F63: texto | H63: Quién | I63: Quien | J63: familia | K63: . USO DE ÉPOCA COMPROBADO: 1886 | L63: relativos "quién/quiénes" y "dónde" con tilde | M63: en librodm_cleaned, suprimir la tilde en las 289 (y conservarla en las 14 excluidas | O63: 87 | U63: FAMILIA relativos "quién/quiénes" y "dónde" con tilde (tilde diacrítica de interrogativo puesta sobre el RELATIVO) -- ENTRADA MAESTRA (2026-09-24, abierta durante el `manual-proofread` de Alma 52, a partir de Alma 52:12 "con quiénes marchó" y 52:27 "ciudad de Abundancia, dónde se encontraton"). NORMA DE ÉPOCA: el Prontuario de ortografía de la lengua castellana de la RAE (1844, oficial para las escuelas por Real Orden) prescribe la tilde en "que, como, cuando, quien, cual, donde y cuanto" solo "siempre que den principio a una cláusula de interrogación o de admiración", y además, sin signos de interrogación, "en los casos en que, para dar la debida entonación a la frase, sea preciso detenerse algo más que de ordinario" en la sílaba (1844: 26-27, citado en M. Peñalver Castillo, Anuario de Letras III-2, 2015) -- es decir, en las interrogativas indirectas tónicas ("no sé quién vino"), NUNCA en el relativo átono ("el hombre á quien vi"); la Gramática de 1870 mantiene la distinción; la norma actual (RAE, Ortografía 2010; DPD s.v. "quién") es la misma. Con "haber/tener": con infinitivo es interrogativo y lleva tilde ("no tenía á quién dejar el reino"); con verbo conjugado es relativo y no la lleva ("no hay quien pueda interpretar"). USO DE ÉPOCA COMPROBADO: 1886 (OCR del PDF completo) escribe el relativo SIEMPRE sin tilde -- fuera de preguntas: 355 "quien/quienes" sin tilde, 146 "donde" sin tilde, 0 "dónde" con tilde, y solo 2 "Quién" con tilde que resultan ser preguntas a las que les falta el "¿" inicial; dentro de preguntas lee 45 "quién" y 9 "dónde" con tilde, prueba de que el OCR sí capta las tildes. La Reina-Valera 1909 (NT, ortografía de época: "á", "fué") sigue la norma de 1844 al pie de la letra: relativos sin tilde ("á quien vosotros no conocéis", "Sobre quien vieres descender") y tilde solo en interrogativas indirectas ("dudando de quién decía", "no sabemos dónde le han puesto"). (El corpus del Quijote de workspace/reference_corpora/ NO sirve como prueba de época: es edición con ortografía moderna -- "fue", "vio", sin "á".) COTEJO POSICIÓN POR POSICIÓN CON 1886 (2026-09-24): (a) automático -- de las 281 posiciones, 276 localizadas en el OCR de 1886 por su contexto, TODAS sin tilde (0 con tilde; 5 no localizadas por ruido del OCR); (b) comprobación visual en las imágenes de 1886 (muestra pedida por el editor), 11 lugares fuera de pregunta, TODOS sin tilde: 1 Nefi 4:26 "á quien yo había matado" (file 28), 1 Nefi 10:8 "á quien no conocéis, quien es más poderoso... de quien no soy digno" (37), 1 Nefi 19:10 "á quienes sacó" (67), Mosíah 7:9 "quien era hijo de Zeniff, quien fué hecho rey" (193), Mosíah 26:21 "Y quien oyere mi voz" (239), Alma 13:15 "á quien Abraham pagaba" (291), Alma 29:5 "quien no conoce... quien distingue" (337), Alma 52:12 "con quienes marchó" (410), Helamán 6:30 "él es quien dirige... él es quien trasmite" (467), Éther 9:14 "á quien llamó Émer" (610), Alma 56:15 "donde encontré" (422), III Nefi 27:11 "de donde no se vuelve" (55
A64: 63 | B64: 1 Nefi | C64: 12 | D64: 4 | E64: 23 | F64: texto | H64: toda clasa | I64: toda clase | J64: letra(s) | K64: toda clasa en 1886 | O64: 50 | U64: 1 Nefi 12:4 toda clasa (toda clase) (toda clasa en 1886)
A65: 64 | B65: 1 Nefi | C65: 12 | D65: 5 | E65: 23 | F65: texto | H65: Y sudeció | I65: Y sucedió | J65: letra(s) | K65: Y sucedió en 1886 | O65: 51 | U65: 1 Nefi 12:5 Y sudeció (Y sucedió) (Y sucedió en 1886)
A66: 65 | B66: 1 Nefi | C66: 12 | D66: 6 | E66: 23 | F66: texto | H66: Él | I66: El | J66: familia | K66: . 1886: el texto OCR del PDF de 1886 | L66: "él" por "el" | M66: _cleaned`, normalizar a "el" sin tilde | O66: 85 | U66: FAMILIA "él" por "el" (artículo acentuado como pronombre ante "de"/"que") -- ENTRADA MAESTRA (2026-09-23, abierta durante el `manual-proofread` de Alma 43; consolida las entradas antes sueltas de Alma 40:6, Mormón 6:21 y Éther 12:38). 1920 imprime sistemáticamente con tilde el ARTÍCULO "el" cuando va ante "de"/"del" (sustantivo elidido: "mayor que él de los Nefitas" = "mayor que el [número] de los Nefitas"; "y él de su familia" = "y el [corazón] de su familia") o ante el relativo "que" ("en él que" = "en el que", "él que busque, halla" = "el que busque, halla", aposición "José, él que fué llevado"). Según la RAE (tilde diacrítica: "él" pronombre personal tónico / "el" artículo átono), en todas estas posiciones corresponde "el" SIN tilde; la forma con tilde leída literalmente significa "él" (he/him), lo que rompe la gramática. Clasificación del editor (2026-09-23): "gringismo" -- error de un hablante de español como segunda lengua (probable calco de "he that..." / "that of..." del inglés), no una variante de época: no se halló ninguna fuente normativa ni histórica que lo avale, y la ortografía académica del siglo XIX ya distinguía "él"/"el". Alcance: 156 apariciones en el cuerpo de librodm.txt (ninguna en los bloques de notas), frente a 0 apariciones del artículo sin tilde en estas mismas construcciones ("el de " 0x; "en el que" 0x; los únicos "el que" sin tilde son del tipo nominalizador "el que + subjuntivo", p.ej. "me aflige el que se levanten", construcción distinta). Excluidas deliberadamente ~29 apariciones de "él" que SÍ son pronombre personal correcto ("hizo él que", "sabía él que", "mandóles él que", "deseando de él que", "contra él de la manera", "trataba él de destruir", etc.). Verificación: las 156 confirmadas independientemente contra el texto OCR de Google del PDF de 1920 (google_text_1920/), que lee "él" en todas; imágenes cotejadas a zoom en Alma 43:21 (pages_1920/page_0387.png) y Alma 62:6 (page_0449.png). 1886: el texto OCR del PDF de 1886 (localizado por página vía chapter_map.csv) lee "el" sin tilde en ~141 de las 156 posiciones; ~5 las lee con tilde (1 Nefi 7:5, Mosíah 18:27, III Nefi 4:17, III Nefi 29:7, Mormón 9:17 -- sin verificar contra imagen) y el resto quedan indeterminadas (redacción distinta u OCR ilegible). Conteo global en 1886: "en el que" 22x vs "en él que" 1x; "mayor que el de" 4x vs 0x. Imagen de 1886 cotejada en Alma 40:6 y 40:9 (pages_1886/page_0371.png: "y el de la resurreccion" en ambos -- corrige la entrada suelta anterior de Alma 40:6, que decía "él de en 1886"), Alma 43:21 (page_0380.png, "el de los Nefitas") y Alma 62:6 (page_0442.png, "el de los partidarios"). Conclusión: la forma con tilde es, en esencia, EXCLUSIVA DE 1920; 1886 usa el artículo correcto. Edición moderna en español (churchofjesuschrist.org, cotejada 2026-09-23): Alma 43:21 "mucho mayor que el de los nefitas"; Alma 40:6 "y el de la resurrección"; Éter 12:38 y Alma 62:6 reformulados sin la construcción. Subgrupo dudoso (anotado, no exclui
A67: 66 | B67: 1 Nefi | C67: 12 | D67: 11 | E67: 24 | F67: texto | H67: aún | I67: aun | J67: familia | K67: por el mismo camino en que vinieron", donde 1886 lee "aun atrás" | L67: "aún" con tilde por "aun" | M67: en librodm_cleaned, "aun" en (a | O67: 90 | U67: FAMILIA "aún" con tilde por "aun" (= "hasta, incluso, también, siquiera") -- ENTRADA MAESTRA (2026-09-26, abierta durante el `manual-proofread` de Alma 58, a partir de Alma 58:24 "sí, aún atrás por el mismo camino en que vinieron", donde 1886 lee "aun atrás"). NORMA DE ÉPOCA: desde la Gramática de la RAE de 1880 y hasta 1952 la tilde de "aun" se regía por la POSICIÓN: antepuesto a lo que modifica era monosílabo átono y se escribía "aun"; pospuesto era bisílabo tónico y se escribía "aún" (Á. Calderón Rivera, Thesaurus XLVIII, 1993). Las Nuevas normas de prosodia y ortografía de 1952 (regla 17; texto en BRAE XXXVIII, cuad. CLV, pp. 331-347) adoptaron el criterio de SIGNIFICADO que mantiene la RAE actual (Ortografía 2010): "aún" cuando puede sustituirse por "todavía" ("aún está enfermo; está enfermo aún"); "aun" con el sentido de "hasta, también, inclusive (o siquiera, con negación)" ("aun los sordos han de oírme; ni hizo nada por él ni aun lo intentó"). CRITERIO DE ESTA ENTRADA: sólo se registran los casos que AMBAS normas condenan: (a) "aún" con tilde con el sentido de "hasta/incluso/siquiera" y ANTEPUESTO a lo que modifica ("aún hasta la muerte", "aún como", "sí, aún la ley de Moisés", "ni aún entre los Nefitas", "aún cuando" concesivo, "aún así"); (b) "aun" sin tilde con el sentido de "todavía" y POSPUESTO a lo que modifica. EXCLUIDOS, no registrados: los correctos por ambas normas ("aun" = "incluso" antepuesto; "aún" = "todavía" pospuesto: "viven aún", "no ha llegado aún", "os llama aún", "permanecían aún duros"); los que una norma aprueba y la otra condena ("aun/aún" = "todavía" antepuesto: "aun no se ha concluido mi obra", "aun están vivas", "mas aun quedará"); y las construcciones con "más/mayor" ("aun más", "aún más ruin", "aun mayor"), que admiten las dos lecturas. Clasificación hecha a mano sobre las 389 apariciones de "aun/aún" en el cuerpo de librodm.txt (217 "aún", 172 "aun"), con apoyo en el inglés en las dudosas ("even" frente a "yet/still"). USO DE 1886: el OCR del PDF completo tiene 194 "aun/Aun" y un solo "aún" (Alma 20:30 "aún más dura", caso excluido); de las 194 posiciones de esta entrada en el cuerpo, 179 se localizaron automáticamente en 1886 por su contexto, TODAS "aun" sin tilde, y las 15 restantes (no localizadas por ruido del OCR o redacción distinta) tampoco pueden llevarla, pues el único "aún" de 1886 está en Alma 20:30 -> el grupo (a) es EXCLUSIVO DE 1920; el grupo (b) es COMPARTIDO CON 1886. APARICIONES: (a) "aún" por "aun" -- 192 en el cuerpo: 1 Nefi 2:2; 1 Nefi 5:13; 1 Nefi 12:11; 1 Nefi 12:18; 1 Nefi 13:29; 1 Nefi 17:4; 1 Nefi 17:48; 1 Nefi 17:52; 1 Nefi 20:5; 1 Nefi 22:17 x2; 2 Nefi 1:13; 2 Nefi 1:29; 2 Nefi 2:15; 2 Nefi 2:18; 2 Nefi 3:20 x2; 2 Nefi 4:10; 2 Nefi 4:25; 2 Nefi 5:25; 2 Nefi 9:2; 2 Nefi 9:14; 2 Nefi 9:46; 2 Nefi 13:9; 2 Nefi 18:7; 2 Nefi 19:7; 2 Nefi 19:9; 2 Nefi 23:12; 2 Nefi 24:9; 2 Nefi 25:16; 2 Nefi 26:15; 2 Nefi 26:16; 2 Nefi 27:1; 2 Nefi 27:11; 2 Nefi 28:23; 2 Nefi 28:30; 2 Nefi 29:7; 2 Nefi 31:
A68: 67 | B68: 1 Nefi | C68: 12 | D68: 18 | E68: 24 | F68: texto | H68: Quién | I68: Quien | J68: familia | K68: . USO DE ÉPOCA COMPROBADO: 1886 | L68: relativos "quién/quiénes" y "dónde" con tilde | M68: en librodm_cleaned, suprimir la tilde en las 289 (y conservarla en las 14 excluidas | O68: 87 | U68: FAMILIA relativos "quién/quiénes" y "dónde" con tilde (tilde diacrítica de interrogativo puesta sobre el RELATIVO) -- ENTRADA MAESTRA (2026-09-24, abierta durante el `manual-proofread` de Alma 52, a partir de Alma 52:12 "con quiénes marchó" y 52:27 "ciudad de Abundancia, dónde se encontraton"). NORMA DE ÉPOCA: el Prontuario de ortografía de la lengua castellana de la RAE (1844, oficial para las escuelas por Real Orden) prescribe la tilde en "que, como, cuando, quien, cual, donde y cuanto" solo "siempre que den principio a una cláusula de interrogación o de admiración", y además, sin signos de interrogación, "en los casos en que, para dar la debida entonación a la frase, sea preciso detenerse algo más que de ordinario" en la sílaba (1844: 26-27, citado en M. Peñalver Castillo, Anuario de Letras III-2, 2015) -- es decir, en las interrogativas indirectas tónicas ("no sé quién vino"), NUNCA en el relativo átono ("el hombre á quien vi"); la Gramática de 1870 mantiene la distinción; la norma actual (RAE, Ortografía 2010; DPD s.v. "quién") es la misma. Con "haber/tener": con infinitivo es interrogativo y lleva tilde ("no tenía á quién dejar el reino"); con verbo conjugado es relativo y no la lleva ("no hay quien pueda interpretar"). USO DE ÉPOCA COMPROBADO: 1886 (OCR del PDF completo) escribe el relativo SIEMPRE sin tilde -- fuera de preguntas: 355 "quien/quienes" sin tilde, 146 "donde" sin tilde, 0 "dónde" con tilde, y solo 2 "Quién" con tilde que resultan ser preguntas a las que les falta el "¿" inicial; dentro de preguntas lee 45 "quién" y 9 "dónde" con tilde, prueba de que el OCR sí capta las tildes. La Reina-Valera 1909 (NT, ortografía de época: "á", "fué") sigue la norma de 1844 al pie de la letra: relativos sin tilde ("á quien vosotros no conocéis", "Sobre quien vieres descender") y tilde solo en interrogativas indirectas ("dudando de quién decía", "no sabemos dónde le han puesto"). (El corpus del Quijote de workspace/reference_corpora/ NO sirve como prueba de época: es edición con ortografía moderna -- "fue", "vio", sin "á".) COTEJO POSICIÓN POR POSICIÓN CON 1886 (2026-09-24): (a) automático -- de las 281 posiciones, 276 localizadas en el OCR de 1886 por su contexto, TODAS sin tilde (0 con tilde; 5 no localizadas por ruido del OCR); (b) comprobación visual en las imágenes de 1886 (muestra pedida por el editor), 11 lugares fuera de pregunta, TODOS sin tilde: 1 Nefi 4:26 "á quien yo había matado" (file 28), 1 Nefi 10:8 "á quien no conocéis, quien es más poderoso... de quien no soy digno" (37), 1 Nefi 19:10 "á quienes sacó" (67), Mosíah 7:9 "quien era hijo de Zeniff, quien fué hecho rey" (193), Mosíah 26:21 "Y quien oyere mi voz" (239), Alma 13:15 "á quien Abraham pagaba" (291), Alma 29:5 "quien no conoce... quien distingue" (337), Alma 52:12 "con quienes marchó" (410), Helamán 6:30 "él es quien dirige... él es quien trasmite" (467), Éther 9:14 "á quien llamó Émer" (610), Alma 56:15 "donde encontré" (422), III Nefi 27:11 "de donde no se vuelve" (55
A69: 68 | B69: 1 Nefi | C69: 12 | D69: 18 | E69: 24 | F69: texto | H69: aún | I69: aun | J69: familia | K69: por el mismo camino en que vinieron", donde 1886 lee "aun atrás" | L69: "aún" con tilde por "aun" | M69: en librodm_cleaned, "aun" en (a | O69: 90 | U69: FAMILIA "aún" con tilde por "aun" (= "hasta, incluso, también, siquiera") -- ENTRADA MAESTRA (2026-09-26, abierta durante el `manual-proofread` de Alma 58, a partir de Alma 58:24 "sí, aún atrás por el mismo camino en que vinieron", donde 1886 lee "aun atrás"). NORMA DE ÉPOCA: desde la Gramática de la RAE de 1880 y hasta 1952 la tilde de "aun" se regía por la POSICIÓN: antepuesto a lo que modifica era monosílabo átono y se escribía "aun"; pospuesto era bisílabo tónico y se escribía "aún" (Á. Calderón Rivera, Thesaurus XLVIII, 1993). Las Nuevas normas de prosodia y ortografía de 1952 (regla 17; texto en BRAE XXXVIII, cuad. CLV, pp. 331-347) adoptaron el criterio de SIGNIFICADO que mantiene la RAE actual (Ortografía 2010): "aún" cuando puede sustituirse por "todavía" ("aún está enfermo; está enfermo aún"); "aun" con el sentido de "hasta, también, inclusive (o siquiera, con negación)" ("aun los sordos han de oírme; ni hizo nada por él ni aun lo intentó"). CRITERIO DE ESTA ENTRADA: sólo se registran los casos que AMBAS normas condenan: (a) "aún" con tilde con el sentido de "hasta/incluso/siquiera" y ANTEPUESTO a lo que modifica ("aún hasta la muerte", "aún como", "sí, aún la ley de Moisés", "ni aún entre los Nefitas", "aún cuando" concesivo, "aún así"); (b) "aun" sin tilde con el sentido de "todavía" y POSPUESTO a lo que modifica. EXCLUIDOS, no registrados: los correctos por ambas normas ("aun" = "incluso" antepuesto; "aún" = "todavía" pospuesto: "viven aún", "no ha llegado aún", "os llama aún", "permanecían aún duros"); los que una norma aprueba y la otra condena ("aun/aún" = "todavía" antepuesto: "aun no se ha concluido mi obra", "aun están vivas", "mas aun quedará"); y las construcciones con "más/mayor" ("aun más", "aún más ruin", "aun mayor"), que admiten las dos lecturas. Clasificación hecha a mano sobre las 389 apariciones de "aun/aún" en el cuerpo de librodm.txt (217 "aún", 172 "aun"), con apoyo en el inglés en las dudosas ("even" frente a "yet/still"). USO DE 1886: el OCR del PDF completo tiene 194 "aun/Aun" y un solo "aún" (Alma 20:30 "aún más dura", caso excluido); de las 194 posiciones de esta entrada en el cuerpo, 179 se localizaron automáticamente en 1886 por su contexto, TODAS "aun" sin tilde, y las 15 restantes (no localizadas por ruido del OCR o redacción distinta) tampoco pueden llevarla, pues el único "aún" de 1886 está en Alma 20:30 -> el grupo (a) es EXCLUSIVO DE 1920; el grupo (b) es COMPARTIDO CON 1886. APARICIONES: (a) "aún" por "aun" -- 192 en el cuerpo: 1 Nefi 2:2; 1 Nefi 5:13; 1 Nefi 12:11; 1 Nefi 12:18; 1 Nefi 13:29; 1 Nefi 17:4; 1 Nefi 17:48; 1 Nefi 17:52; 1 Nefi 20:5; 1 Nefi 22:17 x2; 2 Nefi 1:13; 2 Nefi 1:29; 2 Nefi 2:15; 2 Nefi 2:18; 2 Nefi 3:20 x2; 2 Nefi 4:10; 2 Nefi 4:25; 2 Nefi 5:25; 2 Nefi 9:2; 2 Nefi 9:14; 2 Nefi 9:46; 2 Nefi 13:9; 2 Nefi 18:7; 2 Nefi 19:7; 2 Nefi 19:9; 2 Nefi 23:12; 2 Nefi 24:9; 2 Nefi 25:16; 2 Nefi 26:15; 2 Nefi 26:16; 2 Nefi 27:1; 2 Nefi 27:11; 2 Nefi 28:23; 2 Nefi 28:30; 2 Nefi 29:7; 2 Nefi 31:
A70: 69 | B70: 1 Nefi | C70: 13 | D70: 6 | E70: 25 | F70: texto | H70: quién | I70: quien | J70: familia | K70: . USO DE ÉPOCA COMPROBADO: 1886 | L70: relativos "quién/quiénes" y "dónde" con tilde | M70: en librodm_cleaned, suprimir la tilde en las 289 (y conservarla en las 14 excluidas | O70: 87 | U70: FAMILIA relativos "quién/quiénes" y "dónde" con tilde (tilde diacrítica de interrogativo puesta sobre el RELATIVO) -- ENTRADA MAESTRA (2026-09-24, abierta durante el `manual-proofread` de Alma 52, a partir de Alma 52:12 "con quiénes marchó" y 52:27 "ciudad de Abundancia, dónde se encontraton"). NORMA DE ÉPOCA: el Prontuario de ortografía de la lengua castellana de la RAE (1844, oficial para las escuelas por Real Orden) prescribe la tilde en "que, como, cuando, quien, cual, donde y cuanto" solo "siempre que den principio a una cláusula de interrogación o de admiración", y además, sin signos de interrogación, "en los casos en que, para dar la debida entonación a la frase, sea preciso detenerse algo más que de ordinario" en la sílaba (1844: 26-27, citado en M. Peñalver Castillo, Anuario de Letras III-2, 2015) -- es decir, en las interrogativas indirectas tónicas ("no sé quién vino"), NUNCA en el relativo átono ("el hombre á quien vi"); la Gramática de 1870 mantiene la distinción; la norma actual (RAE, Ortografía 2010; DPD s.v. "quién") es la misma. Con "haber/tener": con infinitivo es interrogativo y lleva tilde ("no tenía á quién dejar el reino"); con verbo conjugado es relativo y no la lleva ("no hay quien pueda interpretar"). USO DE ÉPOCA COMPROBADO: 1886 (OCR del PDF completo) escribe el relativo SIEMPRE sin tilde -- fuera de preguntas: 355 "quien/quienes" sin tilde, 146 "donde" sin tilde, 0 "dónde" con tilde, y solo 2 "Quién" con tilde que resultan ser preguntas a las que les falta el "¿" inicial; dentro de preguntas lee 45 "quién" y 9 "dónde" con tilde, prueba de que el OCR sí capta las tildes. La Reina-Valera 1909 (NT, ortografía de época: "á", "fué") sigue la norma de 1844 al pie de la letra: relativos sin tilde ("á quien vosotros no conocéis", "Sobre quien vieres descender") y tilde solo en interrogativas indirectas ("dudando de quién decía", "no sabemos dónde le han puesto"). (El corpus del Quijote de workspace/reference_corpora/ NO sirve como prueba de época: es edición con ortografía moderna -- "fue", "vio", sin "á".) COTEJO POSICIÓN POR POSICIÓN CON 1886 (2026-09-24): (a) automático -- de las 281 posiciones, 276 localizadas en el OCR de 1886 por su contexto, TODAS sin tilde (0 con tilde; 5 no localizadas por ruido del OCR); (b) comprobación visual en las imágenes de 1886 (muestra pedida por el editor), 11 lugares fuera de pregunta, TODOS sin tilde: 1 Nefi 4:26 "á quien yo había matado" (file 28), 1 Nefi 10:8 "á quien no conocéis, quien es más poderoso... de quien no soy digno" (37), 1 Nefi 19:10 "á quienes sacó" (67), Mosíah 7:9 "quien era hijo de Zeniff, quien fué hecho rey" (193), Mosíah 26:21 "Y quien oyere mi voz" (239), Alma 13:15 "á quien Abraham pagaba" (291), Alma 29:5 "quien no conoce... quien distingue" (337), Alma 52:12 "con quienes marchó" (410), Helamán 6:30 "él es quien dirige... él es quien trasmite" (467), Éther 9:14 "á quien llamó Émer" (610), Alma 56:15 "donde encontré" (422), III Nefi 27:11 "de donde no se vuelve" (55
A71: 70 | B71: 1 Nefi | C71: 13 | D71: 10 | E71: 25 | F71: nota | G71: 88 (13e) | H71: Oceano | I71: Océano | J71: tilde | K71: eva tilde por esdrújula; sin comparación con 1886 | O71: 52 | U71: Footnote 1 Nefi 13e, 88 Oceano (Océano) (nota editorial de O. Pratt "El Oceano Atlántico"; 1920 imprime "Oceano" sin tilde, confirmado a zoom (pages_1920/page_0047.png); "Océano" lleva tilde por esdrújula; sin comparación con 1886 (no tiene aparato de notas) ni 1879 (inglés); error exclusivo de 1920; preservado como se imprime; hallado en la auditoría de permitted words.txt 2026-09-08)
A72: 71 | B72: 1 Nefi | C72: 13 | D72: 12 | E72: 26 | F72: nota | G72: 89 (13f) | H72: Cristóval | I72: Cristóbal | J72: letra(s) | K72: ormativo es "Cristóbal"; sin comparación con 1886/1879 | O72: 53 | U72: Footnote 1 Nefi 13f, 89 Cristóval (Cristóbal) (nota editorial "Cristóval Colón"; 1920 imprime "Cristóval" con "v", confirmado a zoom (pages_1920/page_0048.png); el nombre normativo es "Cristóbal"; sin comparación con 1886/1879; error exclusivo de 1920; preservado como se imprime; hallado en la auditoría de permitted words.txt 2026-09-08)
A73: 72 | B73: 1 Nefi | C73: 13 | D73: 20 | E73: 26 | F73: texto | H73: occurrió | I73: ocurrió | J73: letra(s) | K73: occurrió en 1886 | O73: 54 | U73: 1 Nefi 13:20 occurrió (ocurrió) (occurrió en 1886)
A74: 73 | B74: 1 Nefi | C74: 13 | D74: 29 | E74: 27 | F74: texto | H74: aún | I74: aun | J74: familia | K74: por el mismo camino en que vinieron", donde 1886 lee "aun atrás" | L74: "aún" con tilde por "aun" | M74: en librodm_cleaned, "aun" en (a | O74: 90 | U74: FAMILIA "aún" con tilde por "aun" (= "hasta, incluso, también, siquiera") -- ENTRADA MAESTRA (2026-09-26, abierta durante el `manual-proofread` de Alma 58, a partir de Alma 58:24 "sí, aún atrás por el mismo camino en que vinieron", donde 1886 lee "aun atrás"). NORMA DE ÉPOCA: desde la Gramática de la RAE de 1880 y hasta 1952 la tilde de "aun" se regía por la POSICIÓN: antepuesto a lo que modifica era monosílabo átono y se escribía "aun"; pospuesto era bisílabo tónico y se escribía "aún" (Á. Calderón Rivera, Thesaurus XLVIII, 1993). Las Nuevas normas de prosodia y ortografía de 1952 (regla 17; texto en BRAE XXXVIII, cuad. CLV, pp. 331-347) adoptaron el criterio de SIGNIFICADO que mantiene la RAE actual (Ortografía 2010): "aún" cuando puede sustituirse por "todavía" ("aún está enfermo; está enfermo aún"); "aun" con el sentido de "hasta, también, inclusive (o siquiera, con negación)" ("aun los sordos han de oírme; ni hizo nada por él ni aun lo intentó"). CRITERIO DE ESTA ENTRADA: sólo se registran los casos que AMBAS normas condenan: (a) "aún" con tilde con el sentido de "hasta/incluso/siquiera" y ANTEPUESTO a lo que modifica ("aún hasta la muerte", "aún como", "sí, aún la ley de Moisés", "ni aún entre los Nefitas", "aún cuando" concesivo, "aún así"); (b) "aun" sin tilde con el sentido de "todavía" y POSPUESTO a lo que modifica. EXCLUIDOS, no registrados: los correctos por ambas normas ("aun" = "incluso" antepuesto; "aún" = "todavía" pospuesto: "viven aún", "no ha llegado aún", "os llama aún", "permanecían aún duros"); los que una norma aprueba y la otra condena ("aun/aún" = "todavía" antepuesto: "aun no se ha concluido mi obra", "aun están vivas", "mas aun quedará"); y las construcciones con "más/mayor" ("aun más", "aún más ruin", "aun mayor"), que admiten las dos lecturas. Clasificación hecha a mano sobre las 389 apariciones de "aun/aún" en el cuerpo de librodm.txt (217 "aún", 172 "aun"), con apoyo en el inglés en las dudosas ("even" frente a "yet/still"). USO DE 1886: el OCR del PDF completo tiene 194 "aun/Aun" y un solo "aún" (Alma 20:30 "aún más dura", caso excluido); de las 194 posiciones de esta entrada en el cuerpo, 179 se localizaron automáticamente en 1886 por su contexto, TODAS "aun" sin tilde, y las 15 restantes (no localizadas por ruido del OCR o redacción distinta) tampoco pueden llevarla, pues el único "aún" de 1886 está en Alma 20:30 -> el grupo (a) es EXCLUSIVO DE 1920; el grupo (b) es COMPARTIDO CON 1886. APARICIONES: (a) "aún" por "aun" -- 192 en el cuerpo: 1 Nefi 2:2; 1 Nefi 5:13; 1 Nefi 12:11; 1 Nefi 12:18; 1 Nefi 13:29; 1 Nefi 17:4; 1 Nefi 17:48; 1 Nefi 17:52; 1 Nefi 20:5; 1 Nefi 22:17 x2; 2 Nefi 1:13; 2 Nefi 1:29; 2 Nefi 2:15; 2 Nefi 2:18; 2 Nefi 3:20 x2; 2 Nefi 4:10; 2 Nefi 4:25; 2 Nefi 5:25; 2 Nefi 9:2; 2 Nefi 9:14; 2 Nefi 9:46; 2 Nefi 13:9; 2 Nefi 18:7; 2 Nefi 19:7; 2 Nefi 19:9; 2 Nefi 23:12; 2 Nefi 24:9; 2 Nefi 25:16; 2 Nefi 26:15; 2 Nefi 26:16; 2 Nefi 27:1; 2 Nefi 27:11; 2 Nefi 28:23; 2 Nefi 28:30; 2 Nefi 29:7; 2 Nefi 31:
A75: 74 | B75: 1 Nefi | C75: 13 | D75: 29 | E75: 27 | F75: texto | H75: satán | I75: Satán | J75: familia | K75: . 1886: "Satan" con MAYÚSCULA y SIN tilde en sus 26 apar | L75: "satán" en minúscula | M75: _cleaned si se normaliza a "Satán" o se conserva la minúscula por fidelidad a 1879 | O75: 97 | P75: corregido | Q75: Satán | U75: FAMILIA "satán" en minúscula (por "Satán", nombre propio) -- ENTRADA MAESTRA (2026-10-04, abierta durante el `manual-proofread` de Mormón 5, a partir de Mormón 5:18 "que satán se les lleva como tamo por el viento"). 1920 escribe el nombre propio SIEMPRE en minúscula y con tilde: "satán" 26 de 26 veces en el cuerpo de librodm.txt (ninguna en las notas; ninguna "Satán" ni "Satanás"). NORMA: "Satán" (y "Satanás") es nombre propio y va con mayúscula inicial; la tilde es correcta (aguda terminada en -n). 1886: "Satan" con MAYÚSCULA y SIN tilde en sus 26 apariciones (capa de texto del PDF completo de 1886; el único "satan" en minúscula del OCR es un falso positivo, "cau-sa tan", file 188). 1879 (inglés, Pratt): "satan" en MINÚSCULA en las 3 apariciones halladas en 4 páginas muestreadas por OCR (tesseract) de pages_1879 -- page_0064 (1 Nephi 22:15 "that satan shall have no more power"), page_0065 (1 Nephi 22:26 "satan has no power"), page_0567 (Mormon 5:18 "led about by satan", confirmado además a zoom en la imagen) -- así que la minúscula de 1920 sigue al inglés de 1879, con la tilde española añadida; no es descuido sino decisión consistente del revisor de 1920. Edición moderna en español (churchofjesuschrist.org, Mormón 5:18, cotejada 2026-10-04): "he aquí que Satanás los lleva" -- con mayúscula, y con la otra forma del nombre. CLASIFICACIÓN: convención ortográfica no normativa en español, heredada del modelo inglés. NOTA DEL EDITOR (2026-10-04): registrar, pero "not sure we will really want to change in 1920 in light of 1879" -- decidir al preparar _cleaned si se normaliza a "Satán" o se conserva la minúscula por fidelidad a 1879. APARICIONES (26; libro capítulo:versículo, pág. del libro): 1 Nefi 13:29 (27), 22:15 (56), 22:26 (57); 2 Nefi 30:18 (125); Alma 8:9 (258), 10:25 (266), 12:17 (273), 15:17 (284), 27:12 (319), 37:15 (349); Helamán 6:21 (451), 16:22 (480), 16:23 (480); III Nefi 1:22 (483), 2:2 (484), 2:3 (484), 6:15 (496), 6:16 (496), 7:5 (498), 18:18 (524), 28:39 (547); IV Nefi 1:28 (552); Mormón 5:18 (564); Éther 8:26 (594), 15:19 (613); Moroni 9:3 (626) (lista generada por script sobre librodm.txt; el versículo es el del renglón en que aparece la palabra). -> _cleaned (a decidir por el editor): "Satán"; preservado como se imprime en librodm_transcribed.
A76: 75 | B76: 1 Nefi | C76: 13 | D76: 35 | E76: 28 | F76: texto | H76: hé aquí | I76: he aquí | J76: familia | K76: . 1886 escribe sistemáticamente "hé aquí" con tilde | L76: "hé aquí" con tilde | M76: -> _cleaned: "he aquí" | O76: 98 | P76: corregido | U76: FAMILIA "hé aquí" con tilde (por "he aquí") -- ENTRADA MAESTRA (2026-10-05, abierta durante el `manual-proofread` de Mormón 8, a partir de Mormón 8:41 "Hé aquí, que la espada de la justicia"). 1886 escribe sistemáticamente "hé aquí" con tilde (uso ortográfico del siglo XIX); 1920 lo actualiza a "he aquí" sin tilde 1359 veces ("He aquí" 381, "he aquí" 978) y deja solo 6 con tilde, restos de 1886 sin actualizar, como Mormón 3:6 "fortificámos" y Mormón 6:14 "caido". El monosílabo "he" no lleva tilde (no hay "he" átono del que distinguirlo en este uso). Las 6, confirmadas en el OCR de Google del PDF de 1920: 1 Nefi 13:35 "Porque, hé aquí, dice el Cordero" (pág. 28); Omni 1:9 "porque, hé aquí," (pág. 157); Alma 7:9 "Mas, hé aquí, que el Espíritu" (pág. 255); Alma 28:1 "Zarahemla; hé aquí, que los ejércitos" (pág. 321); Mormón 8:41 "Hé aquí, que la espada" (pág. 573, pages_1920/page_0595.png, cotejada a la vista); Éther 3:24 "Porque, hé aquí, que he confundido" (pág. 584). CLASIFICACIÓN: inconsistencia ortográfica (no error de lengua). Registrado siguiendo el criterio del editor para "fortificámos" (2026-10-04). Distinta de las entradas "He aqui"/"he aqui" sin tilde en "aquí" (2 Nefi 7:11, Helamán 8:23, etc.), que son otro error. -> _cleaned: "he aquí"; preservadas como se imprimen en librodm_transcribed.
A77: 76 | B77: 1 Nefi | C77: 14 | D77: 1 | E77: 29 | F77: texto | H77: eschucharen | I77: escucharen | J77: letra(s) | K77: escucharen en versión de 1886 | O77: 55 | U77: 1 Nefi 14:1 eschucharen (escucharen)(escucharen en versión de 1886)
A78: 77 | B78: 1 Nefi | C78: 14 | D78: 26 | E78: 32 | F78: texto | H78: quiénes | I78: quienes | J78: familia | K78: . USO DE ÉPOCA COMPROBADO: 1886 | L78: relativos "quién/quiénes" y "dónde" con tilde | M78: en librodm_cleaned, suprimir la tilde en las 289 (y conservarla en las 14 excluidas | O78: 87 | U78: FAMILIA relativos "quién/quiénes" y "dónde" con tilde (tilde diacrítica de interrogativo puesta sobre el RELATIVO) -- ENTRADA MAESTRA (2026-09-24, abierta durante el `manual-proofread` de Alma 52, a partir de Alma 52:12 "con quiénes marchó" y 52:27 "ciudad de Abundancia, dónde se encontraton"). NORMA DE ÉPOCA: el Prontuario de ortografía de la lengua castellana de la RAE (1844, oficial para las escuelas por Real Orden) prescribe la tilde en "que, como, cuando, quien, cual, donde y cuanto" solo "siempre que den principio a una cláusula de interrogación o de admiración", y además, sin signos de interrogación, "en los casos en que, para dar la debida entonación a la frase, sea preciso detenerse algo más que de ordinario" en la sílaba (1844: 26-27, citado en M. Peñalver Castillo, Anuario de Letras III-2, 2015) -- es decir, en las interrogativas indirectas tónicas ("no sé quién vino"), NUNCA en el relativo átono ("el hombre á quien vi"); la Gramática de 1870 mantiene la distinción; la norma actual (RAE, Ortografía 2010; DPD s.v. "quién") es la misma. Con "haber/tener": con infinitivo es interrogativo y lleva tilde ("no tenía á quién dejar el reino"); con verbo conjugado es relativo y no la lleva ("no hay quien pueda interpretar"). USO DE ÉPOCA COMPROBADO: 1886 (OCR del PDF completo) escribe el relativo SIEMPRE sin tilde -- fuera de preguntas: 355 "quien/quienes" sin tilde, 146 "donde" sin tilde, 0 "dónde" con tilde, y solo 2 "Quién" con tilde que resultan ser preguntas a las que les falta el "¿" inicial; dentro de preguntas lee 45 "quién" y 9 "dónde" con tilde, prueba de que el OCR sí capta las tildes. La Reina-Valera 1909 (NT, ortografía de época: "á", "fué") sigue la norma de 1844 al pie de la letra: relativos sin tilde ("á quien vosotros no conocéis", "Sobre quien vieres descender") y tilde solo en interrogativas indirectas ("dudando de quién decía", "no sabemos dónde le han puesto"). (El corpus del Quijote de workspace/reference_corpora/ NO sirve como prueba de época: es edición con ortografía moderna -- "fue", "vio", sin "á".) COTEJO POSICIÓN POR POSICIÓN CON 1886 (2026-09-24): (a) automático -- de las 281 posiciones, 276 localizadas en el OCR de 1886 por su contexto, TODAS sin tilde (0 con tilde; 5 no localizadas por ruido del OCR); (b) comprobación visual en las imágenes de 1886 (muestra pedida por el editor), 11 lugares fuera de pregunta, TODOS sin tilde: 1 Nefi 4:26 "á quien yo había matado" (file 28), 1 Nefi 10:8 "á quien no conocéis, quien es más poderoso... de quien no soy digno" (37), 1 Nefi 19:10 "á quienes sacó" (67), Mosíah 7:9 "quien era hijo de Zeniff, quien fué hecho rey" (193), Mosíah 26:21 "Y quien oyere mi voz" (239), Alma 13:15 "á quien Abraham pagaba" (291), Alma 29:5 "quien no conoce... quien distingue" (337), Alma 52:12 "con quienes marchó" (410), Helamán 6:30 "él es quien dirige... él es quien trasmite" (467), Éther 9:14 "á quien llamó Émer" (610), Alma 56:15 "donde encontré" (422), III Nefi 27:11 "de donde no se vuelve" (55
A79: 78 | B79: 1 Nefi | C79: 15 | D79: 13 | E79: 33 | F79: texto | H79: Evengelio | I79: Evangelio | J79: letra(s) | K79: Evangelio en 1886 | O79: 56 | U79: 1 Nefi 15:13 Evengelio (Evangelio) (Evangelio en 1886)
A80: 79 | B80: 1 Nefi | C80: 15 | D80: 13 | E80: 33 | F80: texto | H80: ingerto | I80: injerto | J80: letra(s) | K80: ingerto en 1886 | O80: 57 | U80: 1 Nefi 15:13 ingerto (injerto) (ingerto en 1886)
A81: 80 | B81: 1 Nefi | C81: 15 | D81: 14 | E81: 33 | F81: texto | H81: quiénes | I81: quienes | J81: familia | K81: . USO DE ÉPOCA COMPROBADO: 1886 | L81: relativos "quién/quiénes" y "dónde" con tilde | M81: en librodm_cleaned, suprimir la tilde en las 289 (y conservarla en las 14 excluidas | O81: 87 | U81: FAMILIA relativos "quién/quiénes" y "dónde" con tilde (tilde diacrítica de interrogativo puesta sobre el RELATIVO) -- ENTRADA MAESTRA (2026-09-24, abierta durante el `manual-proofread` de Alma 52, a partir de Alma 52:12 "con quiénes marchó" y 52:27 "ciudad de Abundancia, dónde se encontraton"). NORMA DE ÉPOCA: el Prontuario de ortografía de la lengua castellana de la RAE (1844, oficial para las escuelas por Real Orden) prescribe la tilde en "que, como, cuando, quien, cual, donde y cuanto" solo "siempre que den principio a una cláusula de interrogación o de admiración", y además, sin signos de interrogación, "en los casos en que, para dar la debida entonación a la frase, sea preciso detenerse algo más que de ordinario" en la sílaba (1844: 26-27, citado en M. Peñalver Castillo, Anuario de Letras III-2, 2015) -- es decir, en las interrogativas indirectas tónicas ("no sé quién vino"), NUNCA en el relativo átono ("el hombre á quien vi"); la Gramática de 1870 mantiene la distinción; la norma actual (RAE, Ortografía 2010; DPD s.v. "quién") es la misma. Con "haber/tener": con infinitivo es interrogativo y lleva tilde ("no tenía á quién dejar el reino"); con verbo conjugado es relativo y no la lleva ("no hay quien pueda interpretar"). USO DE ÉPOCA COMPROBADO: 1886 (OCR del PDF completo) escribe el relativo SIEMPRE sin tilde -- fuera de preguntas: 355 "quien/quienes" sin tilde, 146 "donde" sin tilde, 0 "dónde" con tilde, y solo 2 "Quién" con tilde que resultan ser preguntas a las que les falta el "¿" inicial; dentro de preguntas lee 45 "quién" y 9 "dónde" con tilde, prueba de que el OCR sí capta las tildes. La Reina-Valera 1909 (NT, ortografía de época: "á", "fué") sigue la norma de 1844 al pie de la letra: relativos sin tilde ("á quien vosotros no conocéis", "Sobre quien vieres descender") y tilde solo en interrogativas indirectas ("dudando de quién decía", "no sabemos dónde le han puesto"). (El corpus del Quijote de workspace/reference_corpora/ NO sirve como prueba de época: es edición con ortografía moderna -- "fue", "vio", sin "á".) COTEJO POSICIÓN POR POSICIÓN CON 1886 (2026-09-24): (a) automático -- de las 281 posiciones, 276 localizadas en el OCR de 1886 por su contexto, TODAS sin tilde (0 con tilde; 5 no localizadas por ruido del OCR); (b) comprobación visual en las imágenes de 1886 (muestra pedida por el editor), 11 lugares fuera de pregunta, TODOS sin tilde: 1 Nefi 4:26 "á quien yo había matado" (file 28), 1 Nefi 10:8 "á quien no conocéis, quien es más poderoso... de quien no soy digno" (37), 1 Nefi 19:10 "á quienes sacó" (67), Mosíah 7:9 "quien era hijo de Zeniff, quien fué hecho rey" (193), Mosíah 26:21 "Y quien oyere mi voz" (239), Alma 13:15 "á quien Abraham pagaba" (291), Alma 29:5 "quien no conoce... quien distingue" (337), Alma 52:12 "con quienes marchó" (410), Helamán 6:30 "él es quien dirige... él es quien trasmite" (467), Éther 9:14 "á quien llamó Émer" (610), Alma 56:15 "donde encontré" (422), III Nefi 27:11 "de donde no se vuelve" (55
A82: 81 | B82: 1 Nefi | C82: 15 | D82: 16 | E82: 33 | F82: texto | H82: serán ingertados | I82: injertados | J82: palabra(s)/gramática | K82: será ingertada en 1886 | O82: 58 | U82: 1 Nefi 15:16 serán ingertados (injertados) (será ingertada en 1886)
A83: 82 | B83: 1 Nefi | C83: 16 | D83: 3 | E83: 36 | F83: texto | H83: eschuchar | I83: escuchar | J83: letra(s) | K83: escuchar en 1886 | O83: 60 | U83: 1 Nefi 16:3 eschuchar (escuchar) (escuchar en 1886)
A84: 83 | B84: 1 Nefi | C84: 16 | D84: 18 | E84: 37 | F84: texto | H84: acero muy fino: y, he aquí | I84: posiblemente "acero muy fino; y, he aquí" en español moderno | J84: palabra(s)/gramática | K84: as coinciden en dos puntos, no punto y coma; 1886 en este lugar exacto | M84: -> _cleaned: A DISCRETIÓN DEL EDITOR -- dejar el ":" de época tal como se imprime, o modernizar a " | O84: 59 | U84: 1 Nefi 16:18 acero muy fino: y, he aquí (posiblemente "acero muy fino; y, he aquí" en español moderno) (1920 imprime "rompí mi arco que era de un acero muy fino: y, he aquí, que mis hermanos se enojáron contra mí", pág. 37; confirmado a zoom (pages_1920/page_0059.png) y de forma independiente por la capa de OCR incrustada del propio PDF, ambas coinciden en dos puntos, no punto y coma; 1886 en este lugar exacto (pages_1886/page_0055.png, book page 37/file 55, CAPÍTULO 16 v.18) imprime IGUALMENTE "de un acero muy fino: y hé aquí que" -- COMPARTIDO CON 1886, no introducido en 1920; el uso de ":" para introducir una cláusula coordinada con "y" (en vez de ";") es una convención de puntuación de época, no un error tipográfico puntual -- la transcripción anterior tenía por error un punto y coma, ajena a ambas ediciones, ya corregida a ":" para igualar lo impreso; -> _cleaned: A DISCRETIÓN DEL EDITOR -- dejar el ":" de época tal como se imprime, o modernizar a ";" en la versión _cleaned; hallado 2026-09-11 durante el lote piloto de cotejo OCR de las páginas 26-50, véase `workspace/diff1920ocr-trans.md`)
A85: 84 | B85: 1 Nefi | C85: 17 | D85: 4 | E85: 39 | F85: texto | H85: aún | I85: aun | J85: familia | K85: por el mismo camino en que vinieron", donde 1886 lee "aun atrás" | L85: "aún" con tilde por "aun" | M85: en librodm_cleaned, "aun" en (a | O85: 90 | U85: FAMILIA "aún" con tilde por "aun" (= "hasta, incluso, también, siquiera") -- ENTRADA MAESTRA (2026-09-26, abierta durante el `manual-proofread` de Alma 58, a partir de Alma 58:24 "sí, aún atrás por el mismo camino en que vinieron", donde 1886 lee "aun atrás"). NORMA DE ÉPOCA: desde la Gramática de la RAE de 1880 y hasta 1952 la tilde de "aun" se regía por la POSICIÓN: antepuesto a lo que modifica era monosílabo átono y se escribía "aun"; pospuesto era bisílabo tónico y se escribía "aún" (Á. Calderón Rivera, Thesaurus XLVIII, 1993). Las Nuevas normas de prosodia y ortografía de 1952 (regla 17; texto en BRAE XXXVIII, cuad. CLV, pp. 331-347) adoptaron el criterio de SIGNIFICADO que mantiene la RAE actual (Ortografía 2010): "aún" cuando puede sustituirse por "todavía" ("aún está enfermo; está enfermo aún"); "aun" con el sentido de "hasta, también, inclusive (o siquiera, con negación)" ("aun los sordos han de oírme; ni hizo nada por él ni aun lo intentó"). CRITERIO DE ESTA ENTRADA: sólo se registran los casos que AMBAS normas condenan: (a) "aún" con tilde con el sentido de "hasta/incluso/siquiera" y ANTEPUESTO a lo que modifica ("aún hasta la muerte", "aún como", "sí, aún la ley de Moisés", "ni aún entre los Nefitas", "aún cuando" concesivo, "aún así"); (b) "aun" sin tilde con el sentido de "todavía" y POSPUESTO a lo que modifica. EXCLUIDOS, no registrados: los correctos por ambas normas ("aun" = "incluso" antepuesto; "aún" = "todavía" pospuesto: "viven aún", "no ha llegado aún", "os llama aún", "permanecían aún duros"); los que una norma aprueba y la otra condena ("aun/aún" = "todavía" antepuesto: "aun no se ha concluido mi obra", "aun están vivas", "mas aun quedará"); y las construcciones con "más/mayor" ("aun más", "aún más ruin", "aun mayor"), que admiten las dos lecturas. Clasificación hecha a mano sobre las 389 apariciones de "aun/aún" en el cuerpo de librodm.txt (217 "aún", 172 "aun"), con apoyo en el inglés en las dudosas ("even" frente a "yet/still"). USO DE 1886: el OCR del PDF completo tiene 194 "aun/Aun" y un solo "aún" (Alma 20:30 "aún más dura", caso excluido); de las 194 posiciones de esta entrada en el cuerpo, 179 se localizaron automáticamente en 1886 por su contexto, TODAS "aun" sin tilde, y las 15 restantes (no localizadas por ruido del OCR o redacción distinta) tampoco pueden llevarla, pues el único "aún" de 1886 está en Alma 20:30 -> el grupo (a) es EXCLUSIVO DE 1920; el grupo (b) es COMPARTIDO CON 1886. APARICIONES: (a) "aún" por "aun" -- 192 en el cuerpo: 1 Nefi 2:2; 1 Nefi 5:13; 1 Nefi 12:11; 1 Nefi 12:18; 1 Nefi 13:29; 1 Nefi 17:4; 1 Nefi 17:48; 1 Nefi 17:52; 1 Nefi 20:5; 1 Nefi 22:17 x2; 2 Nefi 1:13; 2 Nefi 1:29; 2 Nefi 2:15; 2 Nefi 2:18; 2 Nefi 3:20 x2; 2 Nefi 4:10; 2 Nefi 4:25; 2 Nefi 5:25; 2 Nefi 9:2; 2 Nefi 9:14; 2 Nefi 9:46; 2 Nefi 13:9; 2 Nefi 18:7; 2 Nefi 19:7; 2 Nefi 19:9; 2 Nefi 23:12; 2 Nefi 24:9; 2 Nefi 25:16; 2 Nefi 26:15; 2 Nefi 26:16; 2 Nefi 27:1; 2 Nefi 27:11; 2 Nefi 28:23; 2 Nefi 28:30; 2 Nefi 29:7; 2 Nefi 31:
A86: 85 | B86: 1 Nefi | C86: 17 | D86: 5 | E86: 39 | F86: texto | H86: para que no pereciéremos | I86: (ver la entrada de la familia) | J86: familia | K86: todos oraciones finales, 1525-1886, en documentos notariales, legales, novela, histo | L86: "para que" + futuro de subjuntivo | M86: _cleaned: uso constante del traductor | O86: 96 | P86: corregido | Q86: pereciéramos | U86: FAMILIA "para que" + futuro de subjuntivo ("para que estuvieren", "para que no perecieren" por "para que estuviesen/estuvieran", "perecieran/pereciesen") -- ENTRADA MAESTRA (2026-10-03, abierta durante el `manual-proofread` de III Nefi 19, a partir de III Nefi 19:3 "trabajó excesivamente toda la noche, para que estuvieren en la mañana seguiente", confirmado en la imagen, pages_1920/page_0548.png). CONSTRUCCIÓN: oración final con "para que" y el verbo en futuro de subjuntivo (-re, -ren, -res, -reis, -remos), donde el español de todas las épocas usa el imperfecto de subjuntivo (-se/-ra) o el presente. NORMA: el futuro de subjuntivo se limita a oraciones condicionales, relativas y temporales ("si fuere", "el que viniere", "cuando llegare"); no en oraciones finales. EVIDENCIA DE CORPUS: CORDE (consultas del editor, 2026-10-03): "para que estuviesen" ~150 casos (6 pantallas), todos oraciones finales, 1525-1886, en documentos notariales, legales, novela, historia y viajes (p. ej. Isla 1758, Jorge Juan 1747-1748, Alarcón 1874, Valladar 1886); "para que estuvieran" 11 casos, todos finales, 1627-1970 (7 entre 1842 y 1911); "para que estuvieren/estuviere": solo 2 oraciones finales -- Documentos sobre música en la catedral de Sigüenza (1600-1713, notarial; la misma colección tiene "para que estuviesen" en 1714-1750) y Jorge Rubio, traducción de 1862 de la Historia de la conquista del Perú de Prescott (traducción del inglés, como el Libro de Mormón) -- más 1 relativo ("derechos para que estuvieren concedidos", Ley de Enjuiciamiento Civil 1881) y 5 relativos de 1495-1598 para "para que fuere" ("la obra para que fuere aplicada" = "a la que"), que no cuentan. Corpus locales (workspace/reference_corpora): Quijote 0 de 158 "para que"; Reina-Valera 1909 NT 0 de 110. USO INTERNO: librodm.txt tiene 192 oraciones con "para que" + imperfecto de subjuntivo (169 en -ra, 23 en -se) frente a estas 35 en -re. 1886: las 35 aparecen igual en 1886 (cotejo automático contra la capa de texto del PDF completo de 1886, cada posición localizada por su contexto; comprobación visual en III Nefi 19:3, pages_1886/page_0541.png) -> COMPARTIDO CON 1886 EN SU TOTALIDAD; costumbre del traductor de 1886, no de la revisión de 1920. NOTA PARA _cleaned: uso constante del traductor; el editor (2026-10-03) juzgó primero que bajo el criterio de Project Gutenberg (fidelidad salvo errata, uso contrario al propio texto, o error que los editores originales reconocerían) NO es error, y luego pidió registrarlo de todos modos: "I personally am for cleaning up all the errors and may do it outside of the Project Gutenberg project. Please go ahead and log but I will set the criteria when we do the _clean version." Corrección posible en _cleaned (a decidir por el editor): -re -> -se (o -ra) con la misma persona, p. ej. "estuvieren" -> "estuviesen", "pereciéremos" -> "pereciésemos", "fuere" -> "fuese". APARICIONES (35, lista generada por script sobre librodm.txt y revisada a mano: todas oraciones finales):
A87: 86 | B87: 1 Nefi | C87: 17 | D87: 6 | E87: 40 | F87: texto | H87: país Abundancia | I87: país de Abundancia | J87: familia | K87: rcando saltos de línea y marcadores de nota. 1886: el texto OCR del PDF de 1886 da exactamente el m | L87: "país X" sin "de" | M87: _cleaned`, insertar "de" en las 9 del cuerpo (y en las del índice | O87: 86 | U87: FAMILIA "país X" sin "de" (aposición directa por "país de X" ante nombre propio de lugar) -- ENTRADA MAESTRA (2026-09-24, abierta durante el `manual-proofread` de Alma 51, a partir de Alma 51:32 "sobre los limites del país Abundancia"). En español normativo -- tanto en el siglo XIX como hoy -- el sustantivo clasificador "país"/"tierra"/"ciudad"/"reino" se une al nombre propio del lugar mediante "de" ("la ciudad de Roma", "el reino de Castilla"; Reina-Valera escribe siempre "la tierra de Canaán"); la aposición directa sin "de" es normal solo con ciertas clases de nombres (ríos y montes: "el río Jordán", "el monte Sión", y en esta misma obra "el río Sidón"), no con "país". Las formas sin "de" coinciden exactamente con los nombres que en inglés carecen de "of" ("the land Bountiful", "the land Desolation", "the land Jershon" frente a "the land of Zarahemla"), por lo que se clasifican como calco literal del inglés -- mismo tipo de "gringismo" que la FAMILIA "él" por "el" --, no como variante de época. Los propios traductores escriben mayoritariamente la forma con "de" para los mismos lugares. Apariciones en el cuerpo de librodm.txt (9): país Abundancia -- 1 Nefi 17:6, Alma 22:33, Alma 27:22 (x2), Alma 51:32 (frente a 18 "país de Abundancia"); país Jershon -- Alma 27:22, Alma 27:24 (frente a 15 "país de Jershon"); país Desolación -- Alma 46:17 (frente a 6 "país de Desolación"); país Shemlon -- Mosíah 10:7 (frente a 1 "país de Shemlon", Alma 23:12). Además, en el índice: "El país Desolación y el país Abundancia" y "Toma del país Desolación". Recuentos hechos sin distinguir mayúsculas y abarcando saltos de línea y marcadores de nota. 1886: el texto OCR del PDF de 1886 da exactamente el mismo reparto en los mismos lugares (Abundancia 18 con "de" / 5 sin él + 1 en el índice; Jershon 15/2; Desolación 6/1 + 2 en el índice; Shemlon 1/1) -> COMPARTIDO CON 1886, heredado, no introducido en 1920. DECISIÓN DEL EDITOR (2026-09-24): preservar TODAS tal como se imprimen en librodm.txt; en la futura versión `_cleaned`, insertar "de" en las 9 del cuerpo (y en las del índice) para uniformar la forma de los nombres de lugar en todo el texto, siguiendo la forma mayoritaria. Detalle en `workspace/proofread-1920.md`, sección "Alma 51".
A88: 87 | B88: 1 Nefi | C88: 17 | D88: 13 | E88: 40 | F88: texto | H88: Quién | I88: Quien | J88: familia | K88: . USO DE ÉPOCA COMPROBADO: 1886 | L88: relativos "quién/quiénes" y "dónde" con tilde | M88: en librodm_cleaned, suprimir la tilde en las 289 (y conservarla en las 14 excluidas | O88: 87 | U88: FAMILIA relativos "quién/quiénes" y "dónde" con tilde (tilde diacrítica de interrogativo puesta sobre el RELATIVO) -- ENTRADA MAESTRA (2026-09-24, abierta durante el `manual-proofread` de Alma 52, a partir de Alma 52:12 "con quiénes marchó" y 52:27 "ciudad de Abundancia, dónde se encontraton"). NORMA DE ÉPOCA: el Prontuario de ortografía de la lengua castellana de la RAE (1844, oficial para las escuelas por Real Orden) prescribe la tilde en "que, como, cuando, quien, cual, donde y cuanto" solo "siempre que den principio a una cláusula de interrogación o de admiración", y además, sin signos de interrogación, "en los casos en que, para dar la debida entonación a la frase, sea preciso detenerse algo más que de ordinario" en la sílaba (1844: 26-27, citado en M. Peñalver Castillo, Anuario de Letras III-2, 2015) -- es decir, en las interrogativas indirectas tónicas ("no sé quién vino"), NUNCA en el relativo átono ("el hombre á quien vi"); la Gramática de 1870 mantiene la distinción; la norma actual (RAE, Ortografía 2010; DPD s.v. "quién") es la misma. Con "haber/tener": con infinitivo es interrogativo y lleva tilde ("no tenía á quién dejar el reino"); con verbo conjugado es relativo y no la lleva ("no hay quien pueda interpretar"). USO DE ÉPOCA COMPROBADO: 1886 (OCR del PDF completo) escribe el relativo SIEMPRE sin tilde -- fuera de preguntas: 355 "quien/quienes" sin tilde, 146 "donde" sin tilde, 0 "dónde" con tilde, y solo 2 "Quién" con tilde que resultan ser preguntas a las que les falta el "¿" inicial; dentro de preguntas lee 45 "quién" y 9 "dónde" con tilde, prueba de que el OCR sí capta las tildes. La Reina-Valera 1909 (NT, ortografía de época: "á", "fué") sigue la norma de 1844 al pie de la letra: relativos sin tilde ("á quien vosotros no conocéis", "Sobre quien vieres descender") y tilde solo en interrogativas indirectas ("dudando de quién decía", "no sabemos dónde le han puesto"). (El corpus del Quijote de workspace/reference_corpora/ NO sirve como prueba de época: es edición con ortografía moderna -- "fue", "vio", sin "á".) COTEJO POSICIÓN POR POSICIÓN CON 1886 (2026-09-24): (a) automático -- de las 281 posiciones, 276 localizadas en el OCR de 1886 por su contexto, TODAS sin tilde (0 con tilde; 5 no localizadas por ruido del OCR); (b) comprobación visual en las imágenes de 1886 (muestra pedida por el editor), 11 lugares fuera de pregunta, TODOS sin tilde: 1 Nefi 4:26 "á quien yo había matado" (file 28), 1 Nefi 10:8 "á quien no conocéis, quien es más poderoso... de quien no soy digno" (37), 1 Nefi 19:10 "á quienes sacó" (67), Mosíah 7:9 "quien era hijo de Zeniff, quien fué hecho rey" (193), Mosíah 26:21 "Y quien oyere mi voz" (239), Alma 13:15 "á quien Abraham pagaba" (291), Alma 29:5 "quien no conoce... quien distingue" (337), Alma 52:12 "con quienes marchó" (410), Helamán 6:30 "él es quien dirige... él es quien trasmite" (467), Éther 9:14 "á quien llamó Émer" (610), Alma 56:15 "donde encontré" (422), III Nefi 27:11 "de donde no se vuelve" (55
A89: 88 | B89: 1 Nefi | C89: 17 | D89: 19 | E89: 41 | F89: texto | H89: aflijido / aflijirme | I89: afligido / afligirme | J89: familia | K89: nfirmado en la imagen; aflijirles también en 1886 | L89: j por g ante e/i en verbos en -ger/-gir | M89: -> _cleaned (DECISIÓN DEL EDITOR | O89: 155 | U89: FAMILIA j por g ante e/i en verbos en -ger/-gir -- grafía "j" donde el español estándar escribe "g" para el sonido /x/ ante e/i, en los verbos DIRIGIR, AFLIGIR, PROTEGER, ELEGIR, ESCOGER y COGER. ENTRADA MAESTRA (2026-09-09; consolida y SUSTITUYE las entradas antes dispersas: la antigua "FAMILIA dirij-"; 1 Nefi 17:19 "aflijido/aflijirme"; 2 Nefi 1:5 "escojida"; Alma 4:2 "aflijido"; Alma 46:17 "escojido"; Alma 60:1 "elejidos"; Alma 61:2 "aflijido"; Moroni 2:1 "escojido"). AMPLIACIÓN (2026-10-17, item 4b): Alma 19:27 "aflijirles" ("para aflijirles, á causa de sus iniquidades", página 297, pages_1920/page_0319.png; confirmado en la imagen; aflijirles también en 1886). ALCANCE (~47 apariciones): dirigir -> "dirij-" ~16 (`grep -nE "\bdirij[eií]" librodm_transcribed.txt`, EXCLUYENDO "dirijo" 1.ª pers., correcto); afligir -> "aflij-" ~24 (aflijido/aflijidos, aflijir(+enclíticos), aflijí, aflijimos, aflijían -- EXCLUYENDO "aflija/aflijan" subjuntivo, correctos); proteger -> "protejerá" 2x (1 Nefi 22:17, confirmado a zoom); elegir -> "elejidos" 1x (Alma 60:1); escoger -> "escojida" (2 Nefi 1:5) / "escojido" (Alma 46:17, Moroni 2:1); coger -> "cojidos" 1x (Alma 62:9, confirmado a zoom). NOTA: las formas ante a/o (proteja, escoja, escojo, escojáis, aflija, dirijo, coja, elija, recoja) llevan "j" OBLIGATORIA por regla ortográfica y NO son de esta familia. FRECUENCIA INTERNA: 1920 usa mayoritariamente "g" (dirig- 34 : dirij- 16; aflig- 34 : aflij- 24; escog- 75 : escoj- 3; proteg- 15 : protej- 2; elig-/eleg- 17 : elej- 1; cog- 32 : coj- 1) -- edición INCONSISTENTE, a menudo dentro del mismo párrafo (Alma 62:2 "afligió" y 62:7 "dirigido" con "g", junto a 62:9 "cojidos" con "j"). 1886: comparte la grafía "j" en TODOS los lugares cotejados (dirijir/dirijido/dirijirla/dirijirse..., aflijido, aflijir, escojida, escojido, elejidos, protejerá 1 Nefi 22:17, "dirijir" Éther 2:19 [nota 2026-10-07: en este lugar 1920 imprime "dirigir" con "g" (pages_1920/page_0603.png), es decir, lo corrigió; no es una aparición de la familia en 1920]) -- heredado de la tradición de traducción, NO introducido en 1920; 1886 también es inconsistente ("dirigieron" con "g" en Alma 14:28). ATESTIGUACIÓN EXTERNA: las formas con "j" ante e/i = 0 en Quijote / Reina-Valera 1909 NT / Reina-Valera Biblia completa (con "g": aflig- Quijote 22 / RV completa 69; escog- Quijote 11 / RV completa 76; cogid- Quijote 9; dirig- Quijote 3). 1920 NO aplica el sistema de Bello en general: "gente"/"general"/"gentiles"/"imagen"/"origen"/"ángel"/"región"/"religión"/"Egipto" van TODAS con "g" (0 con "j"). Es, por tanto, una variación ortográfica LIMITADA a los verbos en -ger/-gir -- práctica común en la imprenta hispanoamericana del s. XIX (dentro y fuera del sistema de Bello, oficial en Chile 1844-1927). CLASIFICACIÓN: variante ortográfica de época para verbos en -ger/-gir, compartida con 1886, NO un error tipográfico; la edición mezcla "g" (mayoría) y "j". -> _cleaned (DECISIÓN DEL EDITOR): normalizar TODAS las
A90: 89 | B90: 1 Nefi | C90: 17 | D90: 23 | E90: 41 | F90: texto | H90: eschuchado | I90: escuchado | J90: letra(s) | K90: escuchado en versión de 1886 | O90: 61 | U90: 1 Nefi 17:23 eschuchado (escuchado)(escuchado en versión de 1886)
A91: 90 | B91: 1 Nefi | C91: 17 | D91: 35 | E91: 42 | F91: texto | H91: madijo | I91: maldijo | J91: letra(s) | K91: maldijo en 1886 | O91: 62 | U91: 1 Nefi 17:35 madijo(maldijo) (maldijo en 1886)
A92: 91 | B92: 1 Nefi | C92: 17 | D92: 36 | E92: 42 | F92: texto | H92: terra | I92: tierra | J92: letra(s) | K92: tierra en 1886 | O92: 63 | U92: 1 Nefi 17:36 terra (tierra) (tierra en 1886)
A93: 92 | B93: 1 Nefi | C93: 17 | D93: 44 | E93: 43 | F93: texto | H93: Judiós | I93: Judíos | J93: tilde | K93: 1886 en este lugar exacto | O93: 64 | U93: 1 Nefi 17:44 Judiós (Judíos) (1920 imprime "procuraron matarle los Judiós" con el acento sobre la "o" en vez de la "i", página 43; confirmado a zoom en alta resolución (pages_1920/page_0065.png); 1886 en este lugar exacto (pages_1886/page_0061.png, book page 43/file 61) imprime IGUALMENTE "procuráron matarle los Judiós" -- ERROR COMPARTIDO CON 1886, heredado; preservado como se imprime en librodm_transcribed; hallado 2026-09-13 durante el cotejo manual de imagen del `manual-proofread` -- véase `workspace/proofread-1920.md`)
A94: 93 | B94: 1 Nefi | C94: 17 | D94: 48 | E94: 43 | F94: texto | H94: aún | I94: aun | J94: familia | K94: por el mismo camino en que vinieron", donde 1886 lee "aun atrás" | L94: "aún" con tilde por "aun" | M94: en librodm_cleaned, "aun" en (a | O94: 90 | U94: FAMILIA "aún" con tilde por "aun" (= "hasta, incluso, también, siquiera") -- ENTRADA MAESTRA (2026-09-26, abierta durante el `manual-proofread` de Alma 58, a partir de Alma 58:24 "sí, aún atrás por el mismo camino en que vinieron", donde 1886 lee "aun atrás"). NORMA DE ÉPOCA: desde la Gramática de la RAE de 1880 y hasta 1952 la tilde de "aun" se regía por la POSICIÓN: antepuesto a lo que modifica era monosílabo átono y se escribía "aun"; pospuesto era bisílabo tónico y se escribía "aún" (Á. Calderón Rivera, Thesaurus XLVIII, 1993). Las Nuevas normas de prosodia y ortografía de 1952 (regla 17; texto en BRAE XXXVIII, cuad. CLV, pp. 331-347) adoptaron el criterio de SIGNIFICADO que mantiene la RAE actual (Ortografía 2010): "aún" cuando puede sustituirse por "todavía" ("aún está enfermo; está enfermo aún"); "aun" con el sentido de "hasta, también, inclusive (o siquiera, con negación)" ("aun los sordos han de oírme; ni hizo nada por él ni aun lo intentó"). CRITERIO DE ESTA ENTRADA: sólo se registran los casos que AMBAS normas condenan: (a) "aún" con tilde con el sentido de "hasta/incluso/siquiera" y ANTEPUESTO a lo que modifica ("aún hasta la muerte", "aún como", "sí, aún la ley de Moisés", "ni aún entre los Nefitas", "aún cuando" concesivo, "aún así"); (b) "aun" sin tilde con el sentido de "todavía" y POSPUESTO a lo que modifica. EXCLUIDOS, no registrados: los correctos por ambas normas ("aun" = "incluso" antepuesto; "aún" = "todavía" pospuesto: "viven aún", "no ha llegado aún", "os llama aún", "permanecían aún duros"); los que una norma aprueba y la otra condena ("aun/aún" = "todavía" antepuesto: "aun no se ha concluido mi obra", "aun están vivas", "mas aun quedará"); y las construcciones con "más/mayor" ("aun más", "aún más ruin", "aun mayor"), que admiten las dos lecturas. Clasificación hecha a mano sobre las 389 apariciones de "aun/aún" en el cuerpo de librodm.txt (217 "aún", 172 "aun"), con apoyo en el inglés en las dudosas ("even" frente a "yet/still"). USO DE 1886: el OCR del PDF completo tiene 194 "aun/Aun" y un solo "aún" (Alma 20:30 "aún más dura", caso excluido); de las 194 posiciones de esta entrada en el cuerpo, 179 se localizaron automáticamente en 1886 por su contexto, TODAS "aun" sin tilde, y las 15 restantes (no localizadas por ruido del OCR o redacción distinta) tampoco pueden llevarla, pues el único "aún" de 1886 está en Alma 20:30 -> el grupo (a) es EXCLUSIVO DE 1920; el grupo (b) es COMPARTIDO CON 1886. APARICIONES: (a) "aún" por "aun" -- 192 en el cuerpo: 1 Nefi 2:2; 1 Nefi 5:13; 1 Nefi 12:11; 1 Nefi 12:18; 1 Nefi 13:29; 1 Nefi 17:4; 1 Nefi 17:48; 1 Nefi 17:52; 1 Nefi 20:5; 1 Nefi 22:17 x2; 2 Nefi 1:13; 2 Nefi 1:29; 2 Nefi 2:15; 2 Nefi 2:18; 2 Nefi 3:20 x2; 2 Nefi 4:10; 2 Nefi 4:25; 2 Nefi 5:25; 2 Nefi 9:2; 2 Nefi 9:14; 2 Nefi 9:46; 2 Nefi 13:9; 2 Nefi 18:7; 2 Nefi 19:7; 2 Nefi 19:9; 2 Nefi 23:12; 2 Nefi 24:9; 2 Nefi 25:16; 2 Nefi 26:15; 2 Nefi 26:16; 2 Nefi 27:1; 2 Nefi 27:11; 2 Nefi 28:23; 2 Nefi 28:30; 2 Nefi 29:7; 2 Nefi 31:
A95: 94 | B95: 1 Nefi | C95: 17 | D95: 52 | E95: 44 | F95: texto | H95: aún | I95: aun | J95: familia | K95: por el mismo camino en que vinieron", donde 1886 lee "aun atrás" | L95: "aún" con tilde por "aun" | M95: en librodm_cleaned, "aun" en (a | O95: 90 | U95: FAMILIA "aún" con tilde por "aun" (= "hasta, incluso, también, siquiera") -- ENTRADA MAESTRA (2026-09-26, abierta durante el `manual-proofread` de Alma 58, a partir de Alma 58:24 "sí, aún atrás por el mismo camino en que vinieron", donde 1886 lee "aun atrás"). NORMA DE ÉPOCA: desde la Gramática de la RAE de 1880 y hasta 1952 la tilde de "aun" se regía por la POSICIÓN: antepuesto a lo que modifica era monosílabo átono y se escribía "aun"; pospuesto era bisílabo tónico y se escribía "aún" (Á. Calderón Rivera, Thesaurus XLVIII, 1993). Las Nuevas normas de prosodia y ortografía de 1952 (regla 17; texto en BRAE XXXVIII, cuad. CLV, pp. 331-347) adoptaron el criterio de SIGNIFICADO que mantiene la RAE actual (Ortografía 2010): "aún" cuando puede sustituirse por "todavía" ("aún está enfermo; está enfermo aún"); "aun" con el sentido de "hasta, también, inclusive (o siquiera, con negación)" ("aun los sordos han de oírme; ni hizo nada por él ni aun lo intentó"). CRITERIO DE ESTA ENTRADA: sólo se registran los casos que AMBAS normas condenan: (a) "aún" con tilde con el sentido de "hasta/incluso/siquiera" y ANTEPUESTO a lo que modifica ("aún hasta la muerte", "aún como", "sí, aún la ley de Moisés", "ni aún entre los Nefitas", "aún cuando" concesivo, "aún así"); (b) "aun" sin tilde con el sentido de "todavía" y POSPUESTO a lo que modifica. EXCLUIDOS, no registrados: los correctos por ambas normas ("aun" = "incluso" antepuesto; "aún" = "todavía" pospuesto: "viven aún", "no ha llegado aún", "os llama aún", "permanecían aún duros"); los que una norma aprueba y la otra condena ("aun/aún" = "todavía" antepuesto: "aun no se ha concluido mi obra", "aun están vivas", "mas aun quedará"); y las construcciones con "más/mayor" ("aun más", "aún más ruin", "aun mayor"), que admiten las dos lecturas. Clasificación hecha a mano sobre las 389 apariciones de "aun/aún" en el cuerpo de librodm.txt (217 "aún", 172 "aun"), con apoyo en el inglés en las dudosas ("even" frente a "yet/still"). USO DE 1886: el OCR del PDF completo tiene 194 "aun/Aun" y un solo "aún" (Alma 20:30 "aún más dura", caso excluido); de las 194 posiciones de esta entrada en el cuerpo, 179 se localizaron automáticamente en 1886 por su contexto, TODAS "aun" sin tilde, y las 15 restantes (no localizadas por ruido del OCR o redacción distinta) tampoco pueden llevarla, pues el único "aún" de 1886 está en Alma 20:30 -> el grupo (a) es EXCLUSIVO DE 1920; el grupo (b) es COMPARTIDO CON 1886. APARICIONES: (a) "aún" por "aun" -- 192 en el cuerpo: 1 Nefi 2:2; 1 Nefi 5:13; 1 Nefi 12:11; 1 Nefi 12:18; 1 Nefi 13:29; 1 Nefi 17:4; 1 Nefi 17:48; 1 Nefi 17:52; 1 Nefi 20:5; 1 Nefi 22:17 x2; 2 Nefi 1:13; 2 Nefi 1:29; 2 Nefi 2:15; 2 Nefi 2:18; 2 Nefi 3:20 x2; 2 Nefi 4:10; 2 Nefi 4:25; 2 Nefi 5:25; 2 Nefi 9:2; 2 Nefi 9:14; 2 Nefi 9:46; 2 Nefi 13:9; 2 Nefi 18:7; 2 Nefi 19:7; 2 Nefi 19:9; 2 Nefi 23:12; 2 Nefi 24:9; 2 Nefi 25:16; 2 Nefi 26:15; 2 Nefi 26:16; 2 Nefi 27:1; 2 Nefi 27:11; 2 Nefi 28:23; 2 Nefi 28:30; 2 Nefi 29:7; 2 Nefi 31:
A96: 95 | B96: 1 Nefi | C96: 17 | D96: 55 | E96: 44 | F96: texto | H96: piés | I96: pies | J96: familia | K96: . 1886 imprime la misma forma en todas salvo "fuímos" | L96: grafía de época con tilde o sin ella | M96: _cleaned` si se modernizan | O96: 199 | U96: FAMILIA grafía de época con tilde o sin ella (fé, piés, séis, ántes, fuíste, fuímos; linea) -- ENTRADA MAESTRA (2026-10-17, revisión de variantes de tilde, item 4a). Formas de la ortografía anterior a las reformas académicas de fines del siglo XIX, minoritarias frente a la forma moderna en el resto del libro; todas confirmadas en la imagen 2026-10-17 y la transcripción ya coincide con la impresión. Instancias: "fé" x3 -- Mosiah 3:9 (pág. 169), Mosiah 4:21 (pág. 173), Alma 34:28 (pág. 341) (fe 272 veces en el resto); "piés" x3 -- 1 Nefi 17:55 (pág. 44), 1 Nefi 19:7 (pág. 48), 2 Nefi 6:13 (pág. 75) (pies 46 veces); "séis" -- Mormón 2:2 (pág. 556) (seis 22 veces); "ántes" -- III Nefi 11:28 (pág. 509) (antes 100 veces); "fuíste" -- III Nefi 22:6 (pág. 535) (fuiste 8 veces); "fuímos" -- Mormón 2:6 (pág. 556) (fuimos 15 veces); "linea" x5 -- 2 Nefi 9:41 (pág. 83), 2 Nefi 28:30 x2 (pág. 121), Alma 22:27 (pág. 306), Alma 22:32 (pág. 307) (línea 6 veces). 1886 imprime la misma forma en todas salvo "fuímos" (1886 "fuimos", así que esa es exclusiva de 1920). CLASIFICACIÓN: grafía de época, no errata; antes solo en permitted words.txt (séis documentada como "house style" en la auditoría de 2026-09-08). Registrada por la regla de registrar toda forma no estándar; el editor decide en `_cleaned` si se modernizan.
A97: 96 | B97: 1 Nefi | C97: 18 | D97: 15 | E97: 46 | F97: texto | H97: occurrió | I97: ocurrió | J97: letra(s) | K97: 1886 en este lugar exacto | O97: 65 | U97: 1 Nefi 18:15 occurrió (ocurrió) (1920 imprime "Y occurrió que después que fuimos arrojados hacia atrás", página 46 -- mismo patrón "cc" + "rr" dobles ya documentado en 1 Nefi 13:20, Alma 55:4 e IV Nefi 1:40, no la variante "occurió" [una sola r] de 1 Nefi 18:25/Éther 7:1 ni la variante "ocurrio" [sin tilde] de IV Nefi 1:2; confirmado a zoom en alta resolución (pages_1920/page_0068.png); 1886 en este lugar exacto (pages_1886/page_0064.png, book page 46/file 64) imprime IGUALMENTE "Y occurrió que despues" -- ERROR COMPARTIDO CON 1886, heredado; preservado como se imprime en librodm_transcribed; hallado 2026-09-13 durante el cotejo manual de imagen del `manual-proofread` -- véase `workspace/proofread-1920.md`)
A98: 97 | B98: 1 Nefi | C98: 18 | D98: 25 | E98: 47 | F98: texto | H98: occurió | I98: ocurrió | J98: letra(s) | K98: por el desierto en la tierra de promisión"; 1886 en este lugar exacto | O98: 66 | U98: 1 Nefi 18:25 occurió (ocurrió) (1920 imprime "occurió" -- "cc" doble pero solo una "r" -- en vez de "ocurrió" en "Y occurió que cuando viajábamos por el desierto en la tierra de promisión"; 1886 en este lugar exacto (pages_1886/page_0065.png, book page 47/file 65) imprime "Y ocurrió que cuando viajábamos" con la grafía correcta; distinto del patrón "occurrió" (cc + rr dobles) ya documentado en 1 Nefi 13:20, Alma 55:4 e IV Nefi 1:40, y del patrón "ocurrio" (sin tilde) documentado en IV Nefi 1:2 -- una tercera variante independiente de este mismo error recurrente; la misma grafía exacta reaparece, sin relación directa, en Éther 7:1 (ver esa entrada); ya presente en `permitted words.txt` pero nunca promovida a este archivo hasta ahora; error exclusivo de 1920, no compartido con 1886; preservado como se imprime en la transcripción)
A99: 98 | B99: 1 Nefi | C99: 18 | D99: 25 | E99: 47 | F99: texto | H99: vacas bueyes | I99: vacas, bueyes | J99: puntuación/espacio | K99: vacas, buéyes en 1886 | O99: 67 | U99: 1 Nefi 18:25 vacas bueyes (vacas, bueyes) (vacas, buéyes en 1886)
A100: 99 | B100: 1 Nefi | C100: 19 | D100: 3 | E100: 47 | F100: texto | H100: quiénes | I100: quienes | J100: familia | K100: . USO DE ÉPOCA COMPROBADO: 1886 | L100: relativos "quién/quiénes" y "dónde" con tilde | M100: en librodm_cleaned, suprimir la tilde en las 289 (y conservarla en las 14 excluidas | O100: 87 | U100: FAMILIA relativos "quién/quiénes" y "dónde" con tilde (tilde diacrítica de interrogativo puesta sobre el RELATIVO) -- ENTRADA MAESTRA (2026-09-24, abierta durante el `manual-proofread` de Alma 52, a partir de Alma 52:12 "con quiénes marchó" y 52:27 "ciudad de Abundancia, dónde se encontraton"). NORMA DE ÉPOCA: el Prontuario de ortografía de la lengua castellana de la RAE (1844, oficial para las escuelas por Real Orden) prescribe la tilde en "que, como, cuando, quien, cual, donde y cuanto" solo "siempre que den principio a una cláusula de interrogación o de admiración", y además, sin signos de interrogación, "en los casos en que, para dar la debida entonación a la frase, sea preciso detenerse algo más que de ordinario" en la sílaba (1844: 26-27, citado en M. Peñalver Castillo, Anuario de Letras III-2, 2015) -- es decir, en las interrogativas indirectas tónicas ("no sé quién vino"), NUNCA en el relativo átono ("el hombre á quien vi"); la Gramática de 1870 mantiene la distinción; la norma actual (RAE, Ortografía 2010; DPD s.v. "quién") es la misma. Con "haber/tener": con infinitivo es interrogativo y lleva tilde ("no tenía á quién dejar el reino"); con verbo conjugado es relativo y no la lleva ("no hay quien pueda interpretar"). USO DE ÉPOCA COMPROBADO: 1886 (OCR del PDF completo) escribe el relativo SIEMPRE sin tilde -- fuera de preguntas: 355 "quien/quienes" sin tilde, 146 "donde" sin tilde, 0 "dónde" con tilde, y solo 2 "Quién" con tilde que resultan ser preguntas a las que les falta el "¿" inicial; dentro de preguntas lee 45 "quién" y 9 "dónde" con tilde, prueba de que el OCR sí capta las tildes. La Reina-Valera 1909 (NT, ortografía de época: "á", "fué") sigue la norma de 1844 al pie de la letra: relativos sin tilde ("á quien vosotros no conocéis", "Sobre quien vieres descender") y tilde solo en interrogativas indirectas ("dudando de quién decía", "no sabemos dónde le han puesto"). (El corpus del Quijote de workspace/reference_corpora/ NO sirve como prueba de época: es edición con ortografía moderna -- "fue", "vio", sin "á".) COTEJO POSICIÓN POR POSICIÓN CON 1886 (2026-09-24): (a) automático -- de las 281 posiciones, 276 localizadas en el OCR de 1886 por su contexto, TODAS sin tilde (0 con tilde; 5 no localizadas por ruido del OCR); (b) comprobación visual en las imágenes de 1886 (muestra pedida por el editor), 11 lugares fuera de pregunta, TODOS sin tilde: 1 Nefi 4:26 "á quien yo había matado" (file 28), 1 Nefi 10:8 "á quien no conocéis, quien es más poderoso... de quien no soy digno" (37), 1 Nefi 19:10 "á quienes sacó" (67), Mosíah 7:9 "quien era hijo de Zeniff, quien fué hecho rey" (193), Mosíah 26:21 "Y quien oyere mi voz" (239), Alma 13:15 "á quien Abraham pagaba" (291), Alma 29:5 "quien no conoce... quien distingue" (337), Alma 52:12 "con quienes marchó" (410), Helamán 6:30 "él es quien dirige... él es quien trasmite" (467), Éther 9:14 "á quien llamó Émer" (610), Alma 56:15 "donde encontré" (422), III Nefi 27:11 "de donde no se vuelve" (55
A101: 100 | B101: 1 Nefi | C101: 19 | D101: 4 | E101: 48 | F101: texto | H101: mí | I101: mi | J101: familia | K101: pág. 47; OCR de Google "á mí pueblo"; 1886, file 64, "á mí pueblo" -> COMPARTIDO | L101: posesivo "mi" con tilde | M101: -> _cleaned: "mi" | O101: 101 | P101: corregido | U101: FAMILIA posesivo "mi" con tilde ("mí presencia", "mí propio", "mí pueblo", por "mi") -- ENTRADA MAESTRA (2026-10-08, abierta durante el `manual-proofread` de Éther 3). La tilde diacrítica distingue el pronombre tónico "mí" ("á mí", "de mí") del posesivo átono "mi" ("mi pueblo"); 1920 escribe el posesivo sin tilde miles de veces, pero en 6 lugares lo acentúa, los seis confirmados a la vista en la imagen de 1920 (el OCR de Google omite la tilde en Alma 36:18): 1 Nefi 19:4 "y mandé á mí pueblo lo que debía hacer" (pág. 47; OCR de Google "á mí pueblo"; 1886, file 64, "á mí pueblo" -> COMPARTIDO); Éther 3:9 "nunca ningún hombre apareció en mí presencia con una fe tan grande" (pág. 583, pages_1920/page_0605.png; 1886, file 597, "en mi presencia" -> EXCLUSIVO DE 1920); Éther 3:24 "á mí propio tiempo haré que estas piedras" (pág. 584, page_0606.png; 1886, file 597, "á mí propio tiempo" -> COMPARTIDO). Además (búsqueda de todo "mí" + palabra en librodm.txt, 2026-10-08): Jacob 5:46 "para mí / propio uso" (pág. 144, pages_1920/page_0166.png; 1886 file 159 "para mi propio uso" -> EXCLUSIVO DE 1920); Enós 1:27 "él que se halla en mí / Redentor" (pág. 154, page_0176.png; 1886 file 169 "en mi Redentor" -> EXCLUSIVO DE 1920); Alma 36:18 "Ahora, como mí mente se fijó en este pensamiento" (pág. 346, page_0368.png; 1886 file 361 "como mi mente" -> EXCLUSIVO DE 1920). TOTAL: 6 (2 compartidos con 1886, 4 exclusivos de 1920). Descartado "en mí poder" (Isaías: "¿no hay en mí poder para librar?"), que es pronombre, correcto. -> _cleaned: "mi"; preservados como se imprimen en librodm_transcribed.
...

Sheet Familias
A1: Línea en el registro | B1: Familia | C1: Filas en "Errores" | D1: 1946 – versículos a mirar | E1: 1946 – resultado | F1: 1946 – nota | G1: Decisión Gutenberg (toda la familia) | H1: Decisión moderna (toda la familia) | I1: Comentarios | J1: Entrada completa
A2: 22 | B2: -age | C2: =COUNTIF(Errores!L:L,B2) | D2: 1 Nefi 1:2; 1 Nefi 5:3; Helamán 11:25 | E2: corrige todos | F2: lenguaje, pillaje | J2: FAMILIA -age (por -aje) -- grafía "-age" arcaica donde el español moderno escribe "-aje". ENTRADA MAESTRA (2026-09-09; consolida las entradas antes dispersas de 1 Nefi 1:2 y 1 Nefi 5:3, ambas "el/este lenguage"). Alcance: "lenguage" 11 apariciones en el cuerpo (`grep -nE "lenguage" librodm_transcribed.txt`) + "lenguage del libro" en el índice (pág. xiii) + "344 días de pasage" en el índice (pág. xiii, entrada de Éther 6:11) + "pillage" 1x en el cuerpo (Helamán 11:25, "Y entregándose al pillage y al asesinato", pág. 466/467, LIBRO DE HELAMÁN CAPÍTULO 11; 1886 comparte "pillage" en este lugar exacto, pages_1886/page_0481.png, book page 463/file 481). Frente a "lenguaje" 3x, "pasaje" 12x y "pillaje/pillajes" 13x en el cuerpo (Helamán 11:25 es la ÚNICA aparición de "pillage" -- 1920 usa "pillaje" en las otras 13). La grafía "-age" (mensage/linage/viage/salvage/lenguage/pasage) fue la NORMA del español hasta que la RAE estandarizó "-aje" (~1815); para 1886/1920 era arcaica pero aún frecuente en imprenta. 1920 ya ha completado el cambio a "-aje" en TODAS las demás palabras (mensaje 22x, viaje 29x, salvaje 5x, linaje 4x, ultraje 2x -- 0 con "-age"), quedando SOLO "lenguage" (su forma de casa dominante, 11:3) y un "pasage" suelto en el índice. 1886: comparte "lenguage" ("lenguage en 1886" en las entradas originales de 1 Nefi 1:2 y 5:3). Atestiguación externa: "-age" en estas palabras = 0 en Quijote / Reina-Valera 1909 NT / Reina-Valera Biblia completa; "lenguaje" Quijote 10, "pasaje" Quijote 10, "pillaje" 1 en Reina-Valera Biblia completa (0 "pillage"). CLASIFICACIÓN: grafía ortográfica arcaica de época (norma pre-1815), compartida con 1886, NO un error tipográfico; edición inconsistente (casi todo "-aje", pero "lenguage" mayoritario). -> _cleaned (DECISIÓN DEL EDITOR): normalizar las apariciones restantes de "-age" a "-aje" (lenguage -> lenguaje; pasage -> pasaje; pillage -> pillaje, forma ya mayoritaria 13:1 en la propia 1920), como regularización de una grafía de época, no como corrección de errores. Preservado como se imprime en librodm_transcribed.
A3: 23 | B3: Mosíah/Mosiah | C3: =COUNTIF(Errores!L:L,B3) | D3: Omni 1:18; Alma 1:1; Mosíah nota 1328 (17a); Mosíah nota 1563 (27x); Alma nota 2890 (50-2c) | E3: corrige todos | J3: FAMILIA Mosíah/Mosiah (acento inconsistente) -- el nombre del libro/rey "Mosíah" se imprime en 1920 unas veces con tilde esdrújula y otras sin ella, en ambos bloques de la transcripción. ENTRADA MAESTRA (2026-09-13, abierta durante el `manual-proofread` de 1 Nefi 11 tras encontrar que la nota 11d/70 citaba "Mosíah 15:2-5" con tilde en la transcripción cuando la imagen de 1920 (pages_1920/page_0043.png) imprime "Mosiah" sin tilde -- corregido ese caso puntual para igualar la imagen). Alcance (conteo bruto original de 2026-09-13, SUPERADO -- véase el RECUENTO VERIFICADO de 2026-10-16 al final de esta entrada): `librodm_foot.txt` 507 "Mosíah" con tilde / 115 "Mosiah" sin tilde; `librodm.txt` (cuerpo + Block 2) 348 con tilde / 54 sin tilde -- en ambos archivos la forma CON tilde es mayoritaria (~82-86%), pero la minoría sin tilde es demasiado numerosa para tratarse de simples deslices aislados; probablemente refleja la propia inconsistencia del taller de imprenta de 1920, no un patrón limpio. Comprobación de destino moderno (2026-09-13, churchofjesuschrist.org, título y encabezado del Libro de Mosíah): la edición actual en español escribe "Mosíah" CON tilde de forma uniforme. CLASIFICACIÓN: inconsistencia ortográfica de imprenta de 1920, no un error puntual de la transcripción salvo caso por caso (como 11d/70 arriba, donde la transcripción no igualaba la imagen real). DECISIÓN DEL EDITOR (2026-09-13): la transcripción corriente sigue leyendo cada aparición tal como se verifique contra su propia imagen durante el cotejo manual (no se asume la forma mayoritaria); en la futura versión `_cleaned`, normalizar TODAS las apariciones a "Mosíah" con tilde, igualando la ortografía moderna. Pendiente: una auditoría dedicada, imagen por imagen, de las apariciones sin tilde restantes no se ha emprendido todavía (fuera del alcance de un solo capítulo) -- véase `workspace/proofread-1920.md`, sección "1 Nefi 11", para más detalle. CORRECCIÓN (2026-10-11, barrido de tildes en notas): el caso que abrió esta entrada, la nota 11d/70 de 1 Nefi ("Mosíah 15:2-5", pages_1920/page_0043.png), SÍ lleva tilde en la impresión -- el editor la vio con claridad en un recorte a tamaño moderado; la lectura "sin tilde" de 2026-09-13 era un error de zoom sobre tinta cargada. La transcripción vuelve a "Mosíah" en ambos bloques. Corregidas también 2 Nefi 2e/264 y 9g/364 ("Mosiah" -> "Mosíah"). RECUENTO VERIFICADO (2026-10-16; cada aparición cotejada contra la imagen el 2026-10-11/12 en el barrido de tildes en notas: hojas de contacto a 4x de todos los Mosíah/Mosiah de las notas, y el 2026-10-12 un recorte individual de cada "Mosiah" sin tilde restante, notas y cuerpo): `librodm_foot.txt` (Block 1) 609 "Mosíah" / 14 "Mosiah"; cuerpo de `librodm.txt` (incluidos encabezados y sumarios en cursiva) 82 / 2; Block 2 310 / 4 (las demás notas "Véase x, Mosiah N" se resuelven a un número en Block 2). Las 14 notas sin tilde (punto redondo en la impresión): Mosíah 12e (1251), 16a (1311), 16q (1327), 17a (1328), 18h (1343), 18l (1347), 18w (1358), 19i (1367), 19s (1377), 24h (1481), 27x (1563); Alma 36j (2537), 42y (2667), 50-2c (2890). Las 2 del cuerpo: Omni 1:18 "idioma de Mosiah, Zarahemla" (pág. 158) y Alma 1:1 "Mosiah, quién pugnó" (pág. 235). El recuento original (115 sin tilde en Block 1) se debía sobre todo a deslices de transcripción: 82 notas imprimen "Mosíah" con tilde clara (tinta cargada que las pasadas anteriores leyeron como punto), corregidas el 2026-10-12; además 1 Nefi 11d, 2 Nefi 2e y 9g, Alma 12-2m y 22-2n, III Nefi 11n y el sumario en cursiva de Alma 17 (pág. 286). No se cuentan aquí las erratas registradas aparte: "Nosíah" (Mosíah 23l, 1458) y "Mlsíah" (Mosíah 25i, 1504). Resultado: la forma con tilde es el 97,8 % en las notas (609 de 623) y el 97,6 % en el cuerpo (82 de 84). Detalle: workspace/proofread-1920.md, sección "Footnote accent-variant sweep".
A4: 24 | B4: Éxodo/Exodo | C4: =COUNTIF(Errores!L:L,B4) | D4: 2 Nefi nota 324 (7f); 2 Nefi nota 459 (14g); 2 Nefi nota 590 (21u); 2 Nefi nota 628 (24m); Mosíah nota 1271 (13g) | E4: mixto | F4: Exodo 7f, 7i, 7k, 24m, 12r, 13d, 13g Éxodo 14g, 20t, 20x, 21u, 22c, | J4: FAMILIA Éxodo/Exodo (acento inconsistente) -- el nombre del libro bíblico "Éxodo" (esdrújula, tilde obligatoria por RAE) se imprime en 1920 casi siempre sin tilde en las citas de nota al pie, y solo dos veces con ella. ENTRADA MAESTRA (2026-09-14, abierta durante el `manual-proofread` de 2 Nefi 7 tras encontrar que la nota 7h/326 ("Éxodo 7:18,21") imprime la tilde en la imagen (pages_1920/page_0098.png, confirmado a zoom 4x) mientras que la transcripción tenía "Exodo" sin tilde -- corregido ese caso puntual para igualar la imagen, en ambos bloques). Alcance (conteo bruto de 2026-09-14, confirmado -- véase el RECUENTO VERIFICADO de 2026-10-16 al final de esta entrada): `librodm_foot.txt` y `librodm.txt` 12 "Exodo" sin tilde / 2 "Éxodo" con tilde cada uno (`grep -n "\bExodo\b\|Éxodo" librodm_foot.txt`) -- las 14 apariciones, todas en citas del bloque de notas: 1 Nefi 20g/191 (Éxodo, con tilde, ya coincidía con la imagen antes de este hallazgo), 2 Nefi 7f/324, 7h/326 (Éxodo, corregida en este hallazgo), 7i/327, 7k/329, 14g/459, 20t/554, 20x/558, 21u/590, 22c/593, 24m/628 (todas estas de 2 Nefi sin tilde salvo 7h), Mosíah 12r/1264, 13d/1268, 13g/1271 (sin tilde). La forma SIN tilde es mayoritaria (12:2, ~86%) -- patrón inverso al de [[FAMILIA Mosíah/Mosiah]] (donde la forma CON tilde es la mayoritaria) pero el mismo fenómeno de fondo: inconsistencia ortográfica del propio taller de imprenta de 1920, no necesariamente errores puntuales de esta transcripción. CLASIFICACIÓN: inconsistencia ortográfica de imprenta de 1920. DECISIÓN (siguiendo el mismo criterio que la entrada Mosíah/Mosiah): la transcripción corriente debe seguir leyendo cada aparición tal como se verifique contra su propia imagen durante el cotejo manual (no asumir la forma mayoritaria); en una futura versión `_cleaned`, normalizar todas a "Éxodo" con tilde (RAE exige la tilde; el resto del documento no tiene una forma de casa "Exodo" establecida deliberadamente, a diferencia de "Mosíah" que sí es nombre propio de la propia obra). Pendiente: una auditoría dedicada, imagen por imagen, de las 12 apariciones sin tilde restantes no se ha emprendido todavía (fuera del alcance de un solo capítulo) -- véase `workspace/proofread-1920.md`, sección "2 Nefi 7", para más detalle. ACTUALIZACIÓN (2026-09-16, durante el `manual-proofread` de 2 Nefi 20): 20t/554 y 20x/558 verificados contra sus imágenes (pages_1920/page_0123.png, confirmado a zoom) -- ambos imprimen "Exodo" sin tilde en la imagen, coincidiendo con la transcripción; sin acción, quedan confirmados (no solo pendientes) como error de imprenta de 1920 genuino en estos dos casos puntuales. ACTUALIZACIÓN (2026-09-16, durante el `manual-proofread` de 2 Nefi 21): 21u/590 también verificado (pages_1920/page_0125.png, confirmado a zoom) -- imprime "Exodo" sin tilde en la imagen, coincidiendo con la transcripción; confirmado. ACTUALIZACIÓN (2026-09-16, durante el `manual-proofread` de 2 Nefi 22): 22c/593 también verificado (mismo file 0125, confirmado a zoom) -- imprime "Exodo" sin tilde en la imagen, coincidiendo con la transcripción; confirmado. ACTUALIZACIÓN (2026-09-16, durante el `manual-proofread` de 2 Nefi 24): 24m/628 también verificado (pages_1920/page_0129.png, confirmado a zoom) -- imprime "Exodo" sin tilde en la imagen, coincidiendo con la transcripción; confirmado. ACTUALIZACIÓN (2026-09-19, durante el `manual-proofread` de Mosíah 12): 12r/1264 también verificado (pages_1920/page_0215.png, confirmado a zoom) -- imprime "Exodo" sin tilde en la imagen, coincidiendo con la transcripción; confirmado. ACTUALIZACIÓN (2026-09-19, durante el `manual-proofread` de Mosíah 13): 13d/1268 y 13g/1271 también verificados (pages_1920/page_0216.png, confirmado a zoom) -- ambos imprimen "Exodo" sin tilde en la imagen, coincidiendo con la transcripción; confirmados. Todas las apariciones de "Mosíah" en esta familia quedan ahora verificadas. Restan sin verificar: 7f/324, 7i/327, 7k/329, 14g/459 (todas en 2 Nefi). RECUENTO VERIFICADO (2026-10-16): `librodm_foot.txt` (Block 1) 12 "Exodo" / 2 "Éxodo"; Block 2 igual (12 / 2); ninguna en el cuerpo. Las 14 apariciones están ahora cotejadas contra la imagen: las 4 que quedaban pendientes (2 Nefi 7f/324, 7i/327, 7k/329, 14g/459) se revisaron el 2026-10-11 en el barrido de tildes en notas (detector de píxeles más hojas de contacto) y las cuatro imprimen "Exodo" sin tilde, como la transcripción. Sin cambios en el texto. Detalle: workspace/proofread-1920.md, sección "Footnote accent-variant sweep".
A5: 25 | B5: Versículos/Versiculos | C5: =COUNTIF(Errores!L:L,B5) | D5: Omni nota 1004 (1i); Mosíah nota 1338 (18c); Alma nota 2076 (17w); Alma nota 2493 (34k); Helamán nota 3372 (14s) | E5: corrige todos | J5: FAMILIA Versículos/Versiculos (acento inconsistente) -- la palabra "Versículos" (esdrújula, tilde obligatoria por RAE) aparece casi siempre con tilde en las citas del bloque de notas, y solo 8 veces sin ella. ENTRADA MAESTRA (2026-09-14, abierta durante el `manual-proofread` de 2 Nefi 9 tras encontrar que la nota 9i/366 imprime "Versículos 16, 26, 37, 46" CON tilde en la imagen (pages_1920/page_0101.png, confirmado a zoom) mientras que la transcripción tenía "Versiculos" sin tilde -- corregido ese caso puntual para igualar la imagen, en ambos bloques). Alcance (conteo bruto de 2026-09-14, SUPERADO -- véase el RECUENTO VERIFICADO de 2026-10-16 al final de esta entrada): `librodm_foot.txt` y `librodm.txt` 355-356 "Versículos" con tilde / 8 "Versiculos" sin tilde cada uno (`grep -n "\bVersiculos\b" librodm_foot.txt`) -- las 8 restantes sin verificar: II Nefi 9i/366 (con tilde en imagen, YA CORREGIDA arriba), Omni 1i/1004, Mosíah 18b/1337, Alma 14h/1978, Alma 17w/2076, Alma 21q/2191, Alma 30-2e/2419, Alma 34k/2493. Mismo fenómeno de fondo que [[FAMILIA Mosíah/Mosiah]] y [[FAMILIA Éxodo/Exodo]]: inconsistencia ortográfica del propio taller de imprenta de 1920 (o deslices de esta transcripción todavía no verificados imagen por imagen), no necesariamente errores puntuales. CLASIFICACIÓN: pendiente de determinar caso por caso -- la tilde es obligatoria por RAE en todos los casos, así que cualquier instancia que la imagen confirme sin tilde sería un error exclusivo de 1920 (o compartido con 1886, a verificar), y cualquier instancia donde la imagen SÍ la lleve (como 9i/366) es simplemente un desliz de esta transcripción. DECISIÓN (mismo criterio que las entradas Mosíah/Mosiah y Éxodo/Exodo): la transcripción corriente debe seguir leyendo cada aparición tal como se verifique contra su propia imagen durante el cotejo manual; en una futura versión `_cleaned`, normalizar todas a "Versículos" con tilde. Pendiente: una auditoría dedicada, imagen por imagen, de las 7 apariciones sin tilde restantes no se ha emprendido todavía (fuera del alcance de un solo capítulo) -- véase `workspace/proofread-1920.md`, sección "2 Nefi 9", para más detalle. RECUENTO VERIFICADO (2026-10-16; cada aparición cotejada contra la imagen el 2026-10-11/12 en el barrido de tildes en notas, hojas de contacto a 4x de todos los Versículo(s) de las notas): `librodm_foot.txt` (Block 1) "Versículos" 355 + "versículos" 1 / "Versiculos" 7; "Versículo" 371 + "versículo" 3 / "Versiculo" 3; Block 2 igual; ninguna en el cuerpo. Las 10 sin tilde, todas confirmadas en la impresión: Omni 1i (1004); Mosíah 18b (1337), 18c (1338), 18d (1339); Alma 17w (2076), 21q (2191), 30-2e (2419), 34k (2493), 60r (3082); Helamán 14s (3372; la transcripción tenía "Versículos", corregida a "Versiculos" el 2026-10-11 en el cotejo de tres OCR). Resultaron llevar tilde en la impresión (corregidas en la transcripción, retiradas de esta lista): 2 Nefi 9i (366, 2026-09-14), Éther 14e (4517, 2026-10-10), Alma 14h (1978, 2026-10-11, línea doblemente impresa; el editor vio la tilde). No se cuentan aquí las erratas registradas aparte: "Vérsiculo" (2 Nefi 21a, 570), "Versicúlo" (Éther 6n, 4388), "Versícúlos" (Alma 30y, 2413), "Vernículos" (Mosíah 23d, 1450) y las "Verículo(s)" sin "s". Resultado: la forma con tilde es el 98,6 % (730 de 740). Detalle: workspace/proofread-1920.md, sección "Footnote accent-variant sweep".
A6: 26 | B6: Véase/Vease | C6: =COUNTIF(Errores!L:L,B6) | D6: Jacob nota 818 (2o); Mosíah nota 1069 (1n); Mosíah nota 1095 (2v); Alma nota 1692 (4n); Mormón nota 4204 (8v) | E6: corrige todos | J6: FAMILIA Véase/Vease (acento inconsistente) -- la fórmula de remisión "Véase" (esdrújula, tilde obligatoria por RAE: vé-a-se) se imprime en las notas al pie de 1920 casi siempre con tilde, pero 49 veces sin ella ("Vease"/"vease"). ENTRADA MAESTRA (2026-09-23, abierta durante el `manual-proofread` de Alma 43 a partir de la nota 43d, "Vease b, Alma 31", confirmada contra la imagen, pages_1920/page_0386.png). Alcance (`librodm_foot.txt`): "Véase" 2146x + "véase" 8x con tilde, frente a "Vease" 48x + "vease" 1x sin tilde (~2%). Las formas sin tilde se agrupan sobre todo en un tramo continuo de páginas -- final de Palabras de Mormón y Mosíah 1-2 (notas 1039-1095, file pages 183-186) -- lo que apunta a un cajista o una tanda de composición concreta, no a una convención. Verificación: el texto OCR de Google del PDF de 1920 lee también "Vease" en esas páginas (google_text_1920/page_0183.txt-page_0186.txt: 3+4+6+7 apariciones) y una muestra a zoom (pages_1920/page_0185.png, notas Mosíah 1f/1g/1k/1l) confirma "Vease" sin tilde, tipo limpio. Los bloques 1 y 2 conservan la grafía impresa (Block 2 sustituye la letra por el número pero mantiene "Vease"). Apariciones (libro, clave de nota (número secuencial)): Jacob 2o (818); Palabras de Mormón 1n (1039), 1-2b (1053), 1-2c (1054), 1-2d (1055); Mosíah 1a (1056), 1c (1058), 1d (1059), 1e (1060), 1f (1061), 1g (1062), 1k (1066), 1l (1067), 1m (1068), 1n (1069), 1q (1072), 1r (1073), 2b (1075), 2c (1076), 2d (1077), 2e (1078), 2f (1079), 2l (1085), 2q (1090), 2r (1091), 2t (1093), 2u (1094), 2v (1095), 9a (1194), 9f (1199), 9g (1200), 11h (1231), 13h (1272), 13j (1274), 13k (1275), 21y (1421), 27k (1550); Alma 2t (1661), 4f (1684), 4n (1692), 4o (1693), 8x (1811), 11t (1877), 12-2k (1919), 17n (2067), 24j (2279), 37o (2569), 43d (2681); Mormón 8v (4204). Solo 43d y la muestra de la pág. 185 cotejadas contra imagen una a una; el resto se apoya en la transcripción + la lectura coincidente de Google. No incluye las variantes con tilde mal colocada ya registradas por separado ("Veáse", "Véasé"). CLASIFICACIÓN: inconsistencia ortográfica de imprenta de 1920 (tilde omitida), igual que "Versículos/Versiculos" y "Mosíah/Mosiah". DECISIÓN: preservar como se imprime en la transcripción; en la futura versión `_cleaned`, normalizar todas a "Véase"/"véase" con tilde. AMPLIACIÓN (2026-10-05, `manual-proofread` de Mormón 7): dos "Vease" más, notas Mormón 7d (4171, "Vease i, Mosíah 16") y 7h (4175, "Vease u, II Nefi 9"), página 568 (pages_1920/page_0590.png; el OCR de Google lee también "Vease" en ambas); la transcripción las había normalizado a "Véase" -- restauradas en librodm_foot.txt, en el bloque 2 de librodm.txt y en pages/page_568.txt. NUEVO RECUENTO en librodm_foot.txt: "Vease" 50x. AMPLIACIÓN (2026-10-05, `manual-proofread` de Mormón 8): nota Mormón 8j (4192, "Vease d, I Nefi 12"), página 569 (pages_1920/page_0591.png; Google lee "Vease"); restaurada en ambos bloques y en pages/page_569.txt. NUEVO RECUENTO: "Vease" 51x. RECUENTO VERIFICADO (2026-10-16): `librodm_foot.txt` (Block 1) "Véase" 2140 + "véase" 8 / "Vease" 54 + "vease" 1 (55 notas, ~2,5 %); Block 2 conserva la palabra y da las mismas cifras. Nuevas desde la última ampliación, halladas en el cotejo de tres OCR y el barrido de tildes (2026-10-11): Mosíah 9n (1207, "Vease k."), Alma 19m (2135, "Vease 2b, Alma 17"; la nota carece además de la etiqueta "m,", registrada aparte) y Alma 63n (3135, "Vease f.", la "e" dañada pero sin tilde). Se comprobó contra la imagen cada nota de la lista: el barrido de 2026-10-11 (detector de píxeles sobre todas las Véase/Vease de las notas; cada discrepancia o caso dudoso revisado a ojo en hojas de contacto) y la lectura completa de cada bloque de notas en el `manual-proofread`. No se incluyen las erratas registradas aparte ("Veáse", "Véasé") ni Jacob 5-2h (888), que imprime "Véasc": el editor dictaminó tipo roto (una "e" sin trazo), y la transcripción "Véase" se mantiene. Detalle: workspace/proofread-1920.md, sección "Footnote accent-variant sweep".
A7: 27 | B7: órdenes/ordenes | C7: =COUNTIF(Errores!L:L,B7) | D7: Alma 47:2; Alma 52:16; Alma 56:18 | E7: corrige todos | J7: FAMILIA órdenes/ordenes (acento inconsistente) -- ENTRADA MAESTRA (2026-09-23, abierta durante el `manual-proofread` de Alma 47). "órdenes" (esdrújula, tilde obligatoria por RAE) se imprime en 1920 SIN tilde 7 veces frente a 5 con ella: Alma 47:2, 47:3, 47:8, 47:16, 47:21 (cinco en un mismo capítulo, pages_1920/page_0400-0402.png), Alma 52:16 ("recibió ordenes") y Alma 56:18 ("ordenes de Ammorón"); las 7 confirmadas contra el OCR de Google del PDF de 1920. 1886 imprime "órdenes" CON tilde en todas sus 12 apariciones, incluidas las cinco de Alma 47 (file 392-394) -- ERROR EXCLUSIVO DE 1920. Con tilde en 1920: Jacob 5:72, Alma 61:15, III Nefi 3:3, 4:26, Mormón 2:17 (5 apariciones). DECISIÓN: preservar como se imprime en la transcripción; en la versión `_cleaned`, normalizar a "órdenes".
A8: 28 | B8: "vino á suceder"/"vino a suceder" | C8: =COUNTIF(Errores!L:L,B8) | D8: Mosíah 8:4; Mosíah 10:3; Alma 20:28; Alma 46:35; III Nefi 4:7 | E8: no informa | F8: 1946 no usa tilde en la preposición "a" en ninguna parte (norma de la RAE de 1911); no informa sobre la errata de 1920. Comprobado: 1 Nefi 13:10, 14:13, 16:14 y varias páginas sin ninguna "á". | J8: FAMILIA "vino á suceder"/"vino a suceder" (acento inconsistente) -- la fórmula narrativa "vino á suceder" (á + infinitivo, convención ortográfica de época) aparece 352 veces con tilde en librodm.txt frente a solo 5 sin ella. ENTRADA MAESTRA (2026-09-18, abierta durante el `manual-proofread` de Mosíah 7 tras notar Mosíah 8:4 "Y vino a suceder que después" sin tilde en la página 181, en un capítulo dominado por la forma acentuada). Alcance (conteo bruto, `grep -c "vino á suceder"` = 352 / `grep -n "vino a suceder\b"` = 5, las 5 identificadas por línea y verificada la referencia de capítulo/versículo vía las cabeceras CAPÍTULO/LIBRO DE más cercanas): Mosíah 8:4 (línea 8446, verificado a zoom en pages_1920/page_0203.png -- tipo limpio, "a" genuinamente sin tilde; 1886 en este lugar exacto, pages_1886/page_0197.png, book page 179/file 197, imprime IGUALMENTE "vino a suceder" sin tilde -- ERROR COMPARTIDO CON 1886 para esta instancia, heredado, no introducido en 1920), Mosíah 10:3 (línea 8635, verificado a zoom en pages_1920/page_0207.png -- "a" genuinamente sin tilde; 1886 en este lugar exacto, pages_1886/page_0201.png, book page 185/file 201, imprime IGUALMENTE "vino a suceder" sin tilde -- ERROR COMPARTIDO CON 1886 también en esta instancia), Alma 20:28 (línea 13582), Alma 46:35 (línea 16957), III Nefi 4:7 (línea 21942) -- estas últimas 3 sin verificar aún contra su propia imagen. Mismo fenómeno de fondo que [[FAMILIA Mosíah/Mosiah]], [[FAMILIA Éxodo/Exodo]] y [[FAMILIA Versículos/Versiculos]]: inconsistencia ortográfica del propio taller de imprenta de 1920 (las dos instancias verificadas hasta ahora, Mosíah 8:4 y 10:3, comparten el error con 1886, así que las demás podrían tampoco ser exclusivas de 1920, pero esto no se puede afirmar sin cotejar cada imagen). CLASIFICACIÓN: pendiente de determinar caso por caso -- Mosíah 8:4 y 10:3 verificados (ambos compartidos con 1886); las 3 restantes no verificadas contra imagen. DECISIÓN (mismo criterio que las entradas Mosíah/Mosiah, Éxodo/Exodo y Versículos/Versiculos): la transcripción corriente debe seguir leyendo cada aparición tal como se verifique contra su propia imagen durante el cotejo manual; en una futura versión `_cleaned`, normalizar todas a "vino á suceder" con tilde. Pendiente: verificar imagen por imagen las 3 apariciones restantes (Alma 20:28, Alma 46:35, III Nefi 4:7) cuando el `manual-proofread` llegue a esos capítulos -- véase `workspace/proofread-1920.md`, sección "Mosíah 7", para más detalle. ACTUALIZACIÓN (2026-09-21, durante el `manual-proofread` de Alma 20): Alma 20:28 también verificado (pages_1920/page_0322.png, confirmado a zoom) -- "a" genuinamente sin tilde; 1886 en este lugar exacto (pages_1886/page_0314.png, book page 296/file 314) imprime IGUALMENTE "Y vino a suceder" sin tilde -- ERROR COMPARTIDO CON 1886, tercera instancia verificada de tres, las tres compartidas con 1886 hasta ahora. Restan sin verificar: Alma 46:35, III Nefi 4:7.
A9: 84 | B9: acento agudo espurio | C9: =COUNTIF(Errores!L:L,B9) | D9: 2 Nefi 5:24; 2 Nefi 26:27; Alma 1:1; Alma 56:56; Éther 3:3 | E9: corrige todos | J9: FAMILIA acento agudo espurio (tilde donde ninguna época del español la lleva) -- ENTRADA MAESTRA (2026-09-09, hallada en la auditoría de permitted words.txt). 1920 imprime una tilde aguda sobre palabras que nunca la han llevado (ni por regla actual, ni histórica, ni de diccionario). 12 apariciones, todas ÚNICAS (1x, salvo donde se indica) y confirmadas a zoom como impresas así en 1920, frente a la forma correcta sin tilde, dominante en la propia edición: "sútil" (2 Nefi 5:24; "sutil" 3x en 1920; pág. 73; 1886 pages_1886/page_0091.png imprime "sutil" correcto -> exclusiva de 1920); "ciélo" (2 Nefi 25:12; "cielo" 150x; pág. 109); "grácias" (2 Nefi 9:52, "dad grácias á su santo nombre"; "gracias" en el resto; pág. 84); "álguien" (2 Nefi 26:27; "alguien" 12x, y SIN tilde en los vv.25 y 28 de la misma página; pág. 114); "íra" (Jacob 1:8; "ira" 261x, y "ira" SIN tilde en el v.7 inmediatamente anterior; pág. 131); "íba" (Mosíah 11:20; "iba" 103x; pág. 189); "habríaís" (Mosíah 20:14; tilde extra sobre la "ís" final; correcto "habríais"; pág. 209); "lós" (Alma 56:56; artículo "los" 5054x; pág. 411); "áscuas" (III Nefi 22:16 = Isaías 54:16; "ascuas"; pág. 536) -- esta última COMPARTIDA CON 1886 (pages_1886/page_0550.png imprime igualmente "áscuas"); "Quíen" (2 Nefi 8:12 = Isaías 51:12, "¿Quíen eres tú" -- tilde sobre la "i" en vez de la "e"; "Quién" ~90x en el resto del documento; pág. 77) -- también COMPARTIDA CON 1886 (pages_1886/page_0095.png imprime igualmente "¿Quíen eres tú"; confirmado a zoom en 1920, pages_1920/page_0099.png); "lá" (Alma 1:1, "quién pugnó lá buena batalla"; "la" artículo, jamás con tilde; pág. 235; confirmado a zoom en pages_1920/page_0257.png -- tipo limpio; 1886 en este lugar exacto, pages_1886/page_0250.png, book page 232/file 250, imprime "pugnó la buena batalla" sin tilde -> exclusiva de 1920; hallada 2026-09-21 durante el `manual-proofread` de Alma 21, al buscar otras apariciones de la misma grafía); "lá" (Alma 21:9, "y lá expiación de su sangre"; pág. 302; confirmado a zoom en pages_1920/page_0324.png -- tipo limpio; 1886 en este lugar exacto, pages_1886/page_0316.png, book page 298/file 316, imprime "la expiacion de su sangre" sin tilde -> exclusiva de 1920; segunda instancia independiente de la misma grafía "lá", hallada en la misma sesión). El fenómeno de tildes agudas espurias existe TAMBIÉN en 1886 (p.ej. "léjos", "cáusa" en su pág. 532; "cáusa" también en su 1 Nefi 21:7), en lugares parcialmente distintos; cotejadas con 1886 hasta ahora: "áscuas", "Quíen" y "ciélo" (compartidas, heredadas -- "ciélo" añadida 2026-09-16 durante el `manual-proofread` de 2 Nefi 25: 1886 pages_1886/page_0125.png, book page 107, imprime igualmente "el Padre del ciélo y de la tierra" con la misma tilde espuria, confirmado a zoom en ambas ediciones), "sútil" (exclusiva de 1920); las demás confirmadas en 1920 pero no cotejadas individualmente (deslices tipográficos aislados, no una convención). Atestiguación externa: CERO -- ninguna de estas formas con tilde aparece en Quijote / Reina-Valera 1909 NT / Reina-Valera Biblia completa. NO es una variante ortográfica de época legítima (a diferencia de "jóven", "fué", "vió", que sí lo son): son palabras que jamás han llevado tilde. CLASIFICACIÓN: desliz tipográfico de acentuación (de época), no variante. -> _cleaned: suprimir la tilde espuria en las 10 (moviéndola a la posición correcta en el caso de "Quíen" -> "Quién", ya que ahí sí corresponde una tilde, solo que en la vocal equivocada). Preservado como se imprime en librodm_transcribed. AMPLIACIÓN (2026-10-01, `manual-proofread` de Helamán 10): tilde MAL COLOCADA en el gerundio "diciéndole(s)", impreso "dicíendole(s)" con la tilde sobre la "i" en vez de la "e" (mismo tipo que "Quíen"), 4 apariciones, todas confirmadas en el OCR de Google de 1920: Mosíah 22:3 "dicíendole" (pág. 214; pages_1920/page_0236.png; 1886 sin cotejar), Alma 14:14 "dicíendoles" (pág. 279; page_0302.png; 1886 pages_1886/page_0295.png, book page 277, imprime "diciéndoles" -> exclusiva de 1920), Helamán 10:14 "dicíen-/doles" (pág. 463; page_0485.png, confirmado a zoom: la "i" lleva trazo agudo, no punto; 1886 file 478, book page 460, "diciéndoles", según la nota de Session A -> exclusiva de 1920; la transcripción tenía "diciendoles" sin tilde y se corrigió a lo impreso), y III Nefi 3:15 "dicíendoles" (ya registrada por separado). "diciéndoles" correcto aparece 28 veces. -> _cleaned: "diciéndole(s)". AMPLIACIÓN (2026-10-02, `manual-proofread` de Helamán 13): Helamán 13:32 "porque ya os tenéis encíma vuestra desolación" (pág. 472; pages_1920/page_0494.png, tilde aguda limpia sobre la "i", confirmada a zoom y en el OCR de Google "encíma"; 1886 pages_1886/page_0487.png, book page 469, imprime "encima" -> exclusiva de 1920; "encima" sin tilde en el resto de librodm.txt; la transcripción lo había corregido en silencio y se restauró). AMPLIACIÓN (2026-10-08, `manual-proofread` de Éther 3): Éther 3:3 "áños" -- "nos has hecho caminar por el desierto estos áños", página 582 (pages_1920/page_0604.png), con una tilde aguda bien formada sobre la "a" (misma forma que las demás "á" de la página; el OCR de Google la omite: "años"); 1886 (file 596) "estos años" -> exclusiva de 1920. La transcripción tenía "años"; restaurado a "áños" en librodm.txt y pages/page_582.txt. AMPLIACIÓN (2026-10-11, comprobación OCR a tres bandas): Alma 2:23 "dé los Nefitas" -- "retornaron al campo dé los Nefitas con gran apuro", página 241 (pages_1920/page_0263.png), con tilde bien formada sobre la preposición "de" (comparada con un "de" sin tilde de la misma página); Google y Tesseract leen también "dé"; 1886 (file 256) "de los Nefitas" -> exclusiva de 1920. La transcripción ya tenía "dé". AMPLIACIÓN (2026-10-11, comprobación OCR a tres bandas, índice): Índice página viii "Señales del Cristo, nacimiento y muerté 112" -- tilde aguda sobre la "e" final de "muerte" (pages_1920/page_0016.png), de la misma forma que la de "José" en la misma página; Google y Tesseract leen también "muerté". La transcripción lo había corregido en silencio a "muerte"; restaurado a "muerté".
A10: 85 | B10: "él" por "el" | C10: =COUNTIF(Errores!L:L,B10) | D10: 1 Nefi 7:5; Omni 1:19; Alma 45:4; IV Nefi 1:19; Moroni 8:14 | E10: corrige todos | J10: FAMILIA "él" por "el" (artículo acentuado como pronombre ante "de"/"que") -- ENTRADA MAESTRA (2026-09-23, abierta durante el `manual-proofread` de Alma 43; consolida las entradas antes sueltas de Alma 40:6, Mormón 6:21 y Éther 12:38). 1920 imprime sistemáticamente con tilde el ARTÍCULO "el" cuando va ante "de"/"del" (sustantivo elidido: "mayor que él de los Nefitas" = "mayor que el [número] de los Nefitas"; "y él de su familia" = "y el [corazón] de su familia") o ante el relativo "que" ("en él que" = "en el que", "él que busque, halla" = "el que busque, halla", aposición "José, él que fué llevado"). Según la RAE (tilde diacrítica: "él" pronombre personal tónico / "el" artículo átono), en todas estas posiciones corresponde "el" SIN tilde; la forma con tilde leída literalmente significa "él" (he/him), lo que rompe la gramática. Clasificación del editor (2026-09-23): "gringismo" -- error de un hablante de español como segunda lengua (probable calco de "he that..." / "that of..." del inglés), no una variante de época: no se halló ninguna fuente normativa ni histórica que lo avale, y la ortografía académica del siglo XIX ya distinguía "él"/"el". Alcance: 156 apariciones en el cuerpo de librodm.txt (ninguna en los bloques de notas), frente a 0 apariciones del artículo sin tilde en estas mismas construcciones ("el de " 0x; "en el que" 0x; los únicos "el que" sin tilde son del tipo nominalizador "el que + subjuntivo", p.ej. "me aflige el que se levanten", construcción distinta). Excluidas deliberadamente ~29 apariciones de "él" que SÍ son pronombre personal correcto ("hizo él que", "sabía él que", "mandóles él que", "deseando de él que", "contra él de la manera", "trataba él de destruir", etc.). Verificación: las 156 confirmadas independientemente contra el texto OCR de Google del PDF de 1920 (google_text_1920/), que lee "él" en todas; imágenes cotejadas a zoom en Alma 43:21 (pages_1920/page_0387.png) y Alma 62:6 (page_0449.png). 1886: el texto OCR del PDF de 1886 (localizado por página vía chapter_map.csv) lee "el" sin tilde en ~141 de las 156 posiciones; ~5 las lee con tilde (1 Nefi 7:5, Mosíah 18:27, III Nefi 4:17, III Nefi 29:7, Mormón 9:17 -- sin verificar contra imagen) y el resto quedan indeterminadas (redacción distinta u OCR ilegible). Conteo global en 1886: "en el que" 22x vs "en él que" 1x; "mayor que el de" 4x vs 0x. Imagen de 1886 cotejada en Alma 40:6 y 40:9 (pages_1886/page_0371.png: "y el de la resurreccion" en ambos -- corrige la entrada suelta anterior de Alma 40:6, que decía "él de en 1886"), Alma 43:21 (page_0380.png, "el de los Nefitas") y Alma 62:6 (page_0442.png, "el de los partidarios"). Conclusión: la forma con tilde es, en esencia, EXCLUSIVA DE 1920; 1886 usa el artículo correcto. Edición moderna en español (churchofjesuschrist.org, cotejada 2026-09-23): Alma 43:21 "mucho mayor que el de los nefitas"; Alma 40:6 "y el de la resurrección"; Éter 12:38 y Alma 62:6 reformulados sin la construcción. Subgrupo dudoso (anotado, no excluido): las preguntas "¿Quién es él que...?" (Alma 11:32; Mormón 9:16, 9:17, 9:26 x3) y 1 Nefi 10:8 "Sí, él que iría clamando" admiten una lectura forzada como pronombre ("¿quién es él, el que...?"), pero calcan literalmente el inglés "who is he that..." y el español normativo escribe "¿Quién es el que...?" -- incluidas en el recuento por decisión del editor. Apariciones (libro capítulo:versículo; "(xN)" = varias en el mismo versículo): Testimonio de los Tres Testigos pág. v; 1 Nefi 1:9, 3:2, 4:7, 7:5, 8:26, 10:8, 10:19, 13:32, 14:5, 14:10, 15:30, 18:21, 22:19, 22:20; 2 Nefi 1:27, 3:4, 3:7, 3:24, 4:1, 10:13, 10:25, 13:9, 15:14, 17:2, 20:15, 20:20, 24:3, 24:6, 28:28, 31:15; Jacob 1:4, 2:6, 5:43; Enós 1:27; Omni 1:19; Mosíah 3:27, 13:5, 18:27, 21:28, 23:12; Alma 3:16, 3:17, 5:36, 7:5, 7:21, 8:18, 9:21 (x2), 11:32, 17:3, 17:18, 18:35, 22:31, 22:33, 24:1 (x2), 24:26, 25:13 (x2), 26:22, 27:22, 30:5, 30:34, 31:12, 32:16, 32:19 (x2), 35:8, 38:2, 38:9, 40:6, 40:9, 43:21, 49:26, 50:35, 50:37, 51:29, 61:9, 62:6; Helamán 1:9, 3:3, 6:8, 6:9, 6:10 (x2), 6:28, 6:29, 8:16, 8:18, 8:27, 11:21, 13:18, 14:4, 14:8, 14:30 (x2), 16:10, 16:21; III Nefi 1:17, 2:15, 4:17, 11:8, 11:40, 12:22, 14:8, 14:21, 18:7, 24:18 (x2), 26:5, 27:11, 27:17, 27:29, 29:7; IV Nefi 1:19; Mormón 2:9, 2:13, 3:20, 6:21 (x2), 7:7, 8:19, 8:28 (x2), 8:30, 8:31, 9:2, 9:14, 9:16, 9:17, 9:23 (x2), 9:26 (x3); Éther 1:4, 2:2, 2:10, 4:8 (x2), 4:10, 4:12, 4:16, 4:18 (x2), 4:19, 7:3, 9:25, 11:15, 12:38, 13:30, 15:8; Moroni 8:14, 8:22 (x2). AMPLIACIÓN (2026-09-23, `manual-proofread` de Alma 45, a partir de Alma 45:4 "¿Crees tú en Jesu Cristo, Él que ha de venir?"): la misma construcción aparece también con MAYÚSCULA ("Él que…"), casi siempre referida a la Deidad o a inicio de oración -- no captada por el recuento inicial (solo minúscula). 29 apariciones adicionales de artículo/antecedente de relativo: 1 Nefi 8:27, 12:6, 21:5, 21:10; 2 Nefi 8:9, 8:10 (x2), 24:6, 25:18; Jacob 2:15; Mosíah 2:21, 2:25; Alma 5:48, 36:2, 38:6, 45:4; Helamán 5:26, 8:14; III Nefi 20:39, 22:10, 25:6; Mormón 6:22, 7:5; Éther 1:6, 2:12, 3:14, 4:8, 4:10, 4:12 (p.ej. "yo soy Él que habla" = "yo soy el que habla"; "¿No eres Tú Él que cortó á Rahab?"). La mayúscula de reverencia no cambia la función: sigue siendo el artículo "el" de "el que" (la edición moderna escribe "el que"/"aquel que"). Excluidas 11 apariciones de "Él" mayúscula que SÍ son pronombre ("no permitirá Él que", "dispertóles Él de", "ante Él de que", "nada en Él que nos le pueda hacer deseable", "acuérdase Él de", "partio Él de entre ellos", etc.). Las 29 confirmadas contra el OCR de Google o, donde Google omitió la tilde de la mayúscula (Alma 5:48, Mormón 6:22, 7:5, Éther 4:12), contra la imagen de 1920 directamente (pages_1920/page_0273, 0589, 0590, 0608.png: "Él" con tilde en las cuatro). Además, dos casos del artículo acentuado ANTE SUSTANTIVO (la forma más clara del error): Mosíah 12:24 "24. Él Señor ha desnudado su santo brazo" (Isaías 52:10; página 192; COMPARTIDO CON 1886 -- el OCR de 1886, file 208, lee también "él señor"; la cita paralela de Mosíah 15:31 imprime correctamente "El Señor" en ambas ediciones) y III Nefi 22:10 "dice Él Señor, Él que tiene misericordia de ti" (Isaías 54:10; página 536; 1886 file 550 lee "dice el señor el que tiene" -- exclusivo de 1920). Cotejo 1886 de las 29 mayúsculas (OCR del PDF de 1886, localizado por página vía chapter_map.csv): 20 leen "el" sin tilde (p.ej. Alma 45:4, imagen confirmada en pages_1886/page_0386.png: "¿Crées tú en Jesu-Cristo, el que ha de venir?"; la edición moderna reformula: "¿Crees en Jesucristo, que ha de venir?"); 6 las lee con tilde (1 Nefi 12:6, 2 Nefi 24:6, Jacob 2:15, Alma 5:48, 36:2, Helamán 8:14 -- sin verificar contra imagen); 3 indeterminadas (Mosíah 2:21, 2:25, Éther 1:6). Decisión del editor (2026-09-23): registrar TODAS las "Él" mayúsculas de la lista igual que las minúsculas. TOTAL DE LA FAMILIA: 156 + 29 + 2 = 187 apariciones. DECISIÓN: preservar TODAS tal como se imprimen en librodm.txt (convención del proyecto: el texto de 1920 no se corrige); en la futura versión `_cleaned`, normalizar a "el" sin tilde. Detalle en `workspace/proofread-1920.md`, sección "Alma 43". AMPLIACIÓN (2026-09-27, `manual-proofread` de Helamán 3): tercer caso del artículo acentuado ANTE SUSTANTIVO -- Helamán 3:2 "no hubo ninguna disensión entre el pueblo en él / año cuadragésimo-cuarto" (página 438, file 460; "él" a final de renglón y "año" al comienzo del siguiente, por lo que escapó al recuento inicial, que buscaba la construcción dentro del renglón; confirmado en la imagen y en el OCR de Google; 1886 file 453 "en el año" -> exclusivo de 1920). Barrido de comprobación de los demás "él" a final de renglón ante "que/de/del/año": los 11 restantes ya estaban en la lista o son pronombre (Alma 25:11 "lo que quería decir él de que muchos sufrirían" = "what he meant", pronombre, excluido). TOTAL DE LA FAMILIA: 188 apariciones. AMPLIACIÓN (2026-10-04, `manual-proofread` de III Nefi 28): III Nefi 28:35 "Y mejor le hubiera sido él no haber nacido" (pág. 547, pages_1920/page_0569.png) -- artículo que sustantiva el infinitivo ("el no haber nacido"); 1886 (file 561) imprime "mejor le hubiera sido el no haber nacido" -> EXCLUSIVA DE 1920; no estaba en la lista. NUEVO TOTAL DE LA FAMILIA: 189 apariciones. AMPLIACIÓN (2026-10-10, `manual-proofread` de Éther 12): primer caso EN NOTA (la entrada decía "ninguna en los bloques de notas") -- nota q de Éther 12 (Block 1 librodm_foot.txt 12q = 4478 en Block 2 de librodm.txt): "Sin duda el idioma en él que escribió el hermano de Jared fué más perfecto" (= "en el que"; pág. 604, pages_1920/page_0626.png; OCR de Google "en él que"); 1886 no tiene notas. Preservado como se imprime; en _cleaned, "el".
A11: 86 | B11: "país X" sin "de" | C11: =COUNTIF(Errores!L:L,B11) | D11: 1 Nefi 17:6; Alma 22:33; Alma 27:22; Alma 27:24; Alma 51:32 | E11: mixto | F11: todos tiene de menos 1 Nefi. Mosíah 10:7 y Alma 46:17 también con "de"; Alma 23:12 no es instancia (1920 ya tiene "país de Shemlon"). | J11: FAMILIA "país X" sin "de" (aposición directa por "país de X" ante nombre propio de lugar) -- ENTRADA MAESTRA (2026-09-24, abierta durante el `manual-proofread` de Alma 51, a partir de Alma 51:32 "sobre los limites del país Abundancia"). En español normativo -- tanto en el siglo XIX como hoy -- el sustantivo clasificador "país"/"tierra"/"ciudad"/"reino" se une al nombre propio del lugar mediante "de" ("la ciudad de Roma", "el reino de Castilla"; Reina-Valera escribe siempre "la tierra de Canaán"); la aposición directa sin "de" es normal solo con ciertas clases de nombres (ríos y montes: "el río Jordán", "el monte Sión", y en esta misma obra "el río Sidón"), no con "país". Las formas sin "de" coinciden exactamente con los nombres que en inglés carecen de "of" ("the land Bountiful", "the land Desolation", "the land Jershon" frente a "the land of Zarahemla"), por lo que se clasifican como calco literal del inglés -- mismo tipo de "gringismo" que la FAMILIA "él" por "el" --, no como variante de época. Los propios traductores escriben mayoritariamente la forma con "de" para los mismos lugares. Apariciones en el cuerpo de librodm.txt (9): país Abundancia -- 1 Nefi 17:6, Alma 22:33, Alma 27:22 (x2), Alma 51:32 (frente a 18 "país de Abundancia"); país Jershon -- Alma 27:22, Alma 27:24 (frente a 15 "país de Jershon"); país Desolación -- Alma 46:17 (frente a 6 "país de Desolación"); país Shemlon -- Mosíah 10:7 (frente a 1 "país de Shemlon", Alma 23:12). Además, en el índice: "El país Desolación y el país Abundancia" y "Toma del país Desolación". Recuentos hechos sin distinguir mayúsculas y abarcando saltos de línea y marcadores de nota. 1886: el texto OCR del PDF de 1886 da exactamente el mismo reparto en los mismos lugares (Abundancia 18 con "de" / 5 sin él + 1 en el índice; Jershon 15/2; Desolación 6/1 + 2 en el índice; Shemlon 1/1) -> COMPARTIDO CON 1886, heredado, no introducido en 1920. DECISIÓN DEL EDITOR (2026-09-24): preservar TODAS tal como se imprimen en librodm.txt; en la futura versión `_cleaned`, insertar "de" en las 9 del cuerpo (y en las del índice) para uniformar la forma de los nombres de lugar en todo el texto, siguiendo la forma mayoritaria. Detalle en `workspace/proofread-1920.md`, sección "Alma 51".
